Workbook
Name StartYear: Inputs!$B$6
Name IraStartAge: Inputs!$D$4
Name CarolStartAge: Inputs!$D$5
Name StartAfterTax: Inputs!$B$9
Name StartIRA: Inputs!$B$10
Name StartRoth: Inputs!$B$11
Name SSMonthly: Inputs!$B$14
Name SSAnnual: Inputs!$D$14
Name StartExpenses: Inputs!$B$15
Name ExpenseInflation: Inputs!$B$18
Name SSCOLA: Inputs!$B$19
Name ReturnAfterTax: Inputs!$B$20
Name ReturnIRA: Inputs!$B$21
Name ReturnRoth: Inputs!$B$22
Name DiscountRate: Inputs!$B$23
Name StdDeduction: Inputs!$B$28
Name TaxBracketInflation: Inputs!$B$29
Name ILTaxRate: Inputs!$B$30
Name CapGainsPct: Inputs!$B$31
Name NIITThreshold: Inputs!$B$32
Name MAGI2024: Inputs!$B$35
Name MAGI2025: Inputs!$B$36
Name DeathAge: Inputs!$B$39
Name SurvivorSS: Inputs!$B$40
Name StdDeductionSingle: Inputs!$B$45
Name NIITThresholdSingle: Inputs!$B$46
Name HeirTaxRate: Inputs!$P$6
Name RothConvTable: Inputs!$F$5:$G$34
Name OtherIncomeTable: Inputs!$I$5:$J$34
Name DiscretionaryTable: Inputs!$L$5:$M$34
Name RMDTable: Inputs!$A$50:$B$93
Name IRMAATableMFJ: Inputs!$D$50:$E$55
Name IRMAATableSingle: Inputs!$G$50:$H$55
Name IRMAA_MFJ_Thresh1: Inputs!$D$50
Name IRMAA_MFJ_Thresh2: Inputs!$D$51
Name IRMAA_MFJ_Thresh3: Inputs!$D$52
Name IRMAA_MFJ_Thresh4: Inputs!$D$53
Name IRMAA_MFJ_Thresh5: Inputs!$D$54
Name IRMAA_MFJ_Cost1: Inputs!$E$50
Name IRMAA_MFJ_Cost2: Inputs!$E$51
Name IRMAA_MFJ_Cost3: Inputs!$E$52
Name IRMAA_MFJ_Cost4: Inputs!$E$53
Name IRMAA_MFJ_Cost5: Inputs!$E$54
Name IRMAA_MFJ_Cost6: Inputs!$E$55
Name IRMAA_Single_Thresh1: Inputs!$G$50
Name IRMAA_Single_Thresh2: Inputs!$G$51
Name IRMAA_Single_Thresh3: Inputs!$G$52
Name IRMAA_Single_Thresh4: Inputs!$G$53
Name IRMAA_Single_Thresh5: Inputs!$G$54
Name IRMAA_Single_Cost1: Inputs!$H$50
Name IRMAA_Single_Cost2: Inputs!$H$51
Name IRMAA_Single_Cost3: Inputs!$H$52
Name IRMAA_Single_Cost4: Inputs!$H$53
Name IRMAA_Single_Cost5: Inputs!$H$54
Name IRMAA_Single_Cost6: Inputs!$H$55
Name LowRiskReturn: Inputs!$P$9
Name ModRiskReturn: Inputs!$P$10
Name HighRiskReturn: Inputs!$P$11
Name LowRiskTarget: Inputs!$P$12
Name ModRiskTarget: Inputs!$P$13

Sheet Inputs
A1: RETIREMENT PLANNING MODEL - IRA & CAROL
A3: PERSONAL INFORMATION | F3: ROTH CONVERSIONS | I3: OTHER INCOME | L3: DISCRETIONARY W/D | O3: HEIR TAX PARAMETERS
A4: Ira's Birth Date: | B4: Feb 17, 1955 | C4: Age in 2026: | D4: 71 | F4: Year | G4: Amount | I4: Year | J4: Amount | L4: Year | M4: Amount | O4: Heirs' Fed Tax Rate: | P4: 0.37
A5: Carol's Birth Date: | B5: Jul 17, 1954 | C5: Age in 2026: | D5: 72 | F5: =StartYear+0 | G5: 700000 | I5: =StartYear+0 | J5: 0 | L5: =StartYear+0 | M5: 0 | O5: Heirs' State Tax Rate: | P5: 0.0495
A6: Starting Year: | B6: 2026 | F6: =StartYear+1 | G6: 700000 | I6: =StartYear+1 | J6: 0 | L6: =StartYear+1 | M6: 0 | O6: Combined Heir Rate: | P6: =P4+P5
F7: =StartYear+2 | G7: 0 | I7: =StartYear+2 | J7: 0 | L7: =StartYear+2 | M7: 0
A8: STARTING ACCOUNT BALANCES | F8: =StartYear+3 | G8: 0 | I8: =StartYear+3 | J8: 0 | L8: =StartYear+3 | M8: 0 | O8: RISK ALLOCATION
A9: Joint After-Tax Account: | B9: 474000 | F9: =StartYear+4 | G9: 0 | I9: =StartYear+4 | J9: 0 | L9: =StartYear+4 | M9: 0 | O9: Low Risk Return: | P9: 0.04
A10: Combined Traditional IRA: | B10: 6121000 | F10: =StartYear+5 | G10: 0 | I10: =StartYear+5 | J10: 0 | L10: =StartYear+5 | M10: 0 | O10: Moderate Risk Return: | P10: 0.06
A11: Combined Roth IRA: | B11: 2612000 | F11: =StartYear+6 | G11: 0 | I11: =StartYear+6 | J11: 0 | L11: =StartYear+6 | M11: 0 | O11: High Risk Return: | P11: 0.08
F12: =StartYear+7 | G12: 0 | I12: =StartYear+7 | J12: 0 | L12: =StartYear+7 | M12: 0 | O12: Low Risk Target $: | P12: 474000
A13: SOCIAL SECURITY | F13: =StartYear+8 | G13: 0 | I13: =StartYear+8 | J13: 0 | L13: =StartYear+8 | M13: 0 | O13: Moderate Risk Target $: | P13: 6121000
A14: Monthly (2026): | B14: 5800 | C14: Annual: | D14: =B14*12 | F14: =StartYear+9 | G14: 0 | I14: =StartYear+9 | J14: 0 | L14: =StartYear+9 | M14: 0 | O14: High Risk Target $: | P14: (Remainder)
A15: Starting Annual Expenses: | B15: 180000 | F15: =StartYear+10 | G15: 0 | I15: =StartYear+10 | J15: 0 | L15: =StartYear+10 | M15: 0
F16: =StartYear+11 | G16: 0 | I16: =StartYear+11 | J16: 0 | L16: =StartYear+11 | M16: 0 | O16: Use Blended Returns: | P16: No | Q16: (Yes/No)
A17: RATES & ASSUMPTIONS | F17: =StartYear+12 | G17: 0 | I17: =StartYear+12 | J17: 0 | L17: =StartYear+12 | M17: 0
A18: Expense Inflation Rate: | B18: 0.03 | F18: =StartYear+13 | G18: 0 | I18: =StartYear+13 | J18: 0 | L18: =StartYear+13 | M18: 0
A19: Social Security COLA: | B19: 0.025 | F19: =StartYear+14 | G19: 0 | I19: =StartYear+14 | J19: 0 | L19: =StartYear+14 | M19: 0
A20: After-Tax Account Return: | B20: 0.04 | F20: =StartYear+15 | G20: 0 | I20: =StartYear+15 | J20: 0 | L20: =StartYear+15 | M20: 0
A21: Traditional IRA Return: | B21: 0.06 | F21: =StartYear+16 | G21: 0 | I21: =StartYear+16 | J21: 0 | L21: =StartYear+16 | M21: 0
A22: Roth IRA Return: | B22: 0.08 | F22: =StartYear+17 | G22: 0 | I22: =StartYear+17 | J22: 0 | L22: =StartYear+17 | M22: 0
A23: Discount Rate (for PV): | B23: 0.03 | F23: =StartYear+18 | G23: 0 | I23: =StartYear+18 | J23: 0 | L23: =StartYear+18 | M23: 0
F24: =StartYear+19 | G24: 0 | I24: =StartYear+19 | J24: 0 | L24: =StartYear+19 | M24: 0
A25: TAX PARAMETERS | F25: =StartYear+20 | G25: 0 | I25: =StartYear+20 | J25: 0 | L25: =StartYear+20 | M25: 0
A26: Standard Deduction (2024 base): | B26: 29200 | F26: =StartYear+21 | G26: 0 | I26: =StartYear+21 | J26: 0 | L26: =StartYear+21 | M26: 0
A27: Senior Bonus (both 65+): | B27: 3100 | F27: =StartYear+22 | G27: 0 | I27: =StartYear+22 | J27: 0 | L27: =StartYear+22 | M27: 0
A28: Total Std Deduction (base): | B28: =B26+B27 | F28: =StartYear+23 | G28: 0 | I28: =StartYear+23 | J28: 0 | L28: =StartYear+23 | M28: 0
A29: Tax Bracket Inflation: | B29: 0.025 | F29: =StartYear+24 | G29: 0 | I29: =StartYear+24 | J29: 0 | L29: =StartYear+24 | M29: 0
A30: IL State Tax Rate: | B30: 0.0495 | F30: =StartYear+25 | G30: 0 | I30: =StartYear+25 | J30: 0 | L30: =StartYear+25 | M30: 0
A31: Cap Gains % of After-Tax: | B31: 0.75 | F31: =StartYear+26 | G31: 0 | I31: =StartYear+26 | J31: 0 | L31: =StartYear+26 | M31: 0
A32: NIIT Threshold (2024 base): | B32: 250000 | F32: =StartYear+27 | G32: 0 | I32: =StartYear+27 | J32: 0 | L32: =StartYear+27 | M32: 0
F33: =StartYear+28 | G33: 0 | I33: =StartYear+28 | J33: 0 | L33: =StartYear+28 | M33: 0
A34: IRMAA - PRIOR YEAR MAGI | F34: =StartYear+29 | G34: 0 | I34: =StartYear+29 | J34: 0 | L34: =StartYear+29 | M34: 0
A35: 2024 MAGI (for 2026 IRMAA): | B35: 600000
A36: 2025 MAGI (for 2027 IRMAA): | B36: 600000
A38: SURVIVOR SCENARIO
A39: Ira's Death Age (blank=none): | C39: (e.g., 85)
A40: Survivor SS (Monthly, 2026): | B40: 3860 | C40: (escalates to death year)
A42: SINGLE FILER PARAMETERS
A43: Std Deduction (Single, 2024): | B43: 14600
A44: Senior Bonus (Single 65+): | B44: 1950
A45: Total Single Std Ded (base): | B45: =B43+B44
A46: NIIT Threshold (Single): | B46: 200000
A48: RMD TABLE | D48: IRMAA TABLE (2024 MFJ) | G48: IRMAA TABLE (2024 Single)
A49: Age | B49: Dist Period | D49: MAGI Up To | E49: Annual Cost | G49: MAGI Up To | H49: Annual Cost
A50: 72 | B50: 27.4 | D50: 206000 | E50: 0 | G50: 103000 | H50: 0
A51: 73 | B51: 26.5 | D51: 258000 | E51: 1987 | G51: 129000 | H51: 994
A52: 74 | B52: 25.5 | D52: 322000 | E52: 4992 | G52: 161000 | H52: 2496
A53: 75 | B53: 24.6 | D53: 386000 | E53: 7999 | G53: 193000 | H53: 4000
A54: 76 | B54: 23.7 | D54: 750000 | E54: 11004 | G54: 500000 | H54: 5502
A55: 77 | B55: 22.9 | D55: 99999999 | E55: 12007 | G55: 99999999 | H55: 6004
A56: 78 | B56: 22
A57: 79 | B57: 21.1
A58: 80 | B58: 20.2
A59: 81 | B59: 19.4
A60: 82 | B60: 18.5
A61: 83 | B61: 17.7
A62: 84 | B62: 16.8
A63: 85 | B63: 16
A64: 86 | B64: 15.2
A65: 87 | B65: 14.4
A66: 88 | B66: 13.7
A67: 89 | B67: 12.9
... A93: 115 | B93: 2.9
A97: INSTRUCTIONS:
A98: • Yellow cells are inputs. Enter Roth Conversions, Other Income, and Discretionary W/D in the tables above.
A99: • IRMAA uses 2-year lookback: enter 2024 & 2025 MAGI for 2026 & 2027. Later years auto-calculate.
A100: • Set Ira's Death Age to model surviving spouse scenario (Single filing, reduced SS, different tax brackets).
A101: • Tax brackets, CG thresholds, and NIIT threshold inflate annually per Tax Bracket Inflation rate.
A104: PROJECTIONS TAB - ROW REFERENCE
A105: Row | B105: Field Name | C105: Description
A106: 1 | B106: Year | C106: Calendar year (2026-2055)
A107: 2 | B107: Ira Age | C107: Ira's age during this year
A108: 3 | B108: Carol Age | C108: Carol's age during this year
A109: 4 | B109: Ira Alive? | C109: TRUE if Ira is alive (for survivor scenario)
A110: 6 | B110: — BEGINNING BALANCES — | C110: Account balances at start of year
A111: 7 | B111: After-Tax | C111: Joint taxable brokerage account
A112: 8 | B112: Traditional IRA | C112: Combined Traditional IRA balance
A113: 9 | B113: Roth IRA | C113: Combined Roth IRA balance
A114: 10 | B114: Total | C114: Sum of all accounts (rows 7+8+9)
A115: 12 | B115: — INCOME & EXPENSES — | C115: Cash flows during year
A116: 13 | B116: Social Security | C116: Combined SS benefits (or survivor benefit)
A117: 14 | B117: Other Income | C117: From OtherIncomeTable lookup
... A159: 62 | B159: PV Expenses | C159: Row 15 ÷ (1+DiscountRate)^year

Sheet Projections
A1: Year | B1: =StartYear | C1: =B1+1 | D1: =C1+1 | E1: =D1+1 | F1: =E1+1 | G1: =F1+1 | H1: =G1+1 | I1: =H1+1 | J1: =I1+1 | ... AE1: =AD1+1
A2: Ira Age | B2: =IraStartAge | C2: =B2+1 | D2: =C2+1 | E2: =D2+1 | F2: =E2+1 | G2: =F2+1 | H2: =G2+1 | I2: =H2+1 | J2: =I2+1 | ... AE2: =AD2+1
A3: Carol Age | B3: =CarolStartAge | C3: =B3+1 | D3: =C3+1 | E3: =D3+1 | F3: =E3+1 | G3: =F3+1 | H3: =G3+1 | I3: =H3+1 | J3: =I3+1 | ... AE3: =AD3+1
A4: Ira Alive? | B4: =IF(DeathAge="",TRUE,B2<DeathAge) | C4: =IF(DeathAge="",TRUE,C2<DeathAge) | D4: =IF(DeathAge="",TRUE,D2<DeathAge) | E4: =IF(DeathAge="",TRUE,E2<DeathAge) | F4: =IF(DeathAge="",TRUE,F2<DeathAge) | G4: =IF(DeathAge="",TRUE,G2<DeathAge) | H4: =IF(DeathAge="",TRUE,H2<DeathAge) | I4: =IF(DeathAge="",TRUE,I2<DeathAge) | ... AE4: =IF(DeathAge="",TRUE,AE2<DeathAge)
A6: BEGINNING BALANCES
A7: After-Tax | B7: =StartAfterTax | C7: =B50 | D7: =C50 | E7: =D50 | F7: =E50 | G7: =F50 | H7: =G50 | I7: =H50 | J7: =I50 | ... AE7: =AD50
A8: Traditional IRA | B8: =StartIRA | C8: =B51 | D8: =C51 | E8: =D51 | F8: =E51 | G8: =F51 | H8: =G51 | I8: =H51 | J8: =I51 | ... AE8: =AD51
A9: Roth IRA | B9: =StartRoth | C9: =B52 | D9: =C52 | E9: =D52 | F9: =E52 | G9: =F52 | H9: =G52 | I9: =H52 | J9: =I52 | ... AE9: =AD52
A10: Total | B10: =B7+B8+B9 | C10: =C7+C8+C9 | D10: =D7+D8+D9 | E10: =E7+E8+E9 | F10: =F7+F8+F9 | G10: =G7+G8+G9 | H10: =H7+H8+H9 | I10: =I7+I8+I9 | ... AE10: =AE7+AE8+AE9
A12: INCOME & EXPENSES
A13: Social Security | B13: =IF(B4,SSAnnual,SurvivorSS*12) | C13: =IF(C4,B13*(1+SSCOLA),SurvivorSS*12*(1+SSCOLA)^1) | D13: =IF(D4,C13*(1+SSCOLA),SurvivorSS*12*(1+SSCOLA)^2) | E13: =IF(E4,D13*(1+SSCOLA),SurvivorSS*12*(1+SSCOLA)^3) | F13: =IF(F4,E13*(1+SSCOLA),SurvivorSS*12*(1+SSCOLA)^4) | G13: =IF(G4,F13*(1+SSCOLA),SurvivorSS*12*(1+SSCOLA)^5) | H13: =IF(H4,G13*(1+SSCOLA),SurvivorSS*12*(1+SSCOLA)^6) | I13: =IF(I4,H13*(1+SSCOLA),SurvivorSS*12*(1+SSCOLA)^7) | J13: =IF(J4,I13*(1+SSCOLA),SurvivorSS*12*(1+SSCOLA)^8) | K13: =IF(K4,J13*(1+SSCOLA),SurvivorSS*12*(1+SSCOLA)^9) | L13: =IF(L4,K13*(1+SSCOLA),SurvivorSS*12*(1+SSCOLA)^10) | M13: =IF(M4,L13*(1+SSCOLA),SurvivorSS*12*(1+SSCOLA)^11) | N13: =IF(N4,M13*(1+SSCOLA),SurvivorSS*12*(1+SSCOLA)^12) | O13: =IF(O4,N13*(1+SSCOLA),SurvivorSS*12*(1+SSCOLA)^13) | P13: =IF(P4,O13*(1+SSCOLA),SurvivorSS*12*(1+SSCOLA)^14) | Q13: =IF(Q4,P13*(1+SSCOLA),SurvivorSS*12*(1+SSCOLA)^15) | R13: =IF(R4,Q13*(1+SSCOLA),SurvivorSS*12*(1+SSCOLA)^16) | S13: =IF(S4,R13*(1+SSCOLA),SurvivorSS*12*(1+SSCOLA)^17) | T13: =IF(T4,S13*(1+SSCOLA),SurvivorSS*12*(1+SSCOLA)^18) | U13: =IF(U4,T13*(1+SSCOLA),SurvivorSS*12*(1+SSCOLA)^19) | V13: =IF(V4,U13*(1+SSCOLA),SurvivorSS*12*(1+SSCOLA)^20) | W13: =IF(W4,V13*(1+SSCOLA),SurvivorSS*12*(1+SSCOLA)^21) | X13: =IF(X4,W13*(1+SSCOLA),SurvivorSS*12*(1+SSCOLA)^22) | Y13: =IF(Y4,X13*(1+SSCOLA),SurvivorSS*12*(1+SSCOLA)^23) | Z13: =IF(Z4,Y13*(1+SSCOLA),SurvivorSS*12*(1+SSCOLA)^24) | AA13: =IF(AA4,Z13*(1+SSCOLA),SurvivorSS*12*(1+SSCOLA)^25) | AB13: =IF(AB4,AA13*(1+SSCOLA),SurvivorSS*12*(1+SSCOLA)^26) | AC13: =IF(AC4,AB13*(1+SSCOLA),SurvivorSS*12*(1+SSCOLA)^27) | AD13: =IF(AD4,AC13*(1+SSCOLA),SurvivorSS*12*(1+SSCOLA)^28) | AE13: =IF(AE4,AD13*(1+SSCOLA),SurvivorSS*12*(1+SSCOLA)^29)
A14: Other Income | B14: =IFERROR(VLOOKUP(B1,OtherIncomeTable,2,FALSE),0) | C14: =IFERROR(VLOOKUP(C1,OtherIncomeTable,2,FALSE),0) | D14: =IFERROR(VLOOKUP(D1,OtherIncomeTable,2,FALSE),0) | E14: =IFERROR(VLOOKUP(E1,OtherIncomeTable,2,FALSE),0) | F14: =IFERROR(VLOOKUP(F1,OtherIncomeTable,2,FALSE),0) | G14: =IFERROR(VLOOKUP(G1,OtherIncomeTable,2,FALSE),0) | H14: =IFERROR(VLOOKUP(H1,OtherIncomeTable,2,FALSE),0) | I14: =IFERROR(VLOOKUP(I1,OtherIncomeTable,2,FALSE),0) | ... AE14: =IFERROR(VLOOKUP(AE1,OtherIncomeTable,2,FALSE),0)
A15: Base Expenses | B15: =StartExpenses | C15: =B15*(1+ExpenseInflation) | D15: =C15*(1+ExpenseInflation) | E15: =D15*(1+ExpenseInflation) | F15: =E15*(1+ExpenseInflation) | G15: =F15*(1+ExpenseInflation) | H15: =G15*(1+ExpenseInflation) | I15: =H15*(1+ExpenseInflation) | J15: =I15*(1+ExpenseInflation) | ... AE15: =AD15*(1+ExpenseInflation)
A16: RMD Required | B16: =IF(IF(B4,B2,B3)>=73,IFERROR(B8/VLOOKUP(IF(B4,B2,B3),RMDTable,2,TRUE),B8/2),0) | C16: =IF(IF(C4,C2,C3)>=73,IFERROR(C8/VLOOKUP(IF(C4,C2,C3),RMDTable,2,TRUE),C8/2),0) | D16: =IF(IF(D4,D2,D3)>=73,IFERROR(D8/VLOOKUP(IF(D4,D2,D3),RMDTable,2,TRUE),D8/2),0) | E16: =IF(IF(E4,E2,E3)>=73,IFERROR(E8/VLOOKUP(IF(E4,E2,E3),RMDTable,2,TRUE),E8/2),0) | F16: =IF(IF(F4,F2,F3)>=73,IFERROR(F8/VLOOKUP(IF(F4,F2,F3),RMDTable,2,TRUE),F8/2),0) | G16: =IF(IF(G4,G2,G3)>=73,IFERROR(G8/VLOOKUP(IF(G4,G2,G3),RMDTable,2,TRUE),G8/2),0) | H16: =IF(IF(H4,H2,H3)>=73,IFERROR(H8/VLOOKUP(IF(H4,H2,H3),RMDTable,2,TRUE),H8/2),0) | I16: =IF(IF(I4,I2,I3)>=73,IFERROR(I8/VLOOKUP(IF(I4,I2,I3),RMDTable,2,TRUE),I8/2),0) | ... AE16: =IF(IF(AE4,AE2,AE3)>=73,IFERROR(AE8/VLOOKUP(IF(AE4,AE2,AE3),RMDTable,2,TRUE),AE8/2),0)
A17: Roth Conversion | B17: =IFERROR(VLOOKUP(B1,RothConvTable,2,FALSE),0) | C17: =IFERROR(VLOOKUP(C1,RothConvTable,2,FALSE),0) | D17: =IFERROR(VLOOKUP(D1,RothConvTable,2,FALSE),0) | E17: =IFERROR(VLOOKUP(E1,RothConvTable,2,FALSE),0) | F17: =IFERROR(VLOOKUP(F1,RothConvTable,2,FALSE),0) | G17: =IFERROR(VLOOKUP(G1,RothConvTable,2,FALSE),0) | H17: =IFERROR(VLOOKUP(H1,RothConvTable,2,FALSE),0) | I17: =IFERROR(VLOOKUP(I1,RothConvTable,2,FALSE),0) | ... AE17: =IFERROR(VLOOKUP(AE1,RothConvTable,2,FALSE),0)
A19: INVESTMENT RETURNS
A20: Return After-Tax | B20: =IF(UseBlendedReturns="Yes",B7*'Risk Allocation'!B26,B7*ReturnAfterTax) | C20: =IF(UseBlendedReturns="Yes",C7*'Risk Allocation'!C26,C7*ReturnAfterTax) | D20: =IF(UseBlendedReturns="Yes",D7*'Risk Allocation'!D26,D7*ReturnAfterTax) | E20: =IF(UseBlendedReturns="Yes",E7*'Risk Allocation'!E26,E7*ReturnAfterTax) | F20: =IF(UseBlendedReturns="Yes",F7*'Risk Allocation'!F26,F7*ReturnAfterTax) | G20: =IF(UseBlendedReturns="Yes",G7*'Risk Allocation'!G26,G7*ReturnAfterTax) | H20: =IF(UseBlendedReturns="Yes",H7*'Risk Allocation'!H26,H7*ReturnAfterTax) | I20: =IF(UseBlendedReturns="Yes",I7*'Risk Allocation'!I26,I7*ReturnAfterTax) | ... AE20: =IF(UseBlendedReturns="Yes",AE7*'Risk Allocation'!AE26,AE7*ReturnAfterTax)
A21: Return IRA | B21: =IF(UseBlendedReturns="Yes",MAX(0,(B8-B17))*'Risk Allocation'!B27,MAX(0,(B8-B17))*ReturnIRA) | C21: =IF(UseBlendedReturns="Yes",MAX(0,(C8-C17))*'Risk Allocation'!C27,MAX(0,(C8-C17))*ReturnIRA) | D21: =IF(UseBlendedReturns="Yes",MAX(0,(D8-D17))*'Risk Allocation'!D27,MAX(0,(D8-D17))*ReturnIRA) | E21: =IF(UseBlendedReturns="Yes",MAX(0,(E8-E17))*'Risk Allocation'!E27,MAX(0,(E8-E17))*ReturnIRA) | F21: =IF(UseBlendedReturns="Yes",MAX(0,(F8-F17))*'Risk Allocation'!F27,MAX(0,(F8-F17))*ReturnIRA) | G21: =IF(UseBlendedReturns="Yes",MAX(0,(G8-G17))*'Risk Allocation'!G27,MAX(0,(G8-G17))*ReturnIRA) | H21: =IF(UseBlendedReturns="Yes",MAX(0,(H8-H17))*'Risk Allocation'!H27,MAX(0,(H8-H17))*ReturnIRA) | I21: =IF(UseBlendedReturns="Yes",MAX(0,(I8-I17))*'Risk Allocation'!I27,MAX(0,(I8-I17))*ReturnIRA) | ... AE21: =IF(UseBlendedReturns="Yes",MAX(0,(AE8-AE17))*'Risk Allocation'!AE27,MAX(0,(AE8-AE17))*ReturnIRA)
A22: Return Roth | B22: =IF(UseBlendedReturns="Yes",(B9+B17)*'Risk Allocation'!B28,(B9+B17)*ReturnRoth) | C22: =IF(UseBlendedReturns="Yes",(C9+C17)*'Risk Allocation'!C28,(C9+C17)*ReturnRoth) | D22: =IF(UseBlendedReturns="Yes",(D9+D17)*'Risk Allocation'!D28,(D9+D17)*ReturnRoth) | E22: =IF(UseBlendedReturns="Yes",(E9+E17)*'Risk Allocation'!E28,(E9+E17)*ReturnRoth) | F22: =IF(UseBlendedReturns="Yes",(F9+F17)*'Risk Allocation'!F28,(F9+F17)*ReturnRoth) | G22: =IF(UseBlendedReturns="Yes",(G9+G17)*'Risk Allocation'!G28,(G9+G17)*ReturnRoth) | H22: =IF(UseBlendedReturns="Yes",(H9+H17)*'Risk Allocation'!H28,(H9+H17)*ReturnRoth) | I22: =IF(UseBlendedReturns="Yes",(I9+I17)*'Risk Allocation'!I28,(I9+I17)*ReturnRoth) | ... AE22: =IF(UseBlendedReturns="Yes",(AE9+AE17)*'Risk Allocation'!AE28,(AE9+AE17)*ReturnRoth)
A24: IRMAA & TAXES
A25: Prior Yr MAGI (est) | B25: =MAGI2024 | C25: =MAGI2025 | D25: =B14+B16+B17+B33+0.85*B13+B32*CapGainsPct | E25: =C14+C16+C17+C33+0.85*C13+C32*CapGainsPct | F25: =D14+D16+D17+D33+0.85*D13+D32*CapGainsPct | G25: =E14+E16+E17+E33+0.85*E13+E32*CapGainsPct | H25: =F14+F16+F17+F33+0.85*F13+F32*CapGainsPct | I25: =G14+G16+G17+G33+0.85*G13+G32*CapGainsPct | J25: =H14+H16+H17+H33+0.85*H13+H32*CapGainsPct | K25: =I14+I16+I17+I33+0.85*I13+I32*CapGainsPct | ... AE25: =AC14+AC16+AC17+AC33+0.85*AC13+AC32*CapGainsPct
A26: IRMAA | B26: =IF(B4,IF(B25<=IRMAA_MFJ_Thresh1*(1+TaxBracketInflation)^0,IRMAA_MFJ_Cost1*(1+SSCOLA)^0,IF(B25<=IRMAA_MFJ_Thresh2*(1+TaxBracketInflation)^0,IRMAA_MFJ_Cost2*(1+SSCOLA)^0,IF(B25<=IRMAA_MFJ_Thresh3*(1+TaxBracketInflation)^0,IRMAA_MFJ_Cost3*(1+SSCOLA)^0,IF(B25<=IRMAA_MFJ_Thresh4*(1+TaxBracketInflation)^0,IRMAA_MFJ_Cost4*(1+SSCOLA)^0,IF(B25<=IRMAA_MFJ_Thresh5*(1+TaxBracketInflation)^0,IRMAA_MFJ_Cost5*(1+SSCOLA)^0,IRMAA_MFJ_Cost6*(1+SSCOLA)^0))))),IF(B25<=IRMAA_Single_Thresh1*(1+TaxBracketInflation)^0,IRMAA_Single_Cost1*(1+SSCOLA)^0,IF(B25<=IRMAA_Single_Thresh2*(1+TaxBracketInflation)^0,IRMAA_Single_Cost2*(1+SSCOLA)^0,IF(B25<=IRMAA_Single_Thresh3*(1+TaxBracketInflation)^0,IRMAA_Single_Cost3*(1+SSCOLA)^0,IF(B25<=IRMAA_Single_Thresh4*(1+TaxBracketInflation)^0,IRMAA_Single_Cost4*(1+SSCOLA)^0,IF(B25<=IRMAA_Single_Thresh5*(1+TaxBracketInflation)^0,IRMAA_Single_Cost5*(1+SSCOLA)^0,IRMAA_Single_Cost6*(1+SSCOLA)^0)))))) | C26: =IF(C4,IF(C25<=IRMAA_MFJ_Thresh1*(1+TaxBracketInflation)^1,IRMAA_MFJ_Cost1*(1+SSCOLA)^1,IF(C25<=IRMAA_MFJ_Thresh2*(1+TaxBracketInflation)^1,IRMAA_MFJ_Cost2*(1+SSCOLA)^1,IF(C25<=IRMAA_MFJ_Thresh3*(1+TaxBracketInflation)^1,IRMAA_MFJ_Cost3*(1+SSCOLA)^1,IF(C25<=IRMAA_MFJ_Thresh4*(1+TaxBracketInflation)^1,IRMAA_MFJ_Cost4*(1+SSCOLA)^1,IF(C25<=IRMAA_MFJ_Thresh5*(1+TaxBracketInflation)^1,IRMAA_MFJ_Cost5*(1+SSCOLA)^1,IRMAA_MFJ_Cost6*(1+SSCOLA)^1))))),IF(C25<=IRMAA_Single_Thresh1*(1+TaxBracketInflation)^1,IRMAA_Single_Cost1*(1+SSCOLA)^1,IF(C25<=IRMAA_Single_Thresh2*(1+TaxBracketInflation)^1,IRMAA_Single_Cost2*(1+SSCOLA)^1,IF(C25<=IRMAA_Single_Thresh3*(1+TaxBracketInflation)^1,IRMAA_Single_Cost3*(1+SSCOLA)^1,IF(C25<=IRMAA_Single_Thresh4*(1+TaxBracketInflation)^1,IRMAA_Single_Cost4*(1+SSCOLA)^1,IF(C25<=IRMAA_Single_Thresh5*(1+TaxBracketInflation)^1,IRMAA_Single_Cost5*(1+SSCOLA)^1,IRMAA_Single_Cost6*(1+SSCOLA)^1)))))) | D26: =IF(D4,IF(D25<=IRMAA_MFJ_Thresh1*(1+TaxBracketInflation)^2,IRMAA_MFJ_Cost1*(1+SSCOLA)^2,IF(D25<=IRMAA_MFJ_Thresh2*(1+TaxBracketInflation)^2,IRMAA_MFJ_Cost2*(1+SSCOLA)^2,IF(D25<=IRMAA_MFJ_Thresh3*(1+TaxBracketInflation)^2,IRMAA_MFJ_Cost3*(1+SSCOLA)^2,IF(D25<=IRMAA_MFJ_Thresh4*(1+TaxBracketInflation)^2,IRMAA_MFJ_Cost4*(1+SSCOLA)^2,IF(D25<=IRMAA_MFJ_Thresh5*(1+TaxBracketInflation)^2,IRMAA_MFJ_Cost5*(1+SSCOLA)^2,IRMAA_MFJ_Cost6*(1+SSCOLA)^2))))),IF(D25<=IRMAA_Single_Thresh1*(1+TaxBracketInflation)^2,IRMAA_Single_Cost1*(1+SSCOLA)^2,IF(D25<=IRMAA_Single_Thresh2*(1+TaxBracketInflation)^2,IRMAA_Single_Cost2*(1+SSCOLA)^2,IF(D25<=IRMAA_Single_Thresh3*(1+TaxBracketInflation)^2,IRMAA_Single_Cost3*(1+SSCOLA)^2,IF(D25<=IRMAA_Single_Thresh4*(1+TaxBracketInflation)^2,IRMAA_Single_Cost4*(1+SSCOLA)^2,IF(D25<=IRMAA_Single_Thresh5*(1+TaxBracketInflation)^2,IRMAA_Single_Cost5*(1+SSCOLA)^2,IRMAA_Single_Cost6*(1+SSCOLA)^2)))))) | E26: =IF(E4,IF(E25<=IRMAA_MFJ_Thresh1*(1+TaxBracketInflation)^3,IRMAA_MFJ_Cost1*(1+SSCOLA)^3,IF(E25<=IRMAA_MFJ_Thresh2*(1+TaxBracketInflation)^3,IRMAA_MFJ_Cost2*(1+SSCOLA)^3,IF(E25<=IRMAA_MFJ_Thresh3*(1+TaxBracketInflation)^3,IRMAA_MFJ_Cost3*(1+SSCOLA)^3,IF(E25<=IRMAA_MFJ_Thresh4*(1+TaxBracketInflation)^3,IRMAA_MFJ_Cost4*(1+SSCOLA)^3,IF(E25<=IRMAA_MFJ_Thresh5*(1+TaxBracketInflation)^3,IRMAA_MFJ_Cost5*(1+SSCOLA)^3,IRMAA_MFJ_Cost6*(1+SSCOLA)^3))))),IF(E25<=IRMAA_Single_Thresh1*(1+TaxBracketInflation)^3,IRMAA_Single_Cost1*(1+SSCOLA)^3,IF(E25<=IRMAA_Single_Thresh2*(1+TaxBracketInflation)^3,IRMAA_Single_Cost2*(1+SSCOLA)^3,IF(E25<=IRMAA_Single_Thresh3*(1+TaxBracketInflation)^3,IRMAA_Single_Cost3*(1+SSCOLA)^3,IF(E25<=IRMAA_Single_Thresh4*(1+TaxBracketInflation)^3,IRMAA_Single_Cost4*(1+SSCOLA)^3,IF(E25<=IRMAA_Single_Thresh5*(1+TaxBracketInflation)^3,IRMAA_Single_Cost5*(1+SSCOLA)^3,IRMAA_Single_Cost6*(1+SSCOLA)^3)))))) | F26: =IF(F4,IF(F25<=IRMAA_MFJ_Thresh1*(1+TaxBracketInflation)^4,IRMAA_MFJ_Cost1*(1+SSCOLA)^4,IF(F25<=IRMAA_MFJ_Thresh2*(1+TaxBracketInflation)^4,IRMAA_MFJ_Cost2*(1+SSCOLA)^4,IF(F25<=IRMAA_MFJ_Thresh3*(1+TaxBracketInflation)^4,IRMAA_MFJ_Cost3*(1+SSCOLA)^4,IF(F25<=IRMAA_MFJ_Thresh4*(1+TaxBracketInflation)^4,IRMAA_MFJ_Cost4*(1+SSCOLA)^4,IF(F25<=IRMAA_MFJ_Thresh5*(1+TaxBracketInflation)^4,IRMAA_MFJ_Cost5*(1+SSCOLA)^4,IRMAA_MFJ_Cost6*(1+SSCOLA)^4))))),IF(F25<=IRMAA_Single_Thresh1*(1+TaxBracketInflation)^4,IRMAA_Single_Cost1*(1+SSCOLA)^4,IF(F25<=IRMAA_Single_Thresh2*(1+TaxBracketInflation)^4,IRMAA_Single_Cost2*(1+SSCOLA)^4,IF(F25<=IRMAA_Single_Thresh3*(1+TaxBracketInflation)^4,IRMAA_Single_Cost3*(1+SSCOLA)^4,IF(F25<=IRMAA_Single_Thresh4*(1+TaxBracketInflation)^4,IRMAA_Single_Cost4*(1+SSCOLA)^4,IF(F25<=IRMAA_Single_Thresh5*(1+TaxBracketInflation)^4,IRMAA_Single_Cost5*(1+SSCOLA)^4,IRMAA_Single_Cost6*(1+SSCOLA)^4)))))) | G26: =IF(G4,IF(G25<=IRMAA_MFJ_Thresh1*(1+TaxBracketInflation)^5,IRMAA_MFJ_Cost1*(1+SSCOLA)^5,IF(G25<=IRMAA_MFJ_Thresh2*(1+TaxBracketInflation)^5,IRMAA_MFJ_Cost2*(1+SSCOLA)^5,IF(G25<=IRMAA_MFJ_Thresh3*(1+TaxBracketInflation)^5,IRMAA_MFJ_Cost3*(1+SSCOLA)^5,IF(G25<=IRMAA_MFJ_Thresh4*(1+TaxBracketInflation)^5,IRMAA_MFJ_Cost4*(1+SSCOLA)^5,IF(G25<=IRMAA_MFJ_Thresh5*(1+TaxBracketInflation)^5,IRMAA_MFJ_Cost5*(1+SSCOLA)^5,IRMAA_MFJ_Cost6*(1+SSCOLA)^5))))),IF(G25<=IRMAA_Single_Thresh1*(1+TaxBracketInflation)^5,IRMAA_Single_Cost1*(1+SSCOLA)^5,IF(G25<=IRMAA_Single_Thresh2*(1+TaxBracketInflation)^5,IRMAA_Single_Cost2*(1+SSCOLA)^5,IF(G25<=IRMAA_Single_Thresh3*(1+TaxBracketInflation)^5,IRMAA_Single_Cost3*(1+SSCOLA)^5,IF(G25<=IRMAA_Single_Thresh4*(1+TaxBracketInflation)^5,IRMAA_Single_Cost4*(1+SSCOLA)^5,IF(G25<=IRMAA_Single_Thresh5*(1+TaxBracketInflation)^5,IRMAA_Single_Cost5*(1+SSCOLA)^5,IRMAA_Single_Cost6*(1+SSCOLA)^5)))))) | H26: =IF(H4,IF(H25<=IRMAA_MFJ_Thresh1*(1+TaxBracketInflation)^6,IRMAA_MFJ_Cost1*(1+SSCOLA)^6,IF(H25<=IRMAA_MFJ_Thresh2*(1+TaxBracketInflation)^6,IRMAA_MFJ_Cost2*(1+SSCOLA)^6,IF(H25<=IRMAA_MFJ_Thresh3*(1+TaxBracketInflation)^6,IRMAA_MFJ_Cost3*(1+SSCOLA)^6,IF(H25<=IRMAA_MFJ_Thresh4*(1+TaxBracketInflation)^6,IRMAA_MFJ_Cost4*(1+SSCOLA)^6,IF(H25<=IRMAA_MFJ_Thresh5*(1+TaxBracketInflation)^6,IRMAA_MFJ_Cost5*(1+SSCOLA)^6,IRMAA_MFJ_Cost6*(1+SSCOLA)^6))))),IF(H25<=IRMAA_Single_Thresh1*(1+TaxBracketInflation)^6,IRMAA_Single_Cost1*(1+SSCOLA)^6,IF(H25<=IRMAA_Single_Thresh2*(1+TaxBracketInflation)^6,IRMAA_Single_Cost2*(1+SSCOLA)^6,IF(H25<=IRMAA_Single_Thresh3*(1+TaxBracketInflation)^6,IRMAA_Single_Cost3*(1+SSCOLA)^6,IF(H25<=IRMAA_Single_Thresh4*(1+TaxBracketInflation)^6,IRMAA_Single_Cost4*(1+SSCOLA)^6,IF(H25<=IRMAA_Single_Thresh5*(1+TaxBracketInflation)^6,IRMAA_Single_Cost5*(1+SSCOLA)^6,IRMAA_Single_Cost6*(1+SSCOLA)^6)))))) | I26: =IF(I4,IF(I25<=IRMAA_MFJ_Thresh1*(1+TaxBracketInflation)^7,IRMAA_MFJ_Cost1*(1+SSCOLA)^7,IF(I25<=IRMAA_MFJ_Thresh2*(1+TaxBracketInflation)^7,IRMAA_MFJ_Cost2*(1+SSCOLA)^7,IF(I25<=IRMAA_MFJ_Thresh3*(1+TaxBracketInflation)^7,IRMAA_MFJ_Cost3*(1+SSCOLA)^7,IF(I25<=IRMAA_MFJ_Thresh4*(1+TaxBracketInflation)^7,IRMAA_MFJ_Cost4*(1+SSCOLA)^7,IF(I25<=IRMAA_MFJ_Thresh5*(1+TaxBracketInflation)^7,IRMAA_MFJ_Cost5*(1+SSCOLA)^7,IRMAA_MFJ_Cost6*(1+SSCOLA)^7))))),IF(I25<=IRMAA_Single_Thresh1*(1+TaxBracketInflation)^7,IRMAA_Single_Cost1*(1+SSCOLA)^7,IF(I25<=IRMAA_Single_Thresh2*(1+TaxBracketInflation)^7,IRMAA_Single_Cost2*(1+SSCOLA)^7,IF(I25<=IRMAA_Single_Thresh3*(1+TaxBracketInflation)^7,IRMAA_Single_Cost3*(1+SSCOLA)^7,IF(I25<=IRMAA_Single_Thresh4*(1+TaxBracketInflation)^7,IRMAA_Single_Cost4*(1+SSCOLA)^7,IF(I25<=IRMAA_Single_Thresh5*(1+TaxBracketInflation)^7,IRMAA_Single_Cost5*(1+SSCOLA)^7,IRMAA_Single_Cost6*(1+SSCOLA)^7)))))) | J26: =IF(J4,IF(J25<=IRMAA_MFJ_Thresh1*(1+TaxBracketInflation)^8,IRMAA_MFJ_Cost1*(1+SSCOLA)^8,IF(J25<=IRMAA_MFJ_Thresh2*(1+TaxBracketInflation)^8,IRMAA_MFJ_Cost2*(1+SSCOLA)^8,IF(J25<=IRMAA_MFJ_Thresh3*(1+TaxBracketInflation)^8,IRMAA_MFJ_Cost3*(1+SSCOLA)^8,IF(J25<=IRMAA_MFJ_Thresh4*(1+TaxBracketInflation)^8,IRMAA_MFJ_Cost4*(1+SSCOLA)^8,IF(J25<=IRMAA_MFJ_Thresh5*(1+TaxBracketInflation)^8,IRMAA_MFJ_Cost5*(1+SSCOLA)^8,IRMAA_MFJ_Cost6*(1+SSCOLA)^8))))),IF(J25<=IRMAA_Single_Thresh1*(1+TaxBracketInflation)^8,IRMAA_Single_Cost1*(1+SSCOLA)^8,IF(J25<=IRMAA_Single_Thresh2*(1+TaxBracketInflation)^8,IRMAA_Single_Cost2*(1+SSCOLA)^8,IF(J25<=IRMAA_Single_Thresh3*(1+TaxBracketInflation)^8,IRMAA_Single_Cost3*(1+SSCOLA)^8,IF(J25<=IRMAA_Single_Thresh4*(1+TaxBracketInflation)^8,IRMAA_Single_Cost4*(1+SSCOLA)^8,IF(J25<=IRMAA_Single_Thresh5*(1+TaxBracketInflation)^8,IRMAA_Single_Cost5*(1+SSCOLA)^8,IRMAA_Single_Cost6*(1+SSCOLA)^8)))))) | K26: =IF(K4,IF(K25<=IRMAA_MFJ_Thresh1*(1+TaxBracketInflation)^9,IRMAA_MFJ_Cost1*(1+SSCOLA)^9,IF(K25<=IRMAA_MFJ_Thresh2*(1+TaxBracketInflation)^9,IRMAA_MFJ_Cost2*(1+SSCOLA)^9,IF(K25<=IRMAA_MFJ_Thresh3*(1+TaxBracketInflation)^9,IRMAA_MFJ_Cost3*(1+SSCOLA)^9,IF(K25<=IRMAA_MFJ_Thresh4*(1+TaxBracketInflation)^9,IRMAA_MFJ_Cost4*(1+SSCOLA)^9,IF(K25<=IRMAA_MFJ_Thresh5*(1+TaxBracketInflation)^9,IRMAA_MFJ_Cost5*(1+SSCOLA)^9,IRMAA_MFJ_Cost6*(1+SSCOLA)^9))))),IF(K25<=IRMAA_Single_Thresh1*(1+TaxBracketInflation)^9,IRMAA_Single_Cost1*(1+SSCOLA)^9,IF(K25<=IRMAA_Single_Thresh2*(1+TaxBracketInflation)^9,IRMAA_Single_Cost2*(1+SSCOLA)^9,IF(K25<=IRMAA_Single_Thresh3*(1+TaxBracketInflation)^9,IRMAA_Single_Cost3*(1+SSCOLA)^9,IF(K25<=IRMAA_Single_Thresh4*(1+TaxBracketInflation)^9,IRMAA_Single_Cost4*(1+SSCOLA)^9,IF(K25<=IRMAA_Single_Thresh5*(1+TaxBracketInflation)^9,IRMAA_Single_Cost5*(1+SSCOLA)^9,IRMAA_Single_Cost6*(1+SSCOLA)^9)))))) | L26: =IF(L4,IF(L25<=IRMAA_MFJ_Thresh1*(1+TaxBracketInflation)^10,IRMAA_MFJ_Cost1*(1+SSCOLA)^10,IF(L25<=IRMAA_MFJ_Thresh2*(1+TaxBracketInflation)^10,IRMAA_MFJ_Cost2*(1+SSCOLA)^10,IF(L25<=IRMAA_MFJ_Thresh3*(1+TaxBracketInflation)^10,IRMAA_MFJ_Cost3*(1+SSCOLA)^10,IF(L25<=IRMAA_MFJ_Thresh4*(1+TaxBracketInflation)^10,IRMAA_MFJ_Cost4*(1+SSCOLA)^10,IF(L25<=IRMAA_MFJ_Thresh5*(1+TaxBracketInflation)^10,IRMAA_MFJ_Cost5*(1+SSCOLA)^10,IRMAA_MFJ_Cost6*(1+SSCOLA)^10))))),IF(L25<=IRMAA_Single_Thresh1*(1+TaxBracketInflation)^10,IRMAA_Single_Cost1*(1+SSCOLA)^10,IF(L25<=IRMAA_Single_Thresh2*(1+TaxBracketInflation)^10,IRMAA_Single_Cost2*(1+SSCOLA)^10,IF(L25<=IRMAA_Single_Thresh3*(1+TaxBracketInflation)^10,IRMAA_Single_Cost3*(1+SSCOLA)^10,IF(L25<=IRMAA_Single_Thresh4*(1+TaxBracketInflation)^10,IRMAA_Single_Cost4*(1+SSCOLA)^10,IF(L25<=IRMAA_Single_Thresh5*(1+TaxBracketInflation)^10,IRMAA_Single_Cost5*(1+SSCOLA)^10,IRMAA_Single_Cost6*(1+SSCOLA)^10)))))) | M26: =IF(M4,IF(M25<=IRMAA_MFJ_Thresh1*(1+TaxBracketInflation)^11,IRMAA_MFJ_Cost1*(1+SSCOLA)^11,IF(M25<=IRMAA_MFJ_Thresh2*(1+TaxBracketInflation)^11,IRMAA_MFJ_Cost2*(1+SSCOLA)^11,IF(M25<=IRMAA_MFJ_Thresh3*(1+TaxBracketInflation)^11,IRMAA_MFJ_Cost3*(1+SSCOLA)^11,IF(M25<=IRMAA_MFJ_Thresh4*(1+TaxBracketInflation)^11,IRMAA_MFJ_Cost4*(1+SSCOLA)^11,IF(M25<=IRMAA_MFJ_Thresh5*(1+TaxBracketInflation)^11,IRMAA_MFJ_Cost5*(1+SSCOLA)^11,IRMAA_MFJ_Cost6*(1+SSCOLA)^11))))),IF(M25<=IRMAA_Single_Thresh1*(1+TaxBracketInflation)^11,IRMAA_Single_Cost1*(1+SSCOLA)^11,IF(M25<=IRMAA_Single_Thresh2*(1+TaxBracketInflation)^11,IRMAA_Single_Cost2*(1+SSCOLA)^11,IF(M25<=IRMAA_Single_Thresh3*(1+TaxBracketInflation)^11,IRMAA_Single_Cost3*(1+SSCOLA)^11,IF(M25<=IRMAA_Single_Thresh4*(1+TaxBracketInflation)^11,IRMAA_Single_Cost4*(1+SSCOLA)^11,IF(M25<=IRMAA_Single_Thresh5*(1+TaxBracketInflation)^11,IRMAA_Single_Cost5*(1+SSCOLA)^11,IRMAA_Single_Cost6*(1+SSCOLA)^11)))))) | N26: =IF(N4,IF(N25<=IRMAA_MFJ_Thresh1*(1+TaxBracketInflation)^12,IRMAA_MFJ_Cost1*(1+SSCOLA)^12,IF(N25<=IRMAA_MFJ_Thresh2*(1+TaxBracketInflation)^12,IRMAA_MFJ_Cost2*(1+SSCOLA)^12,IF(N25<=IRMAA_MFJ_Thresh3*(1+TaxBracketInflation)^12,IRMAA_MFJ_Cost3*(1+SSCOLA)^12,IF(N25<=IRMAA_MFJ_Thresh4*(1+TaxBracketInflation)^12,IRMAA_MFJ_Cost4*(1+SSCOLA)^12,IF(N25<=IRMAA_MFJ_Thresh5*(1+TaxBracketInflation)^12,IRMAA_MFJ_Cost5*(1+SSCOLA)^12,IRMAA_MFJ_Cost6*(1+SSCOLA)^12))))),IF(N25<=IRMAA_Single_Thresh1*(1+TaxBracketInflation)^12,IRMAA_Single_Cost1*(1+SSCOLA)^12,IF(N25<=IRMAA_Single_Thresh2*(1+TaxBracketInflation)^12,IRMAA_Single_Cost2*(1+SSCOLA)^12,IF(N25<=IRMAA_Single_Thresh3*(1+TaxBracketInflation)^12,IRMAA_Single_Cost3*(1+SSCOLA)^12,IF(N25<=IRMAA_Single_Thresh4*(1+TaxBracketInflation)^12,IRMAA_Single_Cost4*(1+SSCOLA)^12,IF(N25<=IRMAA_Single_Thresh5*(1+TaxBracketInflation)^12,IRMAA_Single_Cost5*(1+SSCOLA)^12,IRMAA_Single_Cost6*(1+SSCOLA)^12)))))) | O26: =IF(O4,IF(O25<=IRMAA_MFJ_Thresh1*(1+TaxBracketInflation)^13,IRMAA_MFJ_Cost1*(1+SSCOLA)^13,IF(O25<=IRMAA_MFJ_Thresh2*(1+TaxBracketInflation)^13,IRMAA_MFJ_Cost2*(1+SSCOLA)^13,IF(O25<=IRMAA_MFJ_Thresh3*(1+TaxBracketInflation)^13,IRMAA_MFJ_Cost3*(1+SSCOLA)^13,IF(O25<=IRMAA_MFJ_Thresh4*(1+TaxBracketInflation)^13,IRMAA_MFJ_Cost4*(1+SSCOLA)^13,IF(O25<=IRMAA_MFJ_Thresh5*(1+TaxBracketInflation)^13,IRMAA_MFJ_Cost5*(1+SSCOLA)^13,IRMAA_MFJ_Cost6*(1+SSCOLA)^13))))),IF(O25<=IRMAA_Single_Thresh1*(1+TaxBracketInflation)^13,IRMAA_Single_Cost1*(1+SSCOLA)^13,IF(O25<=IRMAA_Single_Thresh2*(1+TaxBracketInflation)^13,IRMAA_Single_Cost2*(1+SSCOLA)^13,IF(O25<=IRMAA_Single_Thresh3*(1+TaxBracketInflation)^13,IRMAA_Single_Cost3*(1+SSCOLA)^13,IF(O25<=IRMAA_Single_Thresh4*(1+TaxBracketInflation)^13,IRMAA_Single_Cost4*(1+SSCOLA)^13,IF(O25<=IRMAA_Single_Thresh5*(1+TaxBracketInflation)^13,IRMAA_Single_Cost5*(1+SSCOLA)^13,IRMAA_Single_Cost6*(1+SSCOLA)^13)))))) | P26: =IF(P4,IF(P25<=IRMAA_MFJ_Thresh1*(1+TaxBracketInflation)^14,IRMAA_MFJ_Cost1*(1+SSCOLA)^14,IF(P25<=IRMAA_MFJ_Thresh2*(1+TaxBracketInflation)^14,IRMAA_MFJ_Cost2*(1+SSCOLA)^14,IF(P25<=IRMAA_MFJ_Thresh3*(1+TaxBracketInflation)^14,IRMAA_MFJ_Cost3*(1+SSCOLA)^14,IF(P25<=IRMAA_MFJ_Thresh4*(1+TaxBracketInflation)^14,IRMAA_MFJ_Cost4*(1+SSCOLA)^14,IF(P25<=IRMAA_MFJ_Thresh5*(1+TaxBracketInflation)^14,IRMAA_MFJ_Cost5*(1+SSCOLA)^14,IRMAA_MFJ_Cost6*(1+SSCOLA)^14))))),IF(P25<=IRMAA_Single_Thresh1*(1+TaxBracketInflation)^14,IRMAA_Single_Cost1*(1+SSCOLA)^14,IF(P25<=IRMAA_Single_Thresh2*(1+TaxBracketInflation)^14,IRMAA_Single_Cost2*(1+SSCOLA)^14,IF(P25<=IRMAA_Single_Thresh3*(1+TaxBracketInflation)^14,IRMAA_Single_Cost3*(1+SSCOLA)^14,IF(P25<=IRMAA_Single_Thresh4*(1+TaxBracketInflation)^14,IRMAA_Single_Cost4*(1+SSCOLA)^14,IF(P25<=IRMAA_Single_Thresh5*(1+TaxBracketInflation)^14,IRMAA_Single_Cost5*(1+SSCOLA)^14,IRMAA_Single_Cost6*(1+SSCOLA)^14)))))) | Q26: =IF(Q4,IF(Q25<=IRMAA_MFJ_Thresh1*(1+TaxBracketInflation)^15,IRMAA_MFJ_Cost1*(1+SSCOLA)^15,IF(Q25<=IRMAA_MFJ_Thresh2*(1+TaxBracketInflation)^15,IRMAA_MFJ_Cost2*(1+SSCOLA)^15,IF(Q25<=IRMAA_MFJ_Thresh3*(1+TaxBracketInflation)^15,IRMAA_MFJ_Cost3*(1+SSCOLA)^15,IF(Q25<=IRMAA_MFJ_Thresh4*(1+TaxBracketInflation)^15,IRMAA_MFJ_Cost4*(1+SSCOLA)^15,IF(Q25<=IRMAA_MFJ_Thresh5*(1+TaxBracketInflation)^15,IRMAA_MFJ_Cost5*(1+SSCOLA)^15,IRMAA_MFJ_Cost6*(1+SSCOLA)^15))))),IF(Q25<=IRMAA_Single_Thresh1*(1+TaxBracketInflation)^15,IRMAA_Single_Cost1*(1+SSCOLA)^15,IF(Q25<=IRMAA_Single_Thresh2*(1+TaxBracketInflation)^15,IRMAA_Single_Cost2*(1+SSCOLA)^15,IF(Q25<=IRMAA_Single_Thresh3*(1+TaxBracketInflation)^15,IRMAA_Single_Cost3*(1+SSCOLA)^15,IF(Q25<=IRMAA_Single_Thresh4*(1+TaxBracketInflation)^15,IRMAA_Single_Cost4*(1+SSCOLA)^15,IF(Q25<=IRMAA_Single_Thresh5*(1+TaxBracketInflation)^15,IRMAA_Single_Cost5*(1+SSCOLA)^15,IRMAA_Single_Cost6*(1+SSCOLA)^15)))))) | R26: =IF(R4,IF(R25<=IRMAA_MFJ_Thresh1*(1+TaxBracketInflation)^16,IRMAA_MFJ_Cost1*(1+SSCOLA)^16,IF(R25<=IRMAA_MFJ_Thresh2*(1+TaxBracketInflation)^16,IRMAA_MFJ_Cost2*(1+SSCOLA)^16,IF(R25<=IRMAA_MFJ_Thresh3*(1+TaxBracketInflation)^16,IRMAA_MFJ_Cost3*(1+SSCOLA)^16,IF(R25<=IRMAA_MFJ_Thresh4*(1+TaxBracketInflation)^16,IRMAA_MFJ_Cost4*(1+SSCOLA)^16,IF(R25<=IRMAA_MFJ_Thresh5*(1+TaxBracketInflation)^16,IRMAA_MFJ_Cost5*(1+SSCOLA)^16,IRMAA_MFJ_Cost6*(1+SSCOLA)^16))))),IF(R25<=IRMAA_Single_Thresh1*(1+TaxBracketInflation)^16,IRMAA_Single_Cost1*(1+SSCOLA)^16,IF(R25<=IRMAA_Single_Thresh2*(1+TaxBracketInflation)^16,IRMAA_Single_Cost2*(1+SSCOLA)^16,IF(R25<=IRMAA_Single_Thresh3*(1+TaxBracketInflation)^16,IRMAA_Single_Cost3*(1+SSCOLA)^16,IF(R25<=IRMAA_Single_Thresh4*(1+TaxBracketInflation)^16,IRMAA_Single_Cost4*(1+SSCOLA)^16,IF(R25<=IRMAA_Single_Thresh5*(1+TaxBracketInflation)^16,IRMAA_Single_Cost5*(1+SSCOLA)^16,IRMAA_Single_Cost6*(1+SSCOLA)^16)))))) | S26: =IF(S4,IF(S25<=IRMAA_MFJ_Thresh1*(1+TaxBracketInflation)^17,IRMAA_MFJ_Cost1*(1+SSCOLA)^17,IF(S25<=IRMAA_MFJ_Thresh2*(1+TaxBracketInflation)^17,IRMAA_MFJ_Cost2*(1+SSCOLA)^17,IF(S25<=IRMAA_MFJ_Thresh3*(1+TaxBracketInflation)^17,IRMAA_MFJ_Cost3*(1+SSCOLA)^17,IF(S25<=IRMAA_MFJ_Thresh4*(1+TaxBracketInflation)^17,IRMAA_MFJ_Cost4*(1+SSCOLA)^17,IF(S25<=IRMAA_MFJ_Thresh5*(1+TaxBracketInflation)^17,IRMAA_MFJ_Cost5*(1+SSCOLA)^17,IRMAA_MFJ_Cost6*(1+SSCOLA)^17))))),IF(S25<=IRMAA_Single_Thresh1*(1+TaxBracketInflation)^17,IRMAA_Single_Cost1*(1+SSCOLA)^17,IF(S25<=IRMAA_Single_Thresh2*(1+TaxBracketInflation)^17,IRMAA_Single_Cost2*(1+SSCOLA)^17,IF(S25<=IRMAA_Single_Thresh3*(1+TaxBracketInflation)^17,IRMAA_Single_Cost3*(1+SSCOLA)^17,IF(S25<=IRMAA_Single_Thresh4*(1+TaxBracketInflation)^17,IRMAA_Single_Cost4*(1+SSCOLA)^17,IF(S25<=IRMAA_Single_Thresh5*(1+TaxBracketInflation)^17,IRMAA_Single_Cost5*(1+SSCOLA)^17,IRMAA_Single_Cost6*(1+SSCOLA)^17)))))) | T26: =IF(T4,IF(T25<=IRMAA_MFJ_Thresh1*(1+TaxBracketInflation)^18,IRMAA_MFJ_Cost1*(1+SSCOLA)^18,IF(T25<=IRMAA_MFJ_Thresh2*(1+TaxBracketInflation)^18,IRMAA_MFJ_Cost2*(1+SSCOLA)^18,IF(T25<=IRMAA_MFJ_Thresh3*(1+TaxBracketInflation)^18,IRMAA_MFJ_Cost3*(1+SSCOLA)^18,IF(T25<=IRMAA_MFJ_Thresh4*(1+TaxBracketInflation)^18,IRMAA_MFJ_Cost4*(1+SSCOLA)^18,IF(T25<=IRMAA_MFJ_Thresh5*(1+TaxBracketInflation)^18,IRMAA_MFJ_Cost5*(1+SSCOLA)^18,IRMAA_MFJ_Cost6*(1+SSCOLA)^18))))),IF(T25<=IRMAA_Single_Thresh1*(1+TaxBracketInflation)^18,IRMAA_Single_Cost1*(1+SSCOLA)^18,IF(T25<=IRMAA_Single_Thresh2*(1+TaxBracketInflation)^18,IRMAA_Single_Cost2*(1+SSCOLA)^18,IF(T25<=IRMAA_Single_Thresh3*(1+TaxBracketInflation)^18,IRMAA_Single_Cost3*(1+SSCOLA)^18,IF(T25<=IRMAA_Single_Thresh4*(1+TaxBracketInflation)^18,IRMAA_Single_Cost4*(1+SSCOLA)^18,IF(T25<=IRMAA_Single_Thresh5*(1+TaxBracketInflation)^18,IRMAA_Single_Cost5*(1+SSCOLA)^18,IRMAA_Single_Cost6*(1+SSCOLA)^18)))))) | U26: =IF(U4,IF(U25<=IRMAA_MFJ_Thresh1*(1+TaxBracketInflation)^19,IRMAA_MFJ_Cost1*(1+SSCOLA)^19,IF(U25<=IRMAA_MFJ_Thresh2*(1+TaxBracketInflation)^19,IRMAA_MFJ_Cost2*(1+SSCOLA)^19,IF(U25<=IRMAA_MFJ_Thresh3*(1+TaxBracketInflation)^19,IRMAA_MFJ_Cost3*(1+SSCOLA)^19,IF(U25<=IRMAA_MFJ_Thresh4*(1+TaxBracketInflation)^19,IRMAA_MFJ_Cost4*(1+SSCOLA)^19,IF(U25<=IRMAA_MFJ_Thresh5*(1+TaxBracketInflation)^19,IRMAA_MFJ_Cost5*(1+SSCOLA)^19,IRMAA_MFJ_Cost6*(1+SSCOLA)^19))))),IF(U25<=IRMAA_Single_Thresh1*(1+TaxBracketInflation)^19,IRMAA_Single_Cost1*(1+SSCOLA)^19,IF(U25<=IRMAA_Single_Thresh2*(1+TaxBracketInflation)^19,IRMAA_Single_Cost2*(1+SSCOLA)^19,IF(U25<=IRMAA_Single_Thresh3*(1+TaxBracketInflation)^19,IRMAA_Single_Cost3*(1+SSCOLA)^19,IF(U25<=IRMAA_Single_Thresh4*(1+TaxBracketInflation)^19,IRMAA_Single_Cost4*(1+SSCOLA)^19,IF(U25<=IRMAA_Single_Thresh5*(1+TaxBracketInflation)^19,IRMAA_Single_Cost5*(1+SSCOLA)^19,IRMAA_Single_Cost6*(1+SSCOLA)^19)))))) | V26: =IF(V4,IF(V25<=IRMAA_MFJ_Thresh1*(1+TaxBracketInflation)^20,IRMAA_MFJ_Cost1*(1+SSCOLA)^20,IF(V25<=IRMAA_MFJ_Thresh2*(1+TaxBracketInflation)^20,IRMAA_MFJ_Cost2*(1+SSCOLA)^20,IF(V25<=IRMAA_MFJ_Thresh3*(1+TaxBracketInflation)^20,IRMAA_MFJ_Cost3*(1+SSCOLA)^20,IF(V25<=IRMAA_MFJ_Thresh4*(1+TaxBracketInflation)^20,IRMAA_MFJ_Cost4*(1+SSCOLA)^20,IF(V25<=IRMAA_MFJ_Thresh5*(1+TaxBracketInflation)^20,IRMAA_MFJ_Cost5*(1+SSCOLA)^20,IRMAA_MFJ_Cost6*(1+SSCOLA)^20))))),IF(V25<=IRMAA_Single_Thresh1*(1+TaxBracketInflation)^20,IRMAA_Single_Cost1*(1+SSCOLA)^20,IF(V25<=IRMAA_Single_Thresh2*(1+TaxBracketInflation)^20,IRMAA_Single_Cost2*(1+SSCOLA)^20,IF(V25<=IRMAA_Single_Thresh3*(1+TaxBracketInflation)^20,IRMAA_Single_Cost3*(1+SSCOLA)^20,IF(V25<=IRMAA_Single_Thresh4*(1+TaxBracketInflation)^20,IRMAA_Single_Cost4*(1+SSCOLA)^20,IF(V25<=IRMAA_Single_Thresh5*(1+TaxBracketInflation)^20,IRMAA_Single_Cost5*(1+SSCOLA)^20,IRMAA_Single_Cost6*(1+SSCOLA)^20)))))) | W26: =IF(W4,IF(W25<=IRMAA_MFJ_Thresh1*(1+TaxBracketInflation)^21,IRMAA_MFJ_Cost1*(1+SSCOLA)^21,IF(W25<=IRMAA_MFJ_Thresh2*(1+TaxBracketInflation)^21,IRMAA_MFJ_Cost2*(1+SSCOLA)^21,IF(W25<=IRMAA_MFJ_Thresh3*(1+TaxBracketInflation)^21,IRMAA_MFJ_Cost3*(1+SSCOLA)^21,IF(W25<=IRMAA_MFJ_Thresh4*(1+TaxBracketInflation)^21,IRMAA_MFJ_Cost4*(1+SSCOLA)^21,IF(W25<=IRMAA_MFJ_Thresh5*(1+TaxBracketInflation)^21,IRMAA_MFJ_Cost5*(1+SSCOLA)^21,IRMAA_MFJ_Cost6*(1+SSCOLA)^21))))),IF(W25<=IRMAA_Single_Thresh1*(1+TaxBracketInflation)^21,IRMAA_Single_Cost1*(1+SSCOLA)^21,IF(W25<=IRMAA_Single_Thresh2*(1+TaxBracketInflation)^21,IRMAA_Single_Cost2*(1+SSCOLA)^21,IF(W25<=IRMAA_Single_Thresh3*(1+TaxBracketInflation)^21,IRMAA_Single_Cost3*(1+SSCOLA)^21,IF(W25<=IRMAA_Single_Thresh4*(1+TaxBracketInflation)^21,IRMAA_Single_Cost4*(1+SSCOLA)^21,IF(W25<=IRMAA_Single_Thresh5*(1+TaxBracketInflation)^21,IRMAA_Single_Cost5*(1+SSCOLA)^21,IRMAA_Single_Cost6*(1+SSCOLA)^21)))))) | X26: =IF(X4,IF(X25<=IRMAA_MFJ_Thresh1*(1+TaxBracketInflation)^22,IRMAA_MFJ_Cost1*(1+SSCOLA)^22,IF(X25<=IRMAA_MFJ_Thresh2*(1+TaxBracketInflation)^22,IRMAA_MFJ_Cost2*(1+SSCOLA)^22,IF(X25<=IRMAA_MFJ_Thresh3*(1+TaxBracketInflation)^22,IRMAA_MFJ_Cost3*(1+SSCOLA)^22,IF(X25<=IRMAA_MFJ_Thresh4*(1+TaxBracketInflation)^22,IRMAA_MFJ_Cost4*(1+SSCOLA)^22,IF(X25<=IRMAA_MFJ_Thresh5*(1+TaxBracketInflation)^22,IRMAA_MFJ_Cost5*(1+SSCOLA)^22,IRMAA_MFJ_Cost6*(1+SSCOLA)^22))))),IF(X25<=IRMAA_Single_Thresh1*(1+TaxBracketInflation)^22,IRMAA_Single_Cost1*(1+SSCOLA)^22,IF(X25<=IRMAA_Single_Thresh2*(1+TaxBracketInflation)^22,IRMAA_Single_Cost2*(1+SSCOLA)^22,IF(X25<=IRMAA_Single_Thresh3*(1+TaxBracketInflation)^22,IRMAA_Single_Cost3*(1+SSCOLA)^22,IF(X25<=IRMAA_Single_Thresh4*(1+TaxBracketInflation)^22,IRMAA_Single_Cost4*(1+SSCOLA)^22,IF(X25<=IRMAA_Single_Thresh5*(1+TaxBracketInflation)^22,IRMAA_Single_Cost5*(1+SSCOLA)^22,IRMAA_Single_Cost6*(1+SSCOLA)^22)))))) | Y26: =IF(Y4,IF(Y25<=IRMAA_MFJ_Thresh1*(1+TaxBracketInflation)^23,IRMAA_MFJ_Cost1*(1+SSCOLA)^23,IF(Y25<=IRMAA_MFJ_Thresh2*(1+TaxBracketInflation)^23,IRMAA_MFJ_Cost2*(1+SSCOLA)^23,IF(Y25<=IRMAA_MFJ_Thresh3*(1+TaxBracketInflation)^23,IRMAA_MFJ_Cost3*(1+SSCOLA)^23,IF(Y25<=IRMAA_MFJ_Thresh4*(1+TaxBracketInflation)^23,IRMAA_MFJ_Cost4*(1+SSCOLA)^23,IF(Y25<=IRMAA_MFJ_Thresh5*(1+TaxBracketInflation)^23,IRMAA_MFJ_Cost5*(1+SSCOLA)^23,IRMAA_MFJ_Cost6*(1+SSCOLA)^23))))),IF(Y25<=IRMAA_Single_Thresh1*(1+TaxBracketInflation)^23,IRMAA_Single_Cost1*(1+SSCOLA)^23,IF(Y25<=IRMAA_Single_Thresh2*(1+TaxBracketInflation)^23,IRMAA_Single_Cost2*(1+SSCOLA)^23,IF(Y25<=IRMAA_Single_Thresh3*(1+TaxBracketInflation)^23,IRMAA_Single_Cost3*(1+SSCOLA)^23,IF(Y25<=IRMAA_Single_Thresh4*(1+TaxBracketInflation)^23,IRMAA_Single_Cost4*(1+SSCOLA)^23,IF(Y25<=IRMAA_Single_Thresh5*(1+TaxBracketInflation)^23,IRMAA_Single_Cost5*(1+SSCOLA)^23,IRMAA_Single_Cost6*(1+SSCOLA)^23)))))) | Z26: =IF(Z4,IF(Z25<=IRMAA_MFJ_Thresh1*(1+TaxBracketInflation)^24,IRMAA_MFJ_Cost1*(1+SSCOLA)^24,IF(Z25<=IRMAA_MFJ_Thresh2*(1+TaxBracketInflation)^24,IRMAA_MFJ_Cost2*(1+SSCOLA)^24,IF(Z25<=IRMAA_MFJ_Thresh3*(1+TaxBracketInflation)^24,IRMAA_MFJ_Cost3*(1+SSCOLA)^24,IF(Z25<=IRMAA_MFJ_Thresh4*(1+TaxBracketInflation)^24,IRMAA_MFJ_Cost4*(1+SSCOLA)^24,IF(Z25<=IRMAA_MFJ_Thresh5*(1+TaxBracketInflation)^24,IRMAA_MFJ_Cost5*(1+SSCOLA)^24,IRMAA_MFJ_Cost6*(1+SSCOLA)^24))))),IF(Z25<=IRMAA_Single_Thresh1*(1+TaxBracketInflation)^24,IRMAA_Single_Cost1*(1+SSCOLA)^24,IF(Z25<=IRMAA_Single_Thresh2*(1+TaxBracketInflation)^24,IRMAA_Single_Cost2*(1+SSCOLA)^24,IF(Z25<=IRMAA_Single_Thresh3*(1+TaxBracketInflation)^24,IRMAA_Single_Cost3*(1+SSCOLA)^24,IF(Z25<=IRMAA_Single_Thresh4*(1+TaxBracketInflation)^24,IRMAA_Single_Cost4*(1+SSCOLA)^24,IF(Z25<=IRMAA_Single_Thresh5*(1+TaxBracketInflation)^24,IRMAA_Single_Cost5*(1+SSCOLA)^24,IRMAA_Single_Cost6*(1+SSCOLA)^24)))))) | AA26: =IF(AA4,IF(AA25<=IRMAA_MFJ_Thresh1*(1+TaxBracketInflation)^25,IRMAA_MFJ_Cost1*(1+SSCOLA)^25,IF(AA25<=IRMAA_MFJ_Thresh2*(1+TaxBracketInflation)^25,IRMAA_MFJ_Cost2*(1+SSCOLA)^25,IF(AA25<=IRMAA_MFJ_Thresh3*(1+TaxBracketInflation)^25,IRMAA_MFJ_Cost3*(1+SSCOLA)^25,IF(AA25<=IRMAA_MFJ_Thresh4*(1+TaxBracketInflation)^25,IRMAA_MFJ_Cost4*(1+SSCOLA)^25,IF(AA25<=IRMAA_MFJ_Thresh5*(1+TaxBracketInflation)^25,IRMAA_MFJ_Cost5*(1+SSCOLA)^25,IRMAA_MFJ_Cost6*(1+SSCOLA)^25))))),IF(AA25<=IRMAA_Single_Thresh1*(1+TaxBracketInflation)^25,IRMAA_Single_Cost1*(1+SSCOLA)^25,IF(AA25<=IRMAA_Single_Thresh2*(1+TaxBracketInflation)^25,IRMAA_Single_Cost2*(1+SSCOLA)^25,IF(AA25<=IRMAA_Single_Thresh3*(1+TaxBracketInflation)^25,IRMAA_Single_Cost3*(1+SSCOLA)^25,IF(AA25<=IRMAA_Single_Thresh4*(1+TaxBracketInflation)^25,IRMAA_Single_Cost4*(1+SSCOLA)^25,IF(AA25<=IRMAA_Single_Thresh5*(1+TaxBracketInflation)^25,IRMAA_Single_Cost5*(1+SSCOLA)^25,IRMAA_Single_Cost6*(1+SSCOLA)^25)))))) | AB26: =IF(AB4,IF(AB25<=IRMAA_MFJ_Thresh1*(1+TaxBracketInflation)^26,IRMAA_MFJ_Cost1*(1+SSCOLA)^26,IF(AB25<=IRMAA_MFJ_Thresh2*(1+TaxBracketInflation)^26,IRMAA_MFJ_Cost2*(1+SSCOLA)^26,IF(AB25<=IRMAA_MFJ_Thresh3*(1+TaxBracketInflation)^26,IRMAA_MFJ_Cost3*(1+SSCOLA)^26,IF(AB25<=IRMAA_MFJ_Thresh4*(1+TaxBracketInflation)^26,IRMAA_MFJ_Cost4*(1+SSCOLA)^26,IF(AB25<=IRMAA_MFJ_Thresh5*(1+TaxBracketInflation)^26,IRMAA_MFJ_Cost5*(1+SSCOLA)^26,IRMAA_MFJ_Cost6*(1+SSCOLA)^26))))),IF(AB25<=IRMAA_Single_Thresh1*(1+TaxBracketInflation)^26,IRMAA_Single_Cost1*(1+SSCOLA)^26,IF(AB25<=IRMAA_Single_Thresh2*(1+TaxBracketInflation)^26,IRMAA_Single_Cost2*(1+SSCOLA)^26,IF(AB25<=IRMAA_Single_Thresh3*(1+TaxBracketInflation)^26,IRMAA_Single_Cost3*(1+SSCOLA)^26,IF(AB25<=IRMAA_Single_Thresh4*(1+TaxBracketInflation)^26,IRMAA_Single_Cost4*(1+SSCOLA)^26,IF(AB25<=IRMAA_Single_Thresh5*(1+TaxBracketInflation)^26,IRMAA_Single_Cost5*(1+SSCOLA)^26,IRMAA_Single_Cost6*(1+SSCOLA)^26)))))) | AC26: =IF(AC4,IF(AC25<=IRMAA_MFJ_Thresh1*(1+TaxBracketInflation)^27,IRMAA_MFJ_Cost1*(1+SSCOLA)^27,IF(AC25<=IRMAA_MFJ_Thresh2*(1+TaxBracketInflation)^27,IRMAA_MFJ_Cost2*(1+SSCOLA)^27,IF(AC25<=IRMAA_MFJ_Thresh3*(1+TaxBracketInflation)^27,IRMAA_MFJ_Cost3*(1+SSCOLA)^27,IF(AC25<=IRMAA_MFJ_Thresh4*(1+TaxBracketInflation)^27,IRMAA_MFJ_Cost4*(1+SSCOLA)^27,IF(AC25<=IRMAA_MFJ_Thresh5*(1+TaxBracketInflation)^27,IRMAA_MFJ_Cost5*(1+SSCOLA)^27,IRMAA_MFJ_Cost6*(1+SSCOLA)^27))))),IF(AC25<=IRMAA_Single_Thresh1*(1+TaxBracketInflation)^27,IRMAA_Single_Cost1*(1+SSCOLA)^27,IF(AC25<=IRMAA_Single_Thresh2*(1+TaxBracketInflation)^27,IRMAA_Single_Cost2*(1+SSCOLA)^27,IF(AC25<=IRMAA_Single_Thresh3*(1+TaxBracketInflation)^27,IRMAA_Single_Cost3*(1+SSCOLA)^27,IF(AC25<=IRMAA_Single_Thresh4*(1+TaxBracketInflation)^27,IRMAA_Single_Cost4*(1+SSCOLA)^27,IF(AC25<=IRMAA_Single_Thresh5*(1+TaxBracketInflation)^27,IRMAA_Single_Cost5*(1+SSCOLA)^27,IRMAA_Single_Cost6*(1+SSCOLA)^27)))))) | AD26: =IF(AD4,IF(AD25<=IRMAA_MFJ_Thresh1*(1+TaxBracketInflation)^28,IRMAA_MFJ_Cost1*(1+SSCOLA)^28,IF(AD25<=IRMAA_MFJ_Thresh2*(1+TaxBracketInflation)^28,IRMAA_MFJ_Cost2*(1+SSCOLA)^28,IF(AD25<=IRMAA_MFJ_Thresh3*(1+TaxBracketInflation)^28,IRMAA_MFJ_Cost3*(1+SSCOLA)^28,IF(AD25<=IRMAA_MFJ_Thresh4*(1+TaxBracketInflation)^28,IRMAA_MFJ_Cost4*(1+SSCOLA)^28,IF(AD25<=IRMAA_MFJ_Thresh5*(1+TaxBracketInflation)^28,IRMAA_MFJ_Cost5*(1+SSCOLA)^28,IRMAA_MFJ_Cost6*(1+SSCOLA)^28))))),IF(AD25<=IRMAA_Single_Thresh1*(1+TaxBracketInflation)^28,IRMAA_Single_Cost1*(1+SSCOLA)^28,IF(AD25<=IRMAA_Single_Thresh2*(1+TaxBracketInflation)^28,IRMAA_Single_Cost2*(1+SSCOLA)^28,IF(AD25<=IRMAA_Single_Thresh3*(1+TaxBracketInflation)^28,IRMAA_Single_Cost3*(1+SSCOLA)^28,IF(AD25<=IRMAA_Single_Thresh4*(1+TaxBracketInflation)^28,IRMAA_Single_Cost4*(1+SSCOLA)^28,IF(AD25<=IRMAA_Single_Thresh5*(1+TaxBracketInflation)^28,IRMAA_Single_Cost5*(1+SSCOLA)^28,IRMAA_Single_Cost6*(1+SSCOLA)^28)))))) | AE26: =IF(AE4,IF(AE25<=IRMAA_MFJ_Thresh1*(1+TaxBracketInflation)^29,IRMAA_MFJ_Cost1*(1+SSCOLA)^29,IF(AE25<=IRMAA_MFJ_Thresh2*(1+TaxBracketInflation)^29,IRMAA_MFJ_Cost2*(1+SSCOLA)^29,IF(AE25<=IRMAA_MFJ_Thresh3*(1+TaxBracketInflation)^29,IRMAA_MFJ_Cost3*(1+SSCOLA)^29,IF(AE25<=IRMAA_MFJ_Thresh4*(1+TaxBracketInflation)^29,IRMAA_MFJ_Cost4*(1+SSCOLA)^29,IF(AE25<=IRMAA_MFJ_Thresh5*(1+TaxBracketInflation)^29,IRMAA_MFJ_Cost5*(1+SSCOLA)^29,IRMAA_MFJ_Cost6*(1+SSCOLA)^29))))),IF(AE25<=IRMAA_Single_Thresh1*(1+TaxBracketInflation)^29,IRMAA_Single_Cost1*(1+SSCOLA)^29,IF(AE25<=IRMAA_Single_Thresh2*(1+TaxBracketInflation)^29,IRMAA_Single_Cost2*(1+SSCOLA)^29,IF(AE25<=IRMAA_Single_Thresh3*(1+TaxBracketInflation)^29,IRMAA_Single_Cost3*(1+SSCOLA)^29,IF(AE25<=IRMAA_Single_Thresh4*(1+TaxBracketInflation)^29,IRMAA_Single_Cost4*(1+SSCOLA)^29,IF(AE25<=IRMAA_Single_Thresh5*(1+TaxBracketInflation)^29,IRMAA_Single_Cost5*(1+SSCOLA)^29,IRMAA_Single_Cost6*(1+SSCOLA)^29))))))
A27: Est Tax | B27: =(MAX(0,B14+B16+B17+0.85*B13-(IF(B4,StdDeduction,StdDeductionSingle))*(1+TaxBracketInflation)^0))*0.22+(MAX(0,(MIN(MAX(0,B15+B26-B13-B14),(B7*(1+ReturnAfterTax)+B16)))*CapGainsPct-MAX(0,(IF(B4,94050,47025))*(1+TaxBracketInflation)^0-MAX(0,B14+B16+B17+0.85*B13-(IF(B4,StdDeduction,StdDeductionSingle))*(1+TaxBracketInflation)^0))))*0.15+0.038*MIN((MIN(MAX(0,B15+B26-B13-B14),(B7*(1+ReturnAfterTax)+B16)))*CapGainsPct,MAX(0,(B14+B16+B17+0.85*B13+(MIN(MAX(0,B15+B26-B13-B14),(B7*(1+ReturnAfterTax)+B16)))*CapGainsPct)-(IF(B4,NIITThreshold,NIITThresholdSingle))*(1+TaxBracketInflation)^0))+(B14+(MIN(MAX(0,B15+B26-B13-B14),(B7*(1+ReturnAfterTax)+B16)))*CapGainsPct)*ILTaxRate | C27: =(MAX(0,C14+C16+C17+0.85*C13-(IF(C4,StdDeduction,StdDeductionSingle))*(1+TaxBracketInflation)^1))*0.22+(MAX(0,(MIN(MAX(0,C15+C26-C13-C14),(C7*(1+ReturnAfterTax)+C16)))*CapGainsPct-MAX(0,(IF(C4,94050,47025))*(1+TaxBracketInflation)^1-MAX(0,C14+C16+C17+0.85*C13-(IF(C4,StdDeduction,StdDeductionSingle))*(1+TaxBracketInflation)^1))))*0.15+0.038*MIN((MIN(MAX(0,C15+C26-C13-C14),(C7*(1+ReturnAfterTax)+C16)))*CapGainsPct,MAX(0,(C14+C16+C17+0.85*C13+(MIN(MAX(0,C15+C26-C13-C14),(C7*(1+ReturnAfterTax)+C16)))*CapGainsPct)-(IF(C4,NIITThreshold,NIITThresholdSingle))*(1+TaxBracketInflation)^1))+(C14+(MIN(MAX(0,C15+C26-C13-C14),(C7*(1+ReturnAfterTax)+C16)))*CapGainsPct)*ILTaxRate | D27: =(MAX(0,D14+D16+D17+0.85*D13-(IF(D4,StdDeduction,StdDeductionSingle))*(1+TaxBracketInflation)^2))*0.22+(MAX(0,(MIN(MAX(0,D15+D26-D13-D14),(D7*(1+ReturnAfterTax)+D16)))*CapGainsPct-MAX(0,(IF(D4,94050,47025))*(1+TaxBracketInflation)^2-MAX(0,D14+D16+D17+0.85*D13-(IF(D4,StdDeduction,StdDeductionSingle))*(1+TaxBracketInflation)^2))))*0.15+0.038*MIN((MIN(MAX(0,D15+D26-D13-D14),(D7*(1+ReturnAfterTax)+D16)))*CapGainsPct,MAX(0,(D14+D16+D17+0.85*D13+(MIN(MAX(0,D15+D26-D13-D14),(D7*(1+ReturnAfterTax)+D16)))*CapGainsPct)-(IF(D4,NIITThreshold,NIITThresholdSingle))*(1+TaxBracketInflation)^2))+(D14+(MIN(MAX(0,D15+D26-D13-D14),(D7*(1+ReturnAfterTax)+D16)))*CapGainsPct)*ILTaxRate | E27: =(MAX(0,E14+E16+E17+0.85*E13-(IF(E4,StdDeduction,StdDeductionSingle))*(1+TaxBracketInflation)^3))*0.22+(MAX(0,(MIN(MAX(0,E15+E26-E13-E14),(E7*(1+ReturnAfterTax)+E16)))*CapGainsPct-MAX(0,(IF(E4,94050,47025))*(1+TaxBracketInflation)^3-MAX(0,E14+E16+E17+0.85*E13-(IF(E4,StdDeduction,StdDeductionSingle))*(1+TaxBracketInflation)^3))))*0.15+0.038*MIN((MIN(MAX(0,E15+E26-E13-E14),(E7*(1+ReturnAfterTax)+E16)))*CapGainsPct,MAX(0,(E14+E16+E17+0.85*E13+(MIN(MAX(0,E15+E26-E13-E14),(E7*(1+ReturnAfterTax)+E16)))*CapGainsPct)-(IF(E4,NIITThreshold,NIITThresholdSingle))*(1+TaxBracketInflation)^3))+(E14+(MIN(MAX(0,E15+E26-E13-E14),(E7*(1+ReturnAfterTax)+E16)))*CapGainsPct)*ILTaxRate | F27: =(MAX(0,F14+F16+F17+0.85*F13-(IF(F4,StdDeduction,StdDeductionSingle))*(1+TaxBracketInflation)^4))*0.22+(MAX(0,(MIN(MAX(0,F15+F26-F13-F14),(F7*(1+ReturnAfterTax)+F16)))*CapGainsPct-MAX(0,(IF(F4,94050,47025))*(1+TaxBracketInflation)^4-MAX(0,F14+F16+F17+0.85*F13-(IF(F4,StdDeduction,StdDeductionSingle))*(1+TaxBracketInflation)^4))))*0.15+0.038*MIN((MIN(MAX(0,F15+F26-F13-F14),(F7*(1+ReturnAfterTax)+F16)))*CapGainsPct,MAX(0,(F14+F16+F17+0.85*F13+(MIN(MAX(0,F15+F26-F13-F14),(F7*(1+ReturnAfterTax)+F16)))*CapGainsPct)-(IF(F4,NIITThreshold,NIITThresholdSingle))*(1+TaxBracketInflation)^4))+(F14+(MIN(MAX(0,F15+F26-F13-F14),(F7*(1+ReturnAfterTax)+F16)))*CapGainsPct)*ILTaxRate | G27: =(MAX(0,G14+G16+G17+0.85*G13-(IF(G4,StdDeduction,StdDeductionSingle))*(1+TaxBracketInflation)^5))*0.22+(MAX(0,(MIN(MAX(0,G15+G26-G13-G14),(G7*(1+ReturnAfterTax)+G16)))*CapGainsPct-MAX(0,(IF(G4,94050,47025))*(1+TaxBracketInflation)^5-MAX(0,G14+G16+G17+0.85*G13-(IF(G4,StdDeduction,StdDeductionSingle))*(1+TaxBracketInflation)^5))))*0.15+0.038*MIN((MIN(MAX(0,G15+G26-G13-G14),(G7*(1+ReturnAfterTax)+G16)))*CapGainsPct,MAX(0,(G14+G16+G17+0.85*G13+(MIN(MAX(0,G15+G26-G13-G14),(G7*(1+ReturnAfterTax)+G16)))*CapGainsPct)-(IF(G4,NIITThreshold,NIITThresholdSingle))*(1+TaxBracketInflation)^5))+(G14+(MIN(MAX(0,G15+G26-G13-G14),(G7*(1+ReturnAfterTax)+G16)))*CapGainsPct)*ILTaxRate | H27: =(MAX(0,H14+H16+H17+0.85*H13-(IF(H4,StdDeduction,StdDeductionSingle))*(1+TaxBracketInflation)^6))*0.22+(MAX(0,(MIN(MAX(0,H15+H26-H13-H14),(H7*(1+ReturnAfterTax)+H16)))*CapGainsPct-MAX(0,(IF(H4,94050,47025))*(1+TaxBracketInflation)^6-MAX(0,H14+H16+H17+0.85*H13-(IF(H4,StdDeduction,StdDeductionSingle))*(1+TaxBracketInflation)^6))))*0.15+0.038*MIN((MIN(MAX(0,H15+H26-H13-H14),(H7*(1+ReturnAfterTax)+H16)))*CapGainsPct,MAX(0,(H14+H16+H17+0.85*H13+(MIN(MAX(0,H15+H26-H13-H14),(H7*(1+ReturnAfterTax)+H16)))*CapGainsPct)-(IF(H4,NIITThreshold,NIITThresholdSingle))*(1+TaxBracketInflation)^6))+(H14+(MIN(MAX(0,H15+H26-H13-H14),(H7*(1+ReturnAfterTax)+H16)))*CapGainsPct)*ILTaxRate | I27: =(MAX(0,I14+I16+I17+0.85*I13-(IF(I4,StdDeduction,StdDeductionSingle))*(1+TaxBracketInflation)^7))*0.22+(MAX(0,(MIN(MAX(0,I15+I26-I13-I14),(I7*(1+ReturnAfterTax)+I16)))*CapGainsPct-MAX(0,(IF(I4,94050,47025))*(1+TaxBracketInflation)^7-MAX(0,I14+I16+I17+0.85*I13-(IF(I4,StdDeduction,StdDeductionSingle))*(1+TaxBracketInflation)^7))))*0.15+0.038*MIN((MIN(MAX(0,I15+I26-I13-I14),(I7*(1+ReturnAfterTax)+I16)))*CapGainsPct,MAX(0,(I14+I16+I17+0.85*I13+(MIN(MAX(0,I15+I26-I13-I14),(I7*(1+ReturnAfterTax)+I16)))*CapGainsPct)-(IF(I4,NIITThreshold,NIITThresholdSingle))*(1+TaxBracketInflation)^7))+(I14+(MIN(MAX(0,I15+I26-I13-I14),(I7*(1+ReturnAfterTax)+I16)))*CapGainsPct)*ILTaxRate | J27: =(MAX(0,J14+J16+J17+0.85*J13-(IF(J4,StdDeduction,StdDeductionSingle))*(1+TaxBracketInflation)^8))*0.22+(MAX(0,(MIN(MAX(0,J15+J26-J13-J14),(J7*(1+ReturnAfterTax)+J16)))*CapGainsPct-MAX(0,(IF(J4,94050,47025))*(1+TaxBracketInflation)^8-MAX(0,J14+J16+J17+0.85*J13-(IF(J4,StdDeduction,StdDeductionSingle))*(1+TaxBracketInflation)^8))))*0.15+0.038*MIN((MIN(MAX(0,J15+J26-J13-J14),(J7*(1+ReturnAfterTax)+J16)))*CapGainsPct,MAX(0,(J14+J16+J17+0.85*J13+(MIN(MAX(0,J15+J26-J13-J14),(J7*(1+ReturnAfterTax)+J16)))*CapGainsPct)-(IF(J4,NIITThreshold,NIITThresholdSingle))*(1+TaxBracketInflation)^8))+(J14+(MIN(MAX(0,J15+J26-J13-J14),(J7*(1+ReturnAfterTax)+J16)))*CapGainsPct)*ILTaxRate | K27: =(MAX(0,K14+K16+K17+0.85*K13-(IF(K4,StdDeduction,StdDeductionSingle))*(1+TaxBracketInflation)^9))*0.22+(MAX(0,(MIN(MAX(0,K15+K26-K13-K14),(K7*(1+ReturnAfterTax)+K16)))*CapGainsPct-MAX(0,(IF(K4,94050,47025))*(1+TaxBracketInflation)^9-MAX(0,K14+K16+K17+0.85*K13-(IF(K4,StdDeduction,StdDeductionSingle))*(1+TaxBracketInflation)^9))))*0.15+0.038*MIN((MIN(MAX(0,K15+K26-K13-K14),(K7*(1+ReturnAfterTax)+K16)))*CapGainsPct,MAX(0,(K14+K16+K17+0.85*K13+(MIN(MAX(0,K15+K26-K13-K14),(K7*(1+ReturnAfterTax)+K16)))*CapGainsPct)-(IF(K4,NIITThreshold,NIITThresholdSingle))*(1+TaxBracketInflation)^9))+(K14+(MIN(MAX(0,K15+K26-K13-K14),(K7*(1+ReturnAfterTax)+K16)))*CapGainsPct)*ILTaxRate | L27: =(MAX(0,L14+L16+L17+0.85*L13-(IF(L4,StdDeduction,StdDeductionSingle))*(1+TaxBracketInflation)^10))*0.22+(MAX(0,(MIN(MAX(0,L15+L26-L13-L14),(L7*(1+ReturnAfterTax)+L16)))*CapGainsPct-MAX(0,(IF(L4,94050,47025))*(1+TaxBracketInflation)^10-MAX(0,L14+L16+L17+0.85*L13-(IF(L4,StdDeduction,StdDeductionSingle))*(1+TaxBracketInflation)^10))))*0.15+0.038*MIN((MIN(MAX(0,L15+L26-L13-L14),(L7*(1+ReturnAfterTax)+L16)))*CapGainsPct,MAX(0,(L14+L16+L17+0.85*L13+(MIN(MAX(0,L15+L26-L13-L14),(L7*(1+ReturnAfterTax)+L16)))*CapGainsPct)-(IF(L4,NIITThreshold,NIITThresholdSingle))*(1+TaxBracketInflation)^10))+(L14+(MIN(MAX(0,L15+L26-L13-L14),(L7*(1+ReturnAfterTax)+L16)))*CapGainsPct)*ILTaxRate | M27: =(MAX(0,M14+M16+M17+0.85*M13-(IF(M4,StdDeduction,StdDeductionSingle))*(1+TaxBracketInflation)^11))*0.22+(MAX(0,(MIN(MAX(0,M15+M26-M13-M14),(M7*(1+ReturnAfterTax)+M16)))*CapGainsPct-MAX(0,(IF(M4,94050,47025))*(1+TaxBracketInflation)^11-MAX(0,M14+M16+M17+0.85*M13-(IF(M4,StdDeduction,StdDeductionSingle))*(1+TaxBracketInflation)^11))))*0.15+0.038*MIN((MIN(MAX(0,M15+M26-M13-M14),(M7*(1+ReturnAfterTax)+M16)))*CapGainsPct,MAX(0,(M14+M16+M17+0.85*M13+(MIN(MAX(0,M15+M26-M13-M14),(M7*(1+ReturnAfterTax)+M16)))*CapGainsPct)-(IF(M4,NIITThreshold,NIITThresholdSingle))*(1+TaxBracketInflation)^11))+(M14+(MIN(MAX(0,M15+M26-M13-M14),(M7*(1+ReturnAfterTax)+M16)))*CapGainsPct)*ILTaxRate | N27: =(MAX(0,N14+N16+N17+0.85*N13-(IF(N4,StdDeduction,StdDeductionSingle))*(1+TaxBracketInflation)^12))*0.22+(MAX(0,(MIN(MAX(0,N15+N26-N13-N14),(N7*(1+ReturnAfterTax)+N16)))*CapGainsPct-MAX(0,(IF(N4,94050,47025))*(1+TaxBracketInflation)^12-MAX(0,N14+N16+N17+0.85*N13-(IF(N4,StdDeduction,StdDeductionSingle))*(1+TaxBracketInflation)^12))))*0.15+0.038*MIN((MIN(MAX(0,N15+N26-N13-N14),(N7*(1+ReturnAfterTax)+N16)))*CapGainsPct,MAX(0,(N14+N16+N17+0.85*N13+(MIN(MAX(0,N15+N26-N13-N14),(N7*(1+ReturnAfterTax)+N16)))*CapGainsPct)-(IF(N4,NIITThreshold,NIITThresholdSingle))*(1+TaxBracketInflation)^12))+(N14+(MIN(MAX(0,N15+N26-N13-N14),(N7*(1+ReturnAfterTax)+N16)))*CapGainsPct)*ILTaxRate | O27: =(MAX(0,O14+O16+O17+0.85*O13-(IF(O4,StdDeduction,StdDeductionSingle))*(1+TaxBracketInflation)^13))*0.22+(MAX(0,(MIN(MAX(0,O15+O26-O13-O14),(O7*(1+ReturnAfterTax)+O16)))*CapGainsPct-MAX(0,(IF(O4,94050,47025))*(1+TaxBracketInflation)^13-MAX(0,O14+O16+O17+0.85*O13-(IF(O4,StdDeduction,StdDeductionSingle))*(1+TaxBracketInflation)^13))))*0.15+0.038*MIN((MIN(MAX(0,O15+O26-O13-O14),(O7*(1+ReturnAfterTax)+O16)))*CapGainsPct,MAX(0,(O14+O16+O17+0.85*O13+(MIN(MAX(0,O15+O26-O13-O14),(O7*(1+ReturnAfterTax)+O16)))*CapGainsPct)-(IF(O4,NIITThreshold,NIITThresholdSingle))*(1+TaxBracketInflation)^13))+(O14+(MIN(MAX(0,O15+O26-O13-O14),(O7*(1+ReturnAfterTax)+O16)))*CapGainsPct)*ILTaxRate | P27: =(MAX(0,P14+P16+P17+0.85*P13-(IF(P4,StdDeduction,StdDeductionSingle))*(1+TaxBracketInflation)^14))*0.22+(MAX(0,(MIN(MAX(0,P15+P26-P13-P14),(P7*(1+ReturnAfterTax)+P16)))*CapGainsPct-MAX(0,(IF(P4,94050,47025))*(1+TaxBracketInflation)^14-MAX(0,P14+P16+P17+0.85*P13-(IF(P4,StdDeduction,StdDeductionSingle))*(1+TaxBracketInflation)^14))))*0.15+0.038*MIN((MIN(MAX(0,P15+P26-P13-P14),(P7*(1+ReturnAfterTax)+P16)))*CapGainsPct,MAX(0,(P14+P16+P17+0.85*P13+(MIN(MAX(0,P15+P26-P13-P14),(P7*(1+ReturnAfterTax)+P16)))*CapGainsPct)-(IF(P4,NIITThreshold,NIITThresholdSingle))*(1+TaxBracketInflation)^14))+(P14+(MIN(MAX(0,P15+P26-P13-P14),(P7*(1+ReturnAfterTax)+P16)))*CapGainsPct)*ILTaxRate | Q27: =(MAX(0,Q14+Q16+Q17+0.85*Q13-(IF(Q4,StdDeduction,StdDeductionSingle))*(1+TaxBracketInflation)^15))*0.22+(MAX(0,(MIN(MAX(0,Q15+Q26-Q13-Q14),(Q7*(1+ReturnAfterTax)+Q16)))*CapGainsPct-MAX(0,(IF(Q4,94050,47025))*(1+TaxBracketInflation)^15-MAX(0,Q14+Q16+Q17+0.85*Q13-(IF(Q4,StdDeduction,StdDeductionSingle))*(1+TaxBracketInflation)^15))))*0.15+0.038*MIN((MIN(MAX(0,Q15+Q26-Q13-Q14),(Q7*(1+ReturnAfterTax)+Q16)))*CapGainsPct,MAX(0,(Q14+Q16+Q17+0.85*Q13+(MIN(MAX(0,Q15+Q26-Q13-Q14),(Q7*(1+ReturnAfterTax)+Q16)))*CapGainsPct)-(IF(Q4,NIITThreshold,NIITThresholdSingle))*(1+TaxBracketInflation)^15))+(Q14+(MIN(MAX(0,Q15+Q26-Q13-Q14),(Q7*(1+ReturnAfterTax)+Q16)))*CapGainsPct)*ILTaxRate | R27: =(MAX(0,R14+R16+R17+0.85*R13-(IF(R4,StdDeduction,StdDeductionSingle))*(1+TaxBracketInflation)^16))*0.22+(MAX(0,(MIN(MAX(0,R15+R26-R13-R14),(R7*(1+ReturnAfterTax)+R16)))*CapGainsPct-MAX(0,(IF(R4,94050,47025))*(1+TaxBracketInflation)^16-MAX(0,R14+R16+R17+0.85*R13-(IF(R4,StdDeduction,StdDeductionSingle))*(1+TaxBracketInflation)^16))))*0.15+0.038*MIN((MIN(MAX(0,R15+R26-R13-R14),(R7*(1+ReturnAfterTax)+R16)))*CapGainsPct,MAX(0,(R14+R16+R17+0.85*R13+(MIN(MAX(0,R15+R26-R13-R14),(R7*(1+ReturnAfterTax)+R16)))*CapGainsPct)-(IF(R4,NIITThreshold,NIITThresholdSingle))*(1+TaxBracketInflation)^16))+(R14+(MIN(MAX(0,R15+R26-R13-R14),(R7*(1+ReturnAfterTax)+R16)))*CapGainsPct)*ILTaxRate | S27: =(MAX(0,S14+S16+S17+0.85*S13-(IF(S4,StdDeduction,StdDeductionSingle))*(1+TaxBracketInflation)^17))*0.22+(MAX(0,(MIN(MAX(0,S15+S26-S13-S14),(S7*(1+ReturnAfterTax)+S16)))*CapGainsPct-MAX(0,(IF(S4,94050,47025))*(1+TaxBracketInflation)^17-MAX(0,S14+S16+S17+0.85*S13-(IF(S4,StdDeduction,StdDeductionSingle))*(1+TaxBracketInflation)^17))))*0.15+0.038*MIN((MIN(MAX(0,S15+S26-S13-S14),(S7*(1+ReturnAfterTax)+S16)))*CapGainsPct,MAX(0,(S14+S16+S17+0.85*S13+(MIN(MAX(0,S15+S26-S13-S14),(S7*(1+ReturnAfterTax)+S16)))*CapGainsPct)-(IF(S4,NIITThreshold,NIITThresholdSingle))*(1+TaxBracketInflation)^17))+(S14+(MIN(MAX(0,S15+S26-S13-S14),(S7*(1+ReturnAfterTax)+S16)))*CapGainsPct)*ILTaxRate | T27: =(MAX(0,T14+T16+T17+0.85*T13-(IF(T4,StdDeduction,StdDeductionSingle))*(1+TaxBracketInflation)^18))*0.22+(MAX(0,(MIN(MAX(0,T15+T26-T13-T14),(T7*(1+ReturnAfterTax)+T16)))*CapGainsPct-MAX(0,(IF(T4,94050,47025))*(1+TaxBracketInflation)^18-MAX(0,T14+T16+T17+0.85*T13-(IF(T4,StdDeduction,StdDeductionSingle))*(1+TaxBracketInflation)^18))))*0.15+0.038*MIN((MIN(MAX(0,T15+T26-T13-T14),(T7*(1+ReturnAfterTax)+T16)))*CapGainsPct,MAX(0,(T14+T16+T17+0.85*T13+(MIN(MAX(0,T15+T26-T13-T14),(T7*(1+ReturnAfterTax)+T16)))*CapGainsPct)-(IF(T4,NIITThreshold,NIITThresholdSingle))*(1+TaxBracketInflation)^18))+(T14+(MIN(MAX(0,T15+T26-T13-T14),(T7*(1+ReturnAfterTax)+T16)))*CapGainsPct)*ILTaxRate | U27: =(MAX(0,U14+U16+U17+0.85*U13-(IF(U4,StdDeduction,StdDeductionSingle))*(1+TaxBracketInflation)^19))*0.22+(MAX(0,(MIN(MAX(0,U15+U26-U13-U14),(U7*(1+ReturnAfterTax)+U16)))*CapGainsPct-MAX(0,(IF(U4,94050,47025))*(1+TaxBracketInflation)^19-MAX(0,U14+U16+U17+0.85*U13-(IF(U4,StdDeduction,StdDeductionSingle))*(1+TaxBracketInflation)^19))))*0.15+0.038*MIN((MIN(MAX(0,U15+U26-U13-U14),(U7*(1+ReturnAfterTax)+U16)))*CapGainsPct,MAX(0,(U14+U16+U17+0.85*U13+(MIN(MAX(0,U15+U26-U13-U14),(U7*(1+ReturnAfterTax)+U16)))*CapGainsPct)-(IF(U4,NIITThreshold,NIITThresholdSingle))*(1+TaxBracketInflation)^19))+(U14+(MIN(MAX(0,U15+U26-U13-U14),(U7*(1+ReturnAfterTax)+U16)))*CapGainsPct)*ILTaxRate | V27: =(MAX(0,V14+V16+V17+0.85*V13-(IF(V4,StdDeduction,StdDeductionSingle))*(1+TaxBracketInflation)^20))*0.22+(MAX(0,(MIN(MAX(0,V15+V26-V13-V14),(V7*(1+ReturnAfterTax)+V16)))*CapGainsPct-MAX(0,(IF(V4,94050,47025))*(1+TaxBracketInflation)^20-MAX(0,V14+V16+V17+0.85*V13-(IF(V4,StdDeduction,StdDeductionSingle))*(1+TaxBracketInflation)^20))))*0.15+0.038*MIN((MIN(MAX(0,V15+V26-V13-V14),(V7*(1+ReturnAfterTax)+V16)))*CapGainsPct,MAX(0,(V14+V16+V17+0.85*V13+(MIN(MAX(0,V15+V26-V13-V14),(V7*(1+ReturnAfterTax)+V16)))*CapGainsPct)-(IF(V4,NIITThreshold,NIITThresholdSingle))*(1+TaxBracketInflation)^20))+(V14+(MIN(MAX(0,V15+V26-V13-V14),(V7*(1+ReturnAfterTax)+V16)))*CapGainsPct)*ILTaxRate | W27: =(MAX(0,W14+W16+W17+0.85*W13-(IF(W4,StdDeduction,StdDeductionSingle))*(1+TaxBracketInflation)^21))*0.22+(MAX(0,(MIN(MAX(0,W15+W26-W13-W14),(W7*(1+ReturnAfterTax)+W16)))*CapGainsPct-MAX(0,(IF(W4,94050,47025))*(1+TaxBracketInflation)^21-MAX(0,W14+W16+W17+0.85*W13-(IF(W4,StdDeduction,StdDeductionSingle))*(1+TaxBracketInflation)^21))))*0.15+0.038*MIN((MIN(MAX(0,W15+W26-W13-W14),(W7*(1+ReturnAfterTax)+W16)))*CapGainsPct,MAX(0,(W14+W16+W17+0.85*W13+(MIN(MAX(0,W15+W26-W13-W14),(W7*(1+ReturnAfterTax)+W16)))*CapGainsPct)-(IF(W4,NIITThreshold,NIITThresholdSingle))*(1+TaxBracketInflation)^21))+(W14+(MIN(MAX(0,W15+W26-W13-W14),(W7*(1+ReturnAfterTax)+W16)))*CapGainsPct)*ILTaxRate | X27: =(MAX(0,X14+X16+X17+0.85*X13-(IF(X4,StdDeduction,StdDeductionSingle))*(1+TaxBracketInflation)^22))*0.22+(MAX(0,(MIN(MAX(0,X15+X26-X13-X14),(X7*(1+ReturnAfterTax)+X16)))*CapGainsPct-MAX(0,(IF(X4,94050,47025))*(1+TaxBracketInflation)^22-MAX(0,X14+X16+X17+0.85*X13-(IF(X4,StdDeduction,StdDeductionSingle))*(1+TaxBracketInflation)^22))))*0.15+0.038*MIN((MIN(MAX(0,X15+X26-X13-X14),(X7*(1+ReturnAfterTax)+X16)))*CapGainsPct,MAX(0,(X14+X16+X17+0.85*X13+(MIN(MAX(0,X15+X26-X13-X14),(X7*(1+ReturnAfterTax)+X16)))*CapGainsPct)-(IF(X4,NIITThreshold,NIITThresholdSingle))*(1+TaxBracketInflation)^22))+(X14+(MIN(MAX(0,X15+X26-X13-X14),(X7*(1+ReturnAfterTax)+X16)))*CapGainsPct)*ILTaxRate | Y27: =(MAX(0,Y14+Y16+Y17+0.85*Y13-(IF(Y4,StdDeduction,StdDeductionSingle))*(1+TaxBracketInflation)^23))*0.22+(MAX(0,(MIN(MAX(0,Y15+Y26-Y13-Y14),(Y7*(1+ReturnAfterTax)+Y16)))*CapGainsPct-MAX(0,(IF(Y4,94050,47025))*(1+TaxBracketInflation)^23-MAX(0,Y14+Y16+Y17+0.85*Y13-(IF(Y4,StdDeduction,StdDeductionSingle))*(1+TaxBracketInflation)^23))))*0.15+0.038*MIN((MIN(MAX(0,Y15+Y26-Y13-Y14),(Y7*(1+ReturnAfterTax)+Y16)))*CapGainsPct,MAX(0,(Y14+Y16+Y17+0.85*Y13+(MIN(MAX(0,Y15+Y26-Y13-Y14),(Y7*(1+ReturnAfterTax)+Y16)))*CapGainsPct)-(IF(Y4,NIITThreshold,NIITThresholdSingle))*(1+TaxBracketInflation)^23))+(Y14+(MIN(MAX(0,Y15+Y26-Y13-Y14),(Y7*(1+ReturnAfterTax)+Y16)))*CapGainsPct)*ILTaxRate | Z27: =(MAX(0,Z14+Z16+Z17+0.85*Z13-(IF(Z4,StdDeduction,StdDeductionSingle))*(1+TaxBracketInflation)^24))*0.22+(MAX(0,(MIN(MAX(0,Z15+Z26-Z13-Z14),(Z7*(1+ReturnAfterTax)+Z16)))*CapGainsPct-MAX(0,(IF(Z4,94050,47025))*(1+TaxBracketInflation)^24-MAX(0,Z14+Z16+Z17+0.85*Z13-(IF(Z4,StdDeduction,StdDeductionSingle))*(1+TaxBracketInflation)^24))))*0.15+0.038*MIN((MIN(MAX(0,Z15+Z26-Z13-Z14),(Z7*(1+ReturnAfterTax)+Z16)))*CapGainsPct,MAX(0,(Z14+Z16+Z17+0.85*Z13+(MIN(MAX(0,Z15+Z26-Z13-Z14),(Z7*(1+ReturnAfterTax)+Z16)))*CapGainsPct)-(IF(Z4,NIITThreshold,NIITThresholdSingle))*(1+TaxBracketInflation)^24))+(Z14+(MIN(MAX(0,Z15+Z26-Z13-Z14),(Z7*(1+ReturnAfterTax)+Z16)))*CapGainsPct)*ILTaxRate | AA27: =(MAX(0,AA14+AA16+AA17+0.85*AA13-(IF(AA4,StdDeduction,StdDeductionSingle))*(1+TaxBracketInflation)^25))*0.22+(MAX(0,(MIN(MAX(0,AA15+AA26-AA13-AA14),(AA7*(1+ReturnAfterTax)+AA16)))*CapGainsPct-MAX(0,(IF(AA4,94050,47025))*(1+TaxBracketInflation)^25-MAX(0,AA14+AA16+AA17+0.85*AA13-(IF(AA4,StdDeduction,StdDeductionSingle))*(1+TaxBracketInflation)^25))))*0.15+0.038*MIN((MIN(MAX(0,AA15+AA26-AA13-AA14),(AA7*(1+ReturnAfterTax)+AA16)))*CapGainsPct,MAX(0,(AA14+AA16+AA17+0.85*AA13+(MIN(MAX(0,AA15+AA26-AA13-AA14),(AA7*(1+ReturnAfterTax)+AA16)))*CapGainsPct)-(IF(AA4,NIITThreshold,NIITThresholdSingle))*(1+TaxBracketInflation)^25))+(AA14+(MIN(MAX(0,AA15+AA26-AA13-AA14),(AA7*(1+ReturnAfterTax)+AA16)))*CapGainsPct)*ILTaxRate | AB27: =(MAX(0,AB14+AB16+AB17+0.85*AB13-(IF(AB4,StdDeduction,StdDeductionSingle))*(1+TaxBracketInflation)^26))*0.22+(MAX(0,(MIN(MAX(0,AB15+AB26-AB13-AB14),(AB7*(1+ReturnAfterTax)+AB16)))*CapGainsPct-MAX(0,(IF(AB4,94050,47025))*(1+TaxBracketInflation)^26-MAX(0,AB14+AB16+AB17+0.85*AB13-(IF(AB4,StdDeduction,StdDeductionSingle))*(1+TaxBracketInflation)^26))))*0.15+0.038*MIN((MIN(MAX(0,AB15+AB26-AB13-AB14),(AB7*(1+ReturnAfterTax)+AB16)))*CapGainsPct,MAX(0,(AB14+AB16+AB17+0.85*AB13+(MIN(MAX(0,AB15+AB26-AB13-AB14),(AB7*(1+ReturnAfterTax)+AB16)))*CapGainsPct)-(IF(AB4,NIITThreshold,NIITThresholdSingle))*(1+TaxBracketInflation)^26))+(AB14+(MIN(MAX(0,AB15+AB26-AB13-AB14),(AB7*(1+ReturnAfterTax)+AB16)))*CapGainsPct)*ILTaxRate | AC27: =(MAX(0,AC14+AC16+AC17+0.85*AC13-(IF(AC4,StdDeduction,StdDeductionSingle))*(1+TaxBracketInflation)^27))*0.22+(MAX(0,(MIN(MAX(0,AC15+AC26-AC13-AC14),(AC7*(1+ReturnAfterTax)+AC16)))*CapGainsPct-MAX(0,(IF(AC4,94050,47025))*(1+TaxBracketInflation)^27-MAX(0,AC14+AC16+AC17+0.85*AC13-(IF(AC4,StdDeduction,StdDeductionSingle))*(1+TaxBracketInflation)^27))))*0.15+0.038*MIN((MIN(MAX(0,AC15+AC26-AC13-AC14),(AC7*(1+ReturnAfterTax)+AC16)))*CapGainsPct,MAX(0,(AC14+AC16+AC17+0.85*AC13+(MIN(MAX(0,AC15+AC26-AC13-AC14),(AC7*(1+ReturnAfterTax)+AC16)))*CapGainsPct)-(IF(AC4,NIITThreshold,NIITThresholdSingle))*(1+TaxBracketInflation)^27))+(AC14+(MIN(MAX(0,AC15+AC26-AC13-AC14),(AC7*(1+ReturnAfterTax)+AC16)))*CapGainsPct)*ILTaxRate | AD27: =(MAX(0,AD14+AD16+AD17+0.85*AD13-(IF(AD4,StdDeduction,StdDeductionSingle))*(1+TaxBracketInflation)^28))*0.22+(MAX(0,(MIN(MAX(0,AD15+AD26-AD13-AD14),(AD7*(1+ReturnAfterTax)+AD16)))*CapGainsPct-MAX(0,(IF(AD4,94050,47025))*(1+TaxBracketInflation)^28-MAX(0,AD14+AD16+AD17+0.85*AD13-(IF(AD4,StdDeduction,StdDeductionSingle))*(1+TaxBracketInflation)^28))))*0.15+0.038*MIN((MIN(MAX(0,AD15+AD26-AD13-AD14),(AD7*(1+ReturnAfterTax)+AD16)))*CapGainsPct,MAX(0,(AD14+AD16+AD17+0.85*AD13+(MIN(MAX(0,AD15+AD26-AD13-AD14),(AD7*(1+ReturnAfterTax)+AD16)))*CapGainsPct)-(IF(AD4,NIITThreshold,NIITThresholdSingle))*(1+TaxBracketInflation)^28))+(AD14+(MIN(MAX(0,AD15+AD26-AD13-AD14),(AD7*(1+ReturnAfterTax)+AD16)))*CapGainsPct)*ILTaxRate | AE27: =(MAX(0,AE14+AE16+AE17+0.85*AE13-(IF(AE4,StdDeduction,StdDeductionSingle))*(1+TaxBracketInflation)^29))*0.22+(MAX(0,(MIN(MAX(0,AE15+AE26-AE13-AE14),(AE7*(1+ReturnAfterTax)+AE16)))*CapGainsPct-MAX(0,(IF(AE4,94050,47025))*(1+TaxBracketInflation)^29-MAX(0,AE14+AE16+AE17+0.85*AE13-(IF(AE4,StdDeduction,StdDeductionSingle))*(1+TaxBracketInflation)^29))))*0.15+0.038*MIN((MIN(MAX(0,AE15+AE26-AE13-AE14),(AE7*(1+ReturnAfterTax)+AE16)))*CapGainsPct,MAX(0,(AE14+AE16+AE17+0.85*AE13+(MIN(MAX(0,AE15+AE26-AE13-AE14),(AE7*(1+ReturnAfterTax)+AE16)))*CapGainsPct)-(IF(AE4,NIITThreshold,NIITThresholdSingle))*(1+TaxBracketInflation)^29))+(AE14+(MIN(MAX(0,AE15+AE26-AE13-AE14),(AE7*(1+ReturnAfterTax)+AE16)))*CapGainsPct)*ILTaxRate
A28: Total Cash Need | B28: =B15+B26+B27 | C28: =C15+C26+C27 | D28: =D15+D26+D27 | E28: =E15+E26+E27 | F28: =F15+F26+F27 | G28: =G15+G26+G27 | H28: =H15+H26+H27 | I28: =I15+I26+I27 | ... AE28: =AE15+AE26+AE27
A30: WITHDRAWALS
A31: Discretionary W/D | B31: =IFERROR(VLOOKUP(B1,DiscretionaryTable,2,FALSE),0) | C31: =IFERROR(VLOOKUP(C1,DiscretionaryTable,2,FALSE),0) | D31: =IFERROR(VLOOKUP(D1,DiscretionaryTable,2,FALSE),0) | E31: =IFERROR(VLOOKUP(E1,DiscretionaryTable,2,FALSE),0) | F31: =IFERROR(VLOOKUP(F1,DiscretionaryTable,2,FALSE),0) | G31: =IFERROR(VLOOKUP(G1,DiscretionaryTable,2,FALSE),0) | H31: =IFERROR(VLOOKUP(H1,DiscretionaryTable,2,FALSE),0) | I31: =IFERROR(VLOOKUP(I1,DiscretionaryTable,2,FALSE),0) | ... AE31: =IFERROR(VLOOKUP(AE1,DiscretionaryTable,2,FALSE),0)
A32: W/D After-Tax | B32: =MIN(MAX(0,B28+B31-B13-B14),B7+B20+B16) | C32: =MIN(MAX(0,C28+C31-C13-C14),C7+C20+C16) | D32: =MIN(MAX(0,D28+D31-D13-D14),D7+D20+D16) | E32: =MIN(MAX(0,E28+E31-E13-E14),E7+E20+E16) | F32: =MIN(MAX(0,F28+F31-F13-F14),F7+F20+F16) | G32: =MIN(MAX(0,G28+G31-G13-G14),G7+G20+G16) | H32: =MIN(MAX(0,H28+H31-H13-H14),H7+H20+H16) | I32: =MIN(MAX(0,I28+I31-I13-I14),I7+I20+I16) | ... AE32: =MIN(MAX(0,AE28+AE31-AE13-AE14),AE7+AE20+AE16)
A33: W/D IRA (above RMD) | B33: =MIN(MAX(0,B28+B31-B13-B14-B32),MAX(0,B8-B17+B21-B16)) | C33: =MIN(MAX(0,C28+C31-C13-C14-C32),MAX(0,C8-C17+C21-C16)) | D33: =MIN(MAX(0,D28+D31-D13-D14-D32),MAX(0,D8-D17+D21-D16)) | E33: =MIN(MAX(0,E28+E31-E13-E14-E32),MAX(0,E8-E17+E21-E16)) | F33: =MIN(MAX(0,F28+F31-F13-F14-F32),MAX(0,F8-F17+F21-F16)) | G33: =MIN(MAX(0,G28+G31-G13-G14-G32),MAX(0,G8-G17+G21-G16)) | H33: =MIN(MAX(0,H28+H31-H13-H14-H32),MAX(0,H8-H17+H21-H16)) | I33: =MIN(MAX(0,I28+I31-I13-I14-I32),MAX(0,I8-I17+I21-I16)) | ... AE33: =MIN(MAX(0,AE28+AE31-AE13-AE14-AE32),MAX(0,AE8-AE17+AE21-AE16))
A34: W/D Roth | B34: =MIN(MAX(0,B28+B31-B13-B14-B32-B33),B9+B17+B22) | C34: =MIN(MAX(0,C28+C31-C13-C14-C32-C33),C9+C17+C22) | D34: =MIN(MAX(0,D28+D31-D13-D14-D32-D33),D9+D17+D22) | E34: =MIN(MAX(0,E28+E31-E13-E14-E32-E33),E9+E17+E22) | F34: =MIN(MAX(0,F28+F31-F13-F14-F32-F33),F9+F17+F22) | G34: =MIN(MAX(0,G28+G31-G13-G14-G32-G33),G9+G17+G22) | H34: =MIN(MAX(0,H28+H31-H13-H14-H32-H33),H9+H17+H22) | I34: =MIN(MAX(0,I28+I31-I13-I14-I32-I33),I9+I17+I22) | ... AE34: =MIN(MAX(0,AE28+AE31-AE13-AE14-AE32-AE33),AE9+AE17+AE22)
A35: Total Withdrawals | B35: =B32+B33+B34 | C35: =C32+C33+C34 | D35: =D32+D33+D34 | E35: =E32+E33+E34 | F35: =F32+F33+F34 | G35: =G32+G33+G34 | H35: =H32+H33+H34 | I35: =I32+I33+I34 | ... AE35: =AE32+AE33+AE34
A37: TAX DETAIL
A38: Taxable Soc Sec | B38: =IF((B14+B16+B17+B33+B32*CapGainsPct+0.5*B13)<=32000,0,IF((B14+B16+B17+B33+B32*CapGainsPct+0.5*B13)<=44000,MIN(0.5*B13,0.5*((B14+B16+B17+B33+B32*CapGainsPct+0.5*B13)-32000)),MIN(0.85*B13,0.5*B13+0.85*((B14+B16+B17+B33+B32*CapGainsPct+0.5*B13)-44000)))) | C38: =IF((C14+C16+C17+C33+C32*CapGainsPct+0.5*C13)<=32000,0,IF((C14+C16+C17+C33+C32*CapGainsPct+0.5*C13)<=44000,MIN(0.5*C13,0.5*((C14+C16+C17+C33+C32*CapGainsPct+0.5*C13)-32000)),MIN(0.85*C13,0.5*C13+0.85*((C14+C16+C17+C33+C32*CapGainsPct+0.5*C13)-44000)))) | D38: =IF((D14+D16+D17+D33+D32*CapGainsPct+0.5*D13)<=32000,0,IF((D14+D16+D17+D33+D32*CapGainsPct+0.5*D13)<=44000,MIN(0.5*D13,0.5*((D14+D16+D17+D33+D32*CapGainsPct+0.5*D13)-32000)),MIN(0.85*D13,0.5*D13+0.85*((D14+D16+D17+D33+D32*CapGainsPct+0.5*D13)-44000)))) | E38: =IF((E14+E16+E17+E33+E32*CapGainsPct+0.5*E13)<=32000,0,IF((E14+E16+E17+E33+E32*CapGainsPct+0.5*E13)<=44000,MIN(0.5*E13,0.5*((E14+E16+E17+E33+E32*CapGainsPct+0.5*E13)-32000)),MIN(0.85*E13,0.5*E13+0.85*((E14+E16+E17+E33+E32*CapGainsPct+0.5*E13)-44000)))) | F38: =IF((F14+F16+F17+F33+F32*CapGainsPct+0.5*F13)<=32000,0,IF((F14+F16+F17+F33+F32*CapGainsPct+0.5*F13)<=44000,MIN(0.5*F13,0.5*((F14+F16+F17+F33+F32*CapGainsPct+0.5*F13)-32000)),MIN(0.85*F13,0.5*F13+0.85*((F14+F16+F17+F33+F32*CapGainsPct+0.5*F13)-44000)))) | G38: =IF((G14+G16+G17+G33+G32*CapGainsPct+0.5*G13)<=32000,0,IF((G14+G16+G17+G33+G32*CapGainsPct+0.5*G13)<=44000,MIN(0.5*G13,0.5*((G14+G16+G17+G33+G32*CapGainsPct+0.5*G13)-32000)),MIN(0.85*G13,0.5*G13+0.85*((G14+G16+G17+G33+G32*CapGainsPct+0.5*G13)-44000)))) | H38: =IF((H14+H16+H17+H33+H32*CapGainsPct+0.5*H13)<=32000,0,IF((H14+H16+H17+H33+H32*CapGainsPct+0.5*H13)<=44000,MIN(0.5*H13,0.5*((H14+H16+H17+H33+H32*CapGainsPct+0.5*H13)-32000)),MIN(0.85*H13,0.5*H13+0.85*((H14+H16+H17+H33+H32*CapGainsPct+0.5*H13)-44000)))) | I38: =IF((I14+I16+I17+I33+I32*CapGainsPct+0.5*I13)<=32000,0,IF((I14+I16+I17+I33+I32*CapGainsPct+0.5*I13)<=44000,MIN(0.5*I13,0.5*((I14+I16+I17+I33+I32*CapGainsPct+0.5*I13)-32000)),MIN(0.85*I13,0.5*I13+0.85*((I14+I16+I17+I33+I32*CapGainsPct+0.5*I13)-44000)))) | ... AE38: =IF((AE14+AE16+AE17+AE33+AE32*CapGainsPct+0.5*AE13)<=32000,0,IF((AE14+AE16+AE17+AE33+AE32*CapGainsPct+0.5*AE13)<=44000,MIN(0.5*AE13,0.5*((AE14+AE16+AE17+AE33+AE32*CapGainsPct+0.5*AE13)-32000)),MIN(0.85*AE13,0.5*AE13+0.85*((AE14+AE16+AE17+AE33+AE32*CapGainsPct+0.5*AE13)-44000))))
A39: Ordinary Income | B39: =MAX(0,B14+B16+B17+B33+B38-(IF(B4,StdDeduction,StdDeductionSingle))*(1+TaxBracketInflation)^0) | C39: =MAX(0,C14+C16+C17+C33+C38-(IF(C4,StdDeduction,StdDeductionSingle))*(1+TaxBracketInflation)^1) | D39: =MAX(0,D14+D16+D17+D33+D38-(IF(D4,StdDeduction,StdDeductionSingle))*(1+TaxBracketInflation)^2) | E39: =MAX(0,E14+E16+E17+E33+E38-(IF(E4,StdDeduction,StdDeductionSingle))*(1+TaxBracketInflation)^3) | F39: =MAX(0,F14+F16+F17+F33+F38-(IF(F4,StdDeduction,StdDeductionSingle))*(1+TaxBracketInflation)^4) | G39: =MAX(0,G14+G16+G17+G33+G38-(IF(G4,StdDeduction,StdDeductionSingle))*(1+TaxBracketInflation)^5) | H39: =MAX(0,H14+H16+H17+H33+H38-(IF(H4,StdDeduction,StdDeductionSingle))*(1+TaxBracketInflation)^6) | I39: =MAX(0,I14+I16+I17+I33+I38-(IF(I4,StdDeduction,StdDeductionSingle))*(1+TaxBracketInflation)^7) | J39: =MAX(0,J14+J16+J17+J33+J38-(IF(J4,StdDeduction,StdDeductionSingle))*(1+TaxBracketInflation)^8) | K39: =MAX(0,K14+K16+K17+K33+K38-(IF(K4,StdDeduction,StdDeductionSingle))*(1+TaxBracketInflation)^9) | L39: =MAX(0,L14+L16+L17+L33+L38-(IF(L4,StdDeduction,StdDeductionSingle))*(1+TaxBracketInflation)^10) | M39: =MAX(0,M14+M16+M17+M33+M38-(IF(M4,StdDeduction,StdDeductionSingle))*(1+TaxBracketInflation)^11) | N39: =MAX(0,N14+N16+N17+N33+N38-(IF(N4,StdDeduction,StdDeductionSingle))*(1+TaxBracketInflation)^12) | O39: =MAX(0,O14+O16+O17+O33+O38-(IF(O4,StdDeduction,StdDeductionSingle))*(1+TaxBracketInflation)^13) | P39: =MAX(0,P14+P16+P17+P33+P38-(IF(P4,StdDeduction,StdDeductionSingle))*(1+TaxBracketInflation)^14) | Q39: =MAX(0,Q14+Q16+Q17+Q33+Q38-(IF(Q4,StdDeduction,StdDeductionSingle))*(1+TaxBracketInflation)^15) | R39: =MAX(0,R14+R16+R17+R33+R38-(IF(R4,StdDeduction,StdDeductionSingle))*(1+TaxBracketInflation)^16) | S39: =MAX(0,S14+S16+S17+S33+S38-(IF(S4,StdDeduction,StdDeductionSingle))*(1+TaxBracketInflation)^17) | T39: =MAX(0,T14+T16+T17+T33+T38-(IF(T4,StdDeduction,StdDeductionSingle))*(1+TaxBracketInflation)^18) | U39: =MAX(0,U14+U16+U17+U33+U38-(IF(U4,StdDeduction,StdDeductionSingle))*(1+TaxBracketInflation)^19) | V39: =MAX(0,V14+V16+V17+V33+V38-(IF(V4,StdDeduction,StdDeductionSingle))*(1+TaxBracketInflation)^20) | W39: =MAX(0,W14+W16+W17+W33+W38-(IF(W4,StdDeduction,StdDeductionSingle))*(1+TaxBracketInflation)^21) | X39: =MAX(0,X14+X16+X17+X33+X38-(IF(X4,StdDeduction,StdDeductionSingle))*(1+TaxBracketInflation)^22) | Y39: =MAX(0,Y14+Y16+Y17+Y33+Y38-(IF(Y4,StdDeduction,StdDeductionSingle))*(1+TaxBracketInflation)^23) | Z39: =MAX(0,Z14+Z16+Z17+Z33+Z38-(IF(Z4,StdDeduction,StdDeductionSingle))*(1+TaxBracketInflation)^24) | AA39: =MAX(0,AA14+AA16+AA17+AA33+AA38-(IF(AA4,StdDeduction,StdDeductionSingle))*(1+TaxBracketInflation)^25) | AB39: =MAX(0,AB14+AB16+AB17+AB33+AB38-(IF(AB4,StdDeduction,StdDeductionSingle))*(1+TaxBracketInflation)^26) | AC39: =MAX(0,AC14+AC16+AC17+AC33+AC38-(IF(AC4,StdDeduction,StdDeductionSingle))*(1+TaxBracketInflation)^27) | AD39: =MAX(0,AD14+AD16+AD17+AD33+AD38-(IF(AD4,StdDeduction,StdDeductionSingle))*(1+TaxBracketInflation)^28) | AE39: =MAX(0,AE14+AE16+AE17+AE33+AE38-(IF(AE4,StdDeduction,StdDeductionSingle))*(1+TaxBracketInflation)^29)
A40: Capital Gains | B40: =B32*CapGainsPct | C40: =C32*CapGainsPct | D40: =D32*CapGainsPct | E40: =E32*CapGainsPct | F40: =F32*CapGainsPct | G40: =G32*CapGainsPct | H40: =H32*CapGainsPct | I40: =I32*CapGainsPct | ... AE40: =AE32*CapGainsPct
A41: Cap Gains @ 0% | B41: =MIN(B40,MAX(0,IF(B4,94050,47025)*(1+TaxBracketInflation)^0-B39)) | C41: =MIN(C40,MAX(0,IF(C4,94050,47025)*(1+TaxBracketInflation)^1-C39)) | D41: =MIN(D40,MAX(0,IF(D4,94050,47025)*(1+TaxBracketInflation)^2-D39)) | E41: =MIN(E40,MAX(0,IF(E4,94050,47025)*(1+TaxBracketInflation)^3-E39)) | F41: =MIN(F40,MAX(0,IF(F4,94050,47025)*(1+TaxBracketInflation)^4-F39)) | G41: =MIN(G40,MAX(0,IF(G4,94050,47025)*(1+TaxBracketInflation)^5-G39)) | H41: =MIN(H40,MAX(0,IF(H4,94050,47025)*(1+TaxBracketInflation)^6-H39)) | I41: =MIN(I40,MAX(0,IF(I4,94050,47025)*(1+TaxBracketInflation)^7-I39)) | J41: =MIN(J40,MAX(0,IF(J4,94050,47025)*(1+TaxBracketInflation)^8-J39)) | K41: =MIN(K40,MAX(0,IF(K4,94050,47025)*(1+TaxBracketInflation)^9-K39)) | L41: =MIN(L40,MAX(0,IF(L4,94050,47025)*(1+TaxBracketInflation)^10-L39)) | M41: =MIN(M40,MAX(0,IF(M4,94050,47025)*(1+TaxBracketInflation)^11-M39)) | N41: =MIN(N40,MAX(0,IF(N4,94050,47025)*(1+TaxBracketInflation)^12-N39)) | O41: =MIN(O40,MAX(0,IF(O4,94050,47025)*(1+TaxBracketInflation)^13-O39)) | P41: =MIN(P40,MAX(0,IF(P4,94050,47025)*(1+TaxBracketInflation)^14-P39)) | Q41: =MIN(Q40,MAX(0,IF(Q4,94050,47025)*(1+TaxBracketInflation)^15-Q39)) | R41: =MIN(R40,MAX(0,IF(R4,94050,47025)*(1+TaxBracketInflation)^16-R39)) | S41: =MIN(S40,MAX(0,IF(S4,94050,47025)*(1+TaxBracketInflation)^17-S39)) | T41: =MIN(T40,MAX(0,IF(T4,94050,47025)*(1+TaxBracketInflation)^18-T39)) | U41: =MIN(U40,MAX(0,IF(U4,94050,47025)*(1+TaxBracketInflation)^19-U39)) | V41: =MIN(V40,MAX(0,IF(V4,94050,47025)*(1+TaxBracketInflation)^20-V39)) | W41: =MIN(W40,MAX(0,IF(W4,94050,47025)*(1+TaxBracketInflation)^21-W39)) | X41: =MIN(X40,MAX(0,IF(X4,94050,47025)*(1+TaxBracketInflation)^22-X39)) | Y41: =MIN(Y40,MAX(0,IF(Y4,94050,47025)*(1+TaxBracketInflation)^23-Y39)) | Z41: =MIN(Z40,MAX(0,IF(Z4,94050,47025)*(1+TaxBracketInflation)^24-Z39)) | AA41: =MIN(AA40,MAX(0,IF(AA4,94050,47025)*(1+TaxBracketInflation)^25-AA39)) | AB41: =MIN(AB40,MAX(0,IF(AB4,94050,47025)*(1+TaxBracketInflation)^26-AB39)) | AC41: =MIN(AC40,MAX(0,IF(AC4,94050,47025)*(1+TaxBracketInflation)^27-AC39)) | AD41: =MIN(AD40,MAX(0,IF(AD4,94050,47025)*(1+TaxBracketInflation)^28-AD39)) | AE41: =MIN(AE40,MAX(0,IF(AE4,94050,47025)*(1+TaxBracketInflation)^29-AE39))
A42: Cap Gains @ 15%+ | B42: =B40-B41 | C42: =C40-C41 | D42: =D40-D41 | E42: =E40-E41 | F42: =F40-F41 | G42: =G40-G41 | H42: =H40-H41 | I42: =I40-I41 | ... AE42: =AE40-AE41
A43: Fed Ordinary Tax | B43: =MIN(B39,IF(B4,23200,11600)*(1+TaxBracketInflation)^0)*0.1+MAX(0,MIN(B39,IF(B4,94300,47150)*(1+TaxBracketInflation)^0)-IF(B4,23200,11600)*(1+TaxBracketInflation)^0)*0.12+MAX(0,MIN(B39,IF(B4,201050,100525)*(1+TaxBracketInflation)^0)-IF(B4,94300,47150)*(1+TaxBracketInflation)^0)*0.22+MAX(0,MIN(B39,IF(B4,383900,191950)*(1+TaxBracketInflation)^0)-IF(B4,201050,100525)*(1+TaxBracketInflation)^0)*0.24+MAX(0,MIN(B39,IF(B4,487450,243725)*(1+TaxBracketInflation)^0)-IF(B4,383900,191950)*(1+TaxBracketInflation)^0)*0.32+MAX(0,MIN(B39,IF(B4,731200,609350)*(1+TaxBracketInflation)^0)-IF(B4,487450,243725)*(1+TaxBracketInflation)^0)*0.35+MAX(0,B39-IF(B4,731200,609350)*(1+TaxBracketInflation)^0)*0.37 | C43: =MIN(C39,IF(C4,23200,11600)*(1+TaxBracketInflation)^1)*0.1+MAX(0,MIN(C39,IF(C4,94300,47150)*(1+TaxBracketInflation)^1)-IF(C4,23200,11600)*(1+TaxBracketInflation)^1)*0.12+MAX(0,MIN(C39,IF(C4,201050,100525)*(1+TaxBracketInflation)^1)-IF(C4,94300,47150)*(1+TaxBracketInflation)^1)*0.22+MAX(0,MIN(C39,IF(C4,383900,191950)*(1+TaxBracketInflation)^1)-IF(C4,201050,100525)*(1+TaxBracketInflation)^1)*0.24+MAX(0,MIN(C39,IF(C4,487450,243725)*(1+TaxBracketInflation)^1)-IF(C4,383900,191950)*(1+TaxBracketInflation)^1)*0.32+MAX(0,MIN(C39,IF(C4,731200,609350)*(1+TaxBracketInflation)^1)-IF(C4,487450,243725)*(1+TaxBracketInflation)^1)*0.35+MAX(0,C39-IF(C4,731200,609350)*(1+TaxBracketInflation)^1)*0.37 | D43: =MIN(D39,IF(D4,23200,11600)*(1+TaxBracketInflation)^2)*0.1+MAX(0,MIN(D39,IF(D4,94300,47150)*(1+TaxBracketInflation)^2)-IF(D4,23200,11600)*(1+TaxBracketInflation)^2)*0.12+MAX(0,MIN(D39,IF(D4,201050,100525)*(1+TaxBracketInflation)^2)-IF(D4,94300,47150)*(1+TaxBracketInflation)^2)*0.22+MAX(0,MIN(D39,IF(D4,383900,191950)*(1+TaxBracketInflation)^2)-IF(D4,201050,100525)*(1+TaxBracketInflation)^2)*0.24+MAX(0,MIN(D39,IF(D4,487450,243725)*(1+TaxBracketInflation)^2)-IF(D4,383900,191950)*(1+TaxBracketInflation)^2)*0.32+MAX(0,MIN(D39,IF(D4,731200,609350)*(1+TaxBracketInflation)^2)-IF(D4,487450,243725)*(1+TaxBracketInflation)^2)*0.35+MAX(0,D39-IF(D4,731200,609350)*(1+TaxBracketInflation)^2)*0.37 | E43: =MIN(E39,IF(E4,23200,11600)*(1+TaxBracketInflation)^3)*0.1+MAX(0,MIN(E39,IF(E4,94300,47150)*(1+TaxBracketInflation)^3)-IF(E4,23200,11600)*(1+TaxBracketInflation)^3)*0.12+MAX(0,MIN(E39,IF(E4,201050,100525)*(1+TaxBracketInflation)^3)-IF(E4,94300,47150)*(1+TaxBracketInflation)^3)*0.22+MAX(0,MIN(E39,IF(E4,383900,191950)*(1+TaxBracketInflation)^3)-IF(E4,201050,100525)*(1+TaxBracketInflation)^3)*0.24+MAX(0,MIN(E39,IF(E4,487450,243725)*(1+TaxBracketInflation)^3)-IF(E4,383900,191950)*(1+TaxBracketInflation)^3)*0.32+MAX(0,MIN(E39,IF(E4,731200,609350)*(1+TaxBracketInflation)^3)-IF(E4,487450,243725)*(1+TaxBracketInflation)^3)*0.35+MAX(0,E39-IF(E4,731200,609350)*(1+TaxBracketInflation)^3)*0.37 | F43: =MIN(F39,IF(F4,23200,11600)*(1+TaxBracketInflation)^4)*0.1+MAX(0,MIN(F39,IF(F4,94300,47150)*(1+TaxBracketInflation)^4)-IF(F4,23200,11600)*(1+TaxBracketInflation)^4)*0.12+MAX(0,MIN(F39,IF(F4,201050,100525)*(1+TaxBracketInflation)^4)-IF(F4,94300,47150)*(1+TaxBracketInflation)^4)*0.22+MAX(0,MIN(F39,IF(F4,383900,191950)*(1+TaxBracketInflation)^4)-IF(F4,201050,100525)*(1+TaxBracketInflation)^4)*0.24+MAX(0,MIN(F39,IF(F4,487450,243725)*(1+TaxBracketInflation)^4)-IF(F4,383900,191950)*(1+TaxBracketInflation)^4)*0.32+MAX(0,MIN(F39,IF(F4,731200,609350)*(1+TaxBracketInflation)^4)-IF(F4,487450,243725)*(1+TaxBracketInflation)^4)*0.35+MAX(0,F39-IF(F4,731200,609350)*(1+TaxBracketInflation)^4)*0.37 | G43: =MIN(G39,IF(G4,23200,11600)*(1+TaxBracketInflation)^5)*0.1+MAX(0,MIN(G39,IF(G4,94300,47150)*(1+TaxBracketInflation)^5)-IF(G4,23200,11600)*(1+TaxBracketInflation)^5)*0.12+MAX(0,MIN(G39,IF(G4,201050,100525)*(1+TaxBracketInflation)^5)-IF(G4,94300,47150)*(1+TaxBracketInflation)^5)*0.22+MAX(0,MIN(G39,IF(G4,383900,191950)*(1+TaxBracketInflation)^5)-IF(G4,201050,100525)*(1+TaxBracketInflation)^5)*0.24+MAX(0,MIN(G39,IF(G4,487450,243725)*(1+TaxBracketInflation)^5)-IF(G4,383900,191950)*(1+TaxBracketInflation)^5)*0.32+MAX(0,MIN(G39,IF(G4,731200,609350)*(1+TaxBracketInflation)^5)-IF(G4,487450,243725)*(1+TaxBracketInflation)^5)*0.35+MAX(0,G39-IF(G4,731200,609350)*(1+TaxBracketInflation)^5)*0.37 | H43: =MIN(H39,IF(H4,23200,11600)*(1+TaxBracketInflation)^6)*0.1+MAX(0,MIN(H39,IF(H4,94300,47150)*(1+TaxBracketInflation)^6)-IF(H4,23200,11600)*(1+TaxBracketInflation)^6)*0.12+MAX(0,MIN(H39,IF(H4,201050,100525)*(1+TaxBracketInflation)^6)-IF(H4,94300,47150)*(1+TaxBracketInflation)^6)*0.22+MAX(0,MIN(H39,IF(H4,383900,191950)*(1+TaxBracketInflation)^6)-IF(H4,201050,100525)*(1+TaxBracketInflation)^6)*0.24+MAX(0,MIN(H39,IF(H4,487450,243725)*(1+TaxBracketInflation)^6)-IF(H4,383900,191950)*(1+TaxBracketInflation)^6)*0.32+MAX(0,MIN(H39,IF(H4,731200,609350)*(1+TaxBracketInflation)^6)-IF(H4,487450,243725)*(1+TaxBracketInflation)^6)*0.35+MAX(0,H39-IF(H4,731200,609350)*(1+TaxBracketInflation)^6)*0.37 | I43: =MIN(I39,IF(I4,23200,11600)*(1+TaxBracketInflation)^7)*0.1+MAX(0,MIN(I39,IF(I4,94300,47150)*(1+TaxBracketInflation)^7)-IF(I4,23200,11600)*(1+TaxBracketInflation)^7)*0.12+MAX(0,MIN(I39,IF(I4,201050,100525)*(1+TaxBracketInflation)^7)-IF(I4,94300,47150)*(1+TaxBracketInflation)^7)*0.22+MAX(0,MIN(I39,IF(I4,383900,191950)*(1+TaxBracketInflation)^7)-IF(I4,201050,100525)*(1+TaxBracketInflation)^7)*0.24+MAX(0,MIN(I39,IF(I4,487450,243725)*(1+TaxBracketInflation)^7)-IF(I4,383900,191950)*(1+TaxBracketInflation)^7)*0.32+MAX(0,MIN(I39,IF(I4,731200,609350)*(1+TaxBracketInflation)^7)-IF(I4,487450,243725)*(1+TaxBracketInflation)^7)*0.35+MAX(0,I39-IF(I4,731200,609350)*(1+TaxBracketInflation)^7)*0.37 | J43: =MIN(J39,IF(J4,23200,11600)*(1+TaxBracketInflation)^8)*0.1+MAX(0,MIN(J39,IF(J4,94300,47150)*(1+TaxBracketInflation)^8)-IF(J4,23200,11600)*(1+TaxBracketInflation)^8)*0.12+MAX(0,MIN(J39,IF(J4,201050,100525)*(1+TaxBracketInflation)^8)-IF(J4,94300,47150)*(1+TaxBracketInflation)^8)*0.22+MAX(0,MIN(J39,IF(J4,383900,191950)*(1+TaxBracketInflation)^8)-IF(J4,201050,100525)*(1+TaxBracketInflation)^8)*0.24+MAX(0,MIN(J39,IF(J4,487450,243725)*(1+TaxBracketInflation)^8)-IF(J4,383900,191950)*(1+TaxBracketInflation)^8)*0.32+MAX(0,MIN(J39,IF(J4,731200,609350)*(1+TaxBracketInflation)^8)-IF(J4,487450,243725)*(1+TaxBracketInflation)^8)*0.35+MAX(0,J39-IF(J4,731200,609350)*(1+TaxBracketInflation)^8)*0.37 | K43: =MIN(K39,IF(K4,23200,11600)*(1+TaxBracketInflation)^9)*0.1+MAX(0,MIN(K39,IF(K4,94300,47150)*(1+TaxBracketInflation)^9)-IF(K4,23200,11600)*(1+TaxBracketInflation)^9)*0.12+MAX(0,MIN(K39,IF(K4,201050,100525)*(1+TaxBracketInflation)^9)-IF(K4,94300,47150)*(1+TaxBracketInflation)^9)*0.22+MAX(0,MIN(K39,IF(K4,383900,191950)*(1+TaxBracketInflation)^9)-IF(K4,201050,100525)*(1+TaxBracketInflation)^9)*0.24+MAX(0,MIN(K39,IF(K4,487450,243725)*(1+TaxBracketInflation)^9)-IF(K4,383900,191950)*(1+TaxBracketInflation)^9)*0.32+MAX(0,MIN(K39,IF(K4,731200,609350)*(1+TaxBracketInflation)^9)-IF(K4,487450,243725)*(1+TaxBracketInflation)^9)*0.35+MAX(0,K39-IF(K4,731200,609350)*(1+TaxBracketInflation)^9)*0.37 | L43: =MIN(L39,IF(L4,23200,11600)*(1+TaxBracketInflation)^10)*0.1+MAX(0,MIN(L39,IF(L4,94300,47150)*(1+TaxBracketInflation)^10)-IF(L4,23200,11600)*(1+TaxBracketInflation)^10)*0.12+MAX(0,MIN(L39,IF(L4,201050,100525)*(1+TaxBracketInflation)^10)-IF(L4,94300,47150)*(1+TaxBracketInflation)^10)*0.22+MAX(0,MIN(L39,IF(L4,383900,191950)*(1+TaxBracketInflation)^10)-IF(L4,201050,100525)*(1+TaxBracketInflation)^10)*0.24+MAX(0,MIN(L39,IF(L4,487450,243725)*(1+TaxBracketInflation)^10)-IF(L4,383900,191950)*(1+TaxBracketInflation)^10)*0.32+MAX(0,MIN(L39,IF(L4,731200,609350)*(1+TaxBracketInflation)^10)-IF(L4,487450,243725)*(1+TaxBracketInflation)^10)*0.35+MAX(0,L39-IF(L4,731200,609350)*(1+TaxBracketInflation)^10)*0.37 | M43: =MIN(M39,IF(M4,23200,11600)*(1+TaxBracketInflation)^11)*0.1+MAX(0,MIN(M39,IF(M4,94300,47150)*(1+TaxBracketInflation)^11)-IF(M4,23200,11600)*(1+TaxBracketInflation)^11)*0.12+MAX(0,MIN(M39,IF(M4,201050,100525)*(1+TaxBracketInflation)^11)-IF(M4,94300,47150)*(1+TaxBracketInflation)^11)*0.22+MAX(0,MIN(M39,IF(M4,383900,191950)*(1+TaxBracketInflation)^11)-IF(M4,201050,100525)*(1+TaxBracketInflation)^11)*0.24+MAX(0,MIN(M39,IF(M4,487450,243725)*(1+TaxBracketInflation)^11)-IF(M4,383900,191950)*(1+TaxBracketInflation)^11)*0.32+MAX(0,MIN(M39,IF(M4,731200,609350)*(1+TaxBracketInflation)^11)-IF(M4,487450,243725)*(1+TaxBracketInflation)^11)*0.35+MAX(0,M39-IF(M4,731200,609350)*(1+TaxBracketInflation)^11)*0.37 | N43: =MIN(N39,IF(N4,23200,11600)*(1+TaxBracketInflation)^12)*0.1+MAX(0,MIN(N39,IF(N4,94300,47150)*(1+TaxBracketInflation)^12)-IF(N4,23200,11600)*(1+TaxBracketInflation)^12)*0.12+MAX(0,MIN(N39,IF(N4,201050,100525)*(1+TaxBracketInflation)^12)-IF(N4,94300,47150)*(1+TaxBracketInflation)^12)*0.22+MAX(0,MIN(N39,IF(N4,383900,191950)*(1+TaxBracketInflation)^12)-IF(N4,201050,100525)*(1+TaxBracketInflation)^12)*0.24+MAX(0,MIN(N39,IF(N4,487450,243725)*(1+TaxBracketInflation)^12)-IF(N4,383900,191950)*(1+TaxBracketInflation)^12)*0.32+MAX(0,MIN(N39,IF(N4,731200,609350)*(1+TaxBracketInflation)^12)-IF(N4,487450,243725)*(1+TaxBracketInflation)^12)*0.35+MAX(0,N39-IF(N4,731200,609350)*(1+TaxBracketInflation)^12)*0.37 | O43: =MIN(O39,IF(O4,23200,11600)*(1+TaxBracketInflation)^13)*0.1+MAX(0,MIN(O39,IF(O4,94300,47150)*(1+TaxBracketInflation)^13)-IF(O4,23200,11600)*(1+TaxBracketInflation)^13)*0.12+MAX(0,MIN(O39,IF(O4,201050,100525)*(1+TaxBracketInflation)^13)-IF(O4,94300,47150)*(1+TaxBracketInflation)^13)*0.22+MAX(0,MIN(O39,IF(O4,383900,191950)*(1+TaxBracketInflation)^13)-IF(O4,201050,100525)*(1+TaxBracketInflation)^13)*0.24+MAX(0,MIN(O39,IF(O4,487450,243725)*(1+TaxBracketInflation)^13)-IF(O4,383900,191950)*(1+TaxBracketInflation)^13)*0.32+MAX(0,MIN(O39,IF(O4,731200,609350)*(1+TaxBracketInflation)^13)-IF(O4,487450,243725)*(1+TaxBracketInflation)^13)*0.35+MAX(0,O39-IF(O4,731200,609350)*(1+TaxBracketInflation)^13)*0.37 | P43: =MIN(P39,IF(P4,23200,11600)*(1+TaxBracketInflation)^14)*0.1+MAX(0,MIN(P39,IF(P4,94300,47150)*(1+TaxBracketInflation)^14)-IF(P4,23200,11600)*(1+TaxBracketInflation)^14)*0.12+MAX(0,MIN(P39,IF(P4,201050,100525)*(1+TaxBracketInflation)^14)-IF(P4,94300,47150)*(1+TaxBracketInflation)^14)*0.22+MAX(0,MIN(P39,IF(P4,383900,191950)*(1+TaxBracketInflation)^14)-IF(P4,201050,100525)*(1+TaxBracketInflation)^14)*0.24+MAX(0,MIN(P39,IF(P4,487450,243725)*(1+TaxBracketInflation)^14)-IF(P4,383900,191950)*(1+TaxBracketInflation)^14)*0.32+MAX(0,MIN(P39,IF(P4,731200,609350)*(1+TaxBracketInflation)^14)-IF(P4,487450,243725)*(1+TaxBracketInflation)^14)*0.35+MAX(0,P39-IF(P4,731200,609350)*(1+TaxBracketInflation)^14)*0.37 | Q43: =MIN(Q39,IF(Q4,23200,11600)*(1+TaxBracketInflation)^15)*0.1+MAX(0,MIN(Q39,IF(Q4,94300,47150)*(1+TaxBracketInflation)^15)-IF(Q4,23200,11600)*(1+TaxBracketInflation)^15)*0.12+MAX(0,MIN(Q39,IF(Q4,201050,100525)*(1+TaxBracketInflation)^15)-IF(Q4,94300,47150)*(1+TaxBracketInflation)^15)*0.22+MAX(0,MIN(Q39,IF(Q4,383900,191950)*(1+TaxBracketInflation)^15)-IF(Q4,201050,100525)*(1+TaxBracketInflation)^15)*0.24+MAX(0,MIN(Q39,IF(Q4,487450,243725)*(1+TaxBracketInflation)^15)-IF(Q4,383900,191950)*(1+TaxBracketInflation)^15)*0.32+MAX(0,MIN(Q39,IF(Q4,731200,609350)*(1+TaxBracketInflation)^15)-IF(Q4,487450,243725)*(1+TaxBracketInflation)^15)*0.35+MAX(0,Q39-IF(Q4,731200,609350)*(1+TaxBracketInflation)^15)*0.37 | R43: =MIN(R39,IF(R4,23200,11600)*(1+TaxBracketInflation)^16)*0.1+MAX(0,MIN(R39,IF(R4,94300,47150)*(1+TaxBracketInflation)^16)-IF(R4,23200,11600)*(1+TaxBracketInflation)^16)*0.12+MAX(0,MIN(R39,IF(R4,201050,100525)*(1+TaxBracketInflation)^16)-IF(R4,94300,47150)*(1+TaxBracketInflation)^16)*0.22+MAX(0,MIN(R39,IF(R4,383900,191950)*(1+TaxBracketInflation)^16)-IF(R4,201050,100525)*(1+TaxBracketInflation)^16)*0.24+MAX(0,MIN(R39,IF(R4,487450,243725)*(1+TaxBracketInflation)^16)-IF(R4,383900,191950)*(1+TaxBracketInflation)^16)*0.32+MAX(0,MIN(R39,IF(R4,731200,609350)*(1+TaxBracketInflation)^16)-IF(R4,487450,243725)*(1+TaxBracketInflation)^16)*0.35+MAX(0,R39-IF(R4,731200,609350)*(1+TaxBracketInflation)^16)*0.37 | S43: =MIN(S39,IF(S4,23200,11600)*(1+TaxBracketInflation)^17)*0.1+MAX(0,MIN(S39,IF(S4,94300,47150)*(1+TaxBracketInflation)^17)-IF(S4,23200,11600)*(1+TaxBracketInflation)^17)*0.12+MAX(0,MIN(S39,IF(S4,201050,100525)*(1+TaxBracketInflation)^17)-IF(S4,94300,47150)*(1+TaxBracketInflation)^17)*0.22+MAX(0,MIN(S39,IF(S4,383900,191950)*(1+TaxBracketInflation)^17)-IF(S4,201050,100525)*(1+TaxBracketInflation)^17)*0.24+MAX(0,MIN(S39,IF(S4,487450,243725)*(1+TaxBracketInflation)^17)-IF(S4,383900,191950)*(1+TaxBracketInflation)^17)*0.32+MAX(0,MIN(S39,IF(S4,731200,609350)*(1+TaxBracketInflation)^17)-IF(S4,487450,243725)*(1+TaxBracketInflation)^17)*0.35+MAX(0,S39-IF(S4,731200,609350)*(1+TaxBracketInflation)^17)*0.37 | T43: =MIN(T39,IF(T4,23200,11600)*(1+TaxBracketInflation)^18)*0.1+MAX(0,MIN(T39,IF(T4,94300,47150)*(1+TaxBracketInflation)^18)-IF(T4,23200,11600)*(1+TaxBracketInflation)^18)*0.12+MAX(0,MIN(T39,IF(T4,201050,100525)*(1+TaxBracketInflation)^18)-IF(T4,94300,47150)*(1+TaxBracketInflation)^18)*0.22+MAX(0,MIN(T39,IF(T4,383900,191950)*(1+TaxBracketInflation)^18)-IF(T4,201050,100525)*(1+TaxBracketInflation)^18)*0.24+MAX(0,MIN(T39,IF(T4,487450,243725)*(1+TaxBracketInflation)^18)-IF(T4,383900,191950)*(1+TaxBracketInflation)^18)*0.32+MAX(0,MIN(T39,IF(T4,731200,609350)*(1+TaxBracketInflation)^18)-IF(T4,487450,243725)*(1+TaxBracketInflation)^18)*0.35+MAX(0,T39-IF(T4,731200,609350)*(1+TaxBracketInflation)^18)*0.37 | U43: =MIN(U39,IF(U4,23200,11600)*(1+TaxBracketInflation)^19)*0.1+MAX(0,MIN(U39,IF(U4,94300,47150)*(1+TaxBracketInflation)^19)-IF(U4,23200,11600)*(1+TaxBracketInflation)^19)*0.12+MAX(0,MIN(U39,IF(U4,201050,100525)*(1+TaxBracketInflation)^19)-IF(U4,94300,47150)*(1+TaxBracketInflation)^19)*0.22+MAX(0,MIN(U39,IF(U4,383900,191950)*(1+TaxBracketInflation)^19)-IF(U4,201050,100525)*(1+TaxBracketInflation)^19)*0.24+MAX(0,MIN(U39,IF(U4,487450,243725)*(1+TaxBracketInflation)^19)-IF(U4,383900,191950)*(1+TaxBracketInflation)^19)*0.32+MAX(0,MIN(U39,IF(U4,731200,609350)*(1+TaxBracketInflation)^19)-IF(U4,487450,243725)*(1+TaxBracketInflation)^19)*0.35+MAX(0,U39-IF(U4,731200,609350)*(1+TaxBracketInflation)^19)*0.37 | V43: =MIN(V39,IF(V4,23200,11600)*(1+TaxBracketInflation)^20)*0.1+MAX(0,MIN(V39,IF(V4,94300,47150)*(1+TaxBracketInflation)^20)-IF(V4,23200,11600)*(1+TaxBracketInflation)^20)*0.12+MAX(0,MIN(V39,IF(V4,201050,100525)*(1+TaxBracketInflation)^20)-IF(V4,94300,47150)*(1+TaxBracketInflation)^20)*0.22+MAX(0,MIN(V39,IF(V4,383900,191950)*(1+TaxBracketInflation)^20)-IF(V4,201050,100525)*(1+TaxBracketInflation)^20)*0.24+MAX(0,MIN(V39,IF(V4,487450,243725)*(1+TaxBracketInflation)^20)-IF(V4,383900,191950)*(1+TaxBracketInflation)^20)*0.32+MAX(0,MIN(V39,IF(V4,731200,609350)*(1+TaxBracketInflation)^20)-IF(V4,487450,243725)*(1+TaxBracketInflation)^20)*0.35+MAX(0,V39-IF(V4,731200,609350)*(1+TaxBracketInflation)^20)*0.37 | W43: =MIN(W39,IF(W4,23200,11600)*(1+TaxBracketInflation)^21)*0.1+MAX(0,MIN(W39,IF(W4,94300,47150)*(1+TaxBracketInflation)^21)-IF(W4,23200,11600)*(1+TaxBracketInflation)^21)*0.12+MAX(0,MIN(W39,IF(W4,201050,100525)*(1+TaxBracketInflation)^21)-IF(W4,94300,47150)*(1+TaxBracketInflation)^21)*0.22+MAX(0,MIN(W39,IF(W4,383900,191950)*(1+TaxBracketInflation)^21)-IF(W4,201050,100525)*(1+TaxBracketInflation)^21)*0.24+MAX(0,MIN(W39,IF(W4,487450,243725)*(1+TaxBracketInflation)^21)-IF(W4,383900,191950)*(1+TaxBracketInflation)^21)*0.32+MAX(0,MIN(W39,IF(W4,731200,609350)*(1+TaxBracketInflation)^21)-IF(W4,487450,243725)*(1+TaxBracketInflation)^21)*0.35+MAX(0,W39-IF(W4,731200,609350)*(1+TaxBracketInflation)^21)*0.37 | X43: =MIN(X39,IF(X4,23200,11600)*(1+TaxBracketInflation)^22)*0.1+MAX(0,MIN(X39,IF(X4,94300,47150)*(1+TaxBracketInflation)^22)-IF(X4,23200,11600)*(1+TaxBracketInflation)^22)*0.12+MAX(0,MIN(X39,IF(X4,201050,100525)*(1+TaxBracketInflation)^22)-IF(X4,94300,47150)*(1+TaxBracketInflation)^22)*0.22+MAX(0,MIN(X39,IF(X4,383900,191950)*(1+TaxBracketInflation)^22)-IF(X4,201050,100525)*(1+TaxBracketInflation)^22)*0.24+MAX(0,MIN(X39,IF(X4,487450,243725)*(1+TaxBracketInflation)^22)-IF(X4,383900,191950)*(1+TaxBracketInflation)^22)*0.32+MAX(0,MIN(X39,IF(X4,731200,609350)*(1+TaxBracketInflation)^22)-IF(X4,487450,243725)*(1+TaxBracketInflation)^22)*0.35+MAX(0,X39-IF(X4,731200,609350)*(1+TaxBracketInflation)^22)*0.37 | Y43: =MIN(Y39,IF(Y4,23200,11600)*(1+TaxBracketInflation)^23)*0.1+MAX(0,MIN(Y39,IF(Y4,94300,47150)*(1+TaxBracketInflation)^23)-IF(Y4,23200,11600)*(1+TaxBracketInflation)^23)*0.12+MAX(0,MIN(Y39,IF(Y4,201050,100525)*(1+TaxBracketInflation)^23)-IF(Y4,94300,47150)*(1+TaxBracketInflation)^23)*0.22+MAX(0,MIN(Y39,IF(Y4,383900,191950)*(1+TaxBracketInflation)^23)-IF(Y4,201050,100525)*(1+TaxBracketInflation)^23)*0.24+MAX(0,MIN(Y39,IF(Y4,487450,243725)*(1+TaxBracketInflation)^23)-IF(Y4,383900,191950)*(1+TaxBracketInflation)^23)*0.32+MAX(0,MIN(Y39,IF(Y4,731200,609350)*(1+TaxBracketInflation)^23)-IF(Y4,487450,243725)*(1+TaxBracketInflation)^23)*0.35+MAX(0,Y39-IF(Y4,731200,609350)*(1+TaxBracketInflation)^23)*0.37 | Z43: =MIN(Z39,IF(Z4,23200,11600)*(1+TaxBracketInflation)^24)*0.1+MAX(0,MIN(Z39,IF(Z4,94300,47150)*(1+TaxBracketInflation)^24)-IF(Z4,23200,11600)*(1+TaxBracketInflation)^24)*0.12+MAX(0,MIN(Z39,IF(Z4,201050,100525)*(1+TaxBracketInflation)^24)-IF(Z4,94300,47150)*(1+TaxBracketInflation)^24)*0.22+MAX(0,MIN(Z39,IF(Z4,383900,191950)*(1+TaxBracketInflation)^24)-IF(Z4,201050,100525)*(1+TaxBracketInflation)^24)*0.24+MAX(0,MIN(Z39,IF(Z4,487450,243725)*(1+TaxBracketInflation)^24)-IF(Z4,383900,191950)*(1+TaxBracketInflation)^24)*0.32+MAX(0,MIN(Z39,IF(Z4,731200,609350)*(1+TaxBracketInflation)^24)-IF(Z4,487450,243725)*(1+TaxBracketInflation)^24)*0.35+MAX(0,Z39-IF(Z4,731200,609350)*(1+TaxBracketInflation)^24)*0.37 | AA43: =MIN(AA39,IF(AA4,23200,11600)*(1+TaxBracketInflation)^25)*0.1+MAX(0,MIN(AA39,IF(AA4,94300,47150)*(1+TaxBracketInflation)^25)-IF(AA4,23200,11600)*(1+TaxBracketInflation)^25)*0.12+MAX(0,MIN(AA39,IF(AA4,201050,100525)*(1+TaxBracketInflation)^25)-IF(AA4,94300,47150)*(1+TaxBracketInflation)^25)*0.22+MAX(0,MIN(AA39,IF(AA4,383900,191950)*(1+TaxBracketInflation)^25)-IF(AA4,201050,100525)*(1+TaxBracketInflation)^25)*0.24+MAX(0,MIN(AA39,IF(AA4,487450,243725)*(1+TaxBracketInflation)^25)-IF(AA4,383900,191950)*(1+TaxBracketInflation)^25)*0.32+MAX(0,MIN(AA39,IF(AA4,731200,609350)*(1+TaxBracketInflation)^25)-IF(AA4,487450,243725)*(1+TaxBracketInflation)^25)*0.35+MAX(0,AA39-IF(AA4,731200,609350)*(1+TaxBracketInflation)^25)*0.37 | AB43: =MIN(AB39,IF(AB4,23200,11600)*(1+TaxBracketInflation)^26)*0.1+MAX(0,MIN(AB39,IF(AB4,94300,47150)*(1+TaxBracketInflation)^26)-IF(AB4,23200,11600)*(1+TaxBracketInflation)^26)*0.12+MAX(0,MIN(AB39,IF(AB4,201050,100525)*(1+TaxBracketInflation)^26)-IF(AB4,94300,47150)*(1+TaxBracketInflation)^26)*0.22+MAX(0,MIN(AB39,IF(AB4,383900,191950)*(1+TaxBracketInflation)^26)-IF(AB4,201050,100525)*(1+TaxBracketInflation)^26)*0.24+MAX(0,MIN(AB39,IF(AB4,487450,243725)*(1+TaxBracketInflation)^26)-IF(AB4,383900,191950)*(1+TaxBracketInflation)^26)*0.32+MAX(0,MIN(AB39,IF(AB4,731200,609350)*(1+TaxBracketInflation)^26)-IF(AB4,487450,243725)*(1+TaxBracketInflation)^26)*0.35+MAX(0,AB39-IF(AB4,731200,609350)*(1+TaxBracketInflation)^26)*0.37 | AC43: =MIN(AC39,IF(AC4,23200,11600)*(1+TaxBracketInflation)^27)*0.1+MAX(0,MIN(AC39,IF(AC4,94300,47150)*(1+TaxBracketInflation)^27)-IF(AC4,23200,11600)*(1+TaxBracketInflation)^27)*0.12+MAX(0,MIN(AC39,IF(AC4,201050,100525)*(1+TaxBracketInflation)^27)-IF(AC4,94300,47150)*(1+TaxBracketInflation)^27)*0.22+MAX(0,MIN(AC39,IF(AC4,383900,191950)*(1+TaxBracketInflation)^27)-IF(AC4,201050,100525)*(1+TaxBracketInflation)^27)*0.24+MAX(0,MIN(AC39,IF(AC4,487450,243725)*(1+TaxBracketInflation)^27)-IF(AC4,383900,191950)*(1+TaxBracketInflation)^27)*0.32+MAX(0,MIN(AC39,IF(AC4,731200,609350)*(1+TaxBracketInflation)^27)-IF(AC4,487450,243725)*(1+TaxBracketInflation)^27)*0.35+MAX(0,AC39-IF(AC4,731200,609350)*(1+TaxBracketInflation)^27)*0.37 | AD43: =MIN(AD39,IF(AD4,23200,11600)*(1+TaxBracketInflation)^28)*0.1+MAX(0,MIN(AD39,IF(AD4,94300,47150)*(1+TaxBracketInflation)^28)-IF(AD4,23200,11600)*(1+TaxBracketInflation)^28)*0.12+MAX(0,MIN(AD39,IF(AD4,201050,100525)*(1+TaxBracketInflation)^28)-IF(AD4,94300,47150)*(1+TaxBracketInflation)^28)*0.22+MAX(0,MIN(AD39,IF(AD4,383900,191950)*(1+TaxBracketInflation)^28)-IF(AD4,201050,100525)*(1+TaxBracketInflation)^28)*0.24+MAX(0,MIN(AD39,IF(AD4,487450,243725)*(1+TaxBracketInflation)^28)-IF(AD4,383900,191950)*(1+TaxBracketInflation)^28)*0.32+MAX(0,MIN(AD39,IF(AD4,731200,609350)*(1+TaxBracketInflation)^28)-IF(AD4,487450,243725)*(1+TaxBracketInflation)^28)*0.35+MAX(0,AD39-IF(AD4,731200,609350)*(1+TaxBracketInflation)^28)*0.37 | AE43: =MIN(AE39,IF(AE4,23200,11600)*(1+TaxBracketInflation)^29)*0.1+MAX(0,MIN(AE39,IF(AE4,94300,47150)*(1+TaxBracketInflation)^29)-IF(AE4,23200,11600)*(1+TaxBracketInflation)^29)*0.12+MAX(0,MIN(AE39,IF(AE4,201050,100525)*(1+TaxBracketInflation)^29)-IF(AE4,94300,47150)*(1+TaxBracketInflation)^29)*0.22+MAX(0,MIN(AE39,IF(AE4,383900,191950)*(1+TaxBracketInflation)^29)-IF(AE4,201050,100525)*(1+TaxBracketInflation)^29)*0.24+MAX(0,MIN(AE39,IF(AE4,487450,243725)*(1+TaxBracketInflation)^29)-IF(AE4,383900,191950)*(1+TaxBracketInflation)^29)*0.32+MAX(0,MIN(AE39,IF(AE4,731200,609350)*(1+TaxBracketInflation)^29)-IF(AE4,487450,243725)*(1+TaxBracketInflation)^29)*0.35+MAX(0,AE39-IF(AE4,731200,609350)*(1+TaxBracketInflation)^29)*0.37
A44: Fed Cap Gains Tax | B44: =(B42-MIN(B42,MAX(0,(B39+B40)-IF(B4,583750,518900)*(1+TaxBracketInflation)^0)))*0.15+(MIN(B42,MAX(0,(B39+B40)-IF(B4,583750,518900)*(1+TaxBracketInflation)^0)))*0.20 | C44: =(C42-MIN(C42,MAX(0,(C39+C40)-IF(C4,583750,518900)*(1+TaxBracketInflation)^1)))*0.15+(MIN(C42,MAX(0,(C39+C40)-IF(C4,583750,518900)*(1+TaxBracketInflation)^1)))*0.20 | D44: =(D42-MIN(D42,MAX(0,(D39+D40)-IF(D4,583750,518900)*(1+TaxBracketInflation)^2)))*0.15+(MIN(D42,MAX(0,(D39+D40)-IF(D4,583750,518900)*(1+TaxBracketInflation)^2)))*0.20 | E44: =(E42-MIN(E42,MAX(0,(E39+E40)-IF(E4,583750,518900)*(1+TaxBracketInflation)^3)))*0.15+(MIN(E42,MAX(0,(E39+E40)-IF(E4,583750,518900)*(1+TaxBracketInflation)^3)))*0.20 | F44: =(F42-MIN(F42,MAX(0,(F39+F40)-IF(F4,583750,518900)*(1+TaxBracketInflation)^4)))*0.15+(MIN(F42,MAX(0,(F39+F40)-IF(F4,583750,518900)*(1+TaxBracketInflation)^4)))*0.20 | G44: =(G42-MIN(G42,MAX(0,(G39+G40)-IF(G4,583750,518900)*(1+TaxBracketInflation)^5)))*0.15+(MIN(G42,MAX(0,(G39+G40)-IF(G4,583750,518900)*(1+TaxBracketInflation)^5)))*0.20 | H44: =(H42-MIN(H42,MAX(0,(H39+H40)-IF(H4,583750,518900)*(1+TaxBracketInflation)^6)))*0.15+(MIN(H42,MAX(0,(H39+H40)-IF(H4,583750,518900)*(1+TaxBracketInflation)^6)))*0.20 | I44: =(I42-MIN(I42,MAX(0,(I39+I40)-IF(I4,583750,518900)*(1+TaxBracketInflation)^7)))*0.15+(MIN(I42,MAX(0,(I39+I40)-IF(I4,583750,518900)*(1+TaxBracketInflation)^7)))*0.20 | J44: =(J42-MIN(J42,MAX(0,(J39+J40)-IF(J4,583750,518900)*(1+TaxBracketInflation)^8)))*0.15+(MIN(J42,MAX(0,(J39+J40)-IF(J4,583750,518900)*(1+TaxBracketInflation)^8)))*0.20 | K44: =(K42-MIN(K42,MAX(0,(K39+K40)-IF(K4,583750,518900)*(1+TaxBracketInflation)^9)))*0.15+(MIN(K42,MAX(0,(K39+K40)-IF(K4,583750,518900)*(1+TaxBracketInflation)^9)))*0.20 | L44: =(L42-MIN(L42,MAX(0,(L39+L40)-IF(L4,583750,518900)*(1+TaxBracketInflation)^10)))*0.15+(MIN(L42,MAX(0,(L39+L40)-IF(L4,583750,518900)*(1+TaxBracketInflation)^10)))*0.20 | M44: =(M42-MIN(M42,MAX(0,(M39+M40)-IF(M4,583750,518900)*(1+TaxBracketInflation)^11)))*0.15+(MIN(M42,MAX(0,(M39+M40)-IF(M4,583750,518900)*(1+TaxBracketInflation)^11)))*0.20 | N44: =(N42-MIN(N42,MAX(0,(N39+N40)-IF(N4,583750,518900)*(1+TaxBracketInflation)^12)))*0.15+(MIN(N42,MAX(0,(N39+N40)-IF(N4,583750,518900)*(1+TaxBracketInflation)^12)))*0.20 | O44: =(O42-MIN(O42,MAX(0,(O39+O40)-IF(O4,583750,518900)*(1+TaxBracketInflation)^13)))*0.15+(MIN(O42,MAX(0,(O39+O40)-IF(O4,583750,518900)*(1+TaxBracketInflation)^13)))*0.20 | P44: =(P42-MIN(P42,MAX(0,(P39+P40)-IF(P4,583750,518900)*(1+TaxBracketInflation)^14)))*0.15+(MIN(P42,MAX(0,(P39+P40)-IF(P4,583750,518900)*(1+TaxBracketInflation)^14)))*0.20 | Q44: =(Q42-MIN(Q42,MAX(0,(Q39+Q40)-IF(Q4,583750,518900)*(1+TaxBracketInflation)^15)))*0.15+(MIN(Q42,MAX(0,(Q39+Q40)-IF(Q4,583750,518900)*(1+TaxBracketInflation)^15)))*0.20 | R44: =(R42-MIN(R42,MAX(0,(R39+R40)-IF(R4,583750,518900)*(1+TaxBracketInflation)^16)))*0.15+(MIN(R42,MAX(0,(R39+R40)-IF(R4,583750,518900)*(1+TaxBracketInflation)^16)))*0.20 | S44: =(S42-MIN(S42,MAX(0,(S39+S40)-IF(S4,583750,518900)*(1+TaxBracketInflation)^17)))*0.15+(MIN(S42,MAX(0,(S39+S40)-IF(S4,583750,518900)*(1+TaxBracketInflation)^17)))*0.20 | T44: =(T42-MIN(T42,MAX(0,(T39+T40)-IF(T4,583750,518900)*(1+TaxBracketInflation)^18)))*0.15+(MIN(T42,MAX(0,(T39+T40)-IF(T4,583750,518900)*(1+TaxBracketInflation)^18)))*0.20 | U44: =(U42-MIN(U42,MAX(0,(U39+U40)-IF(U4,583750,518900)*(1+TaxBracketInflation)^19)))*0.15+(MIN(U42,MAX(0,(U39+U40)-IF(U4,583750,518900)*(1+TaxBracketInflation)^19)))*0.20 | V44: =(V42-MIN(V42,MAX(0,(V39+V40)-IF(V4,583750,518900)*(1+TaxBracketInflation)^20)))*0.15+(MIN(V42,MAX(0,(V39+V40)-IF(V4,583750,518900)*(1+TaxBracketInflation)^20)))*0.20 | W44: =(W42-MIN(W42,MAX(0,(W39+W40)-IF(W4,583750,518900)*(1+TaxBracketInflation)^21)))*0.15+(MIN(W42,MAX(0,(W39+W40)-IF(W4,583750,518900)*(1+TaxBracketInflation)^21)))*0.20 | X44: =(X42-MIN(X42,MAX(0,(X39+X40)-IF(X4,583750,518900)*(1+TaxBracketInflation)^22)))*0.15+(MIN(X42,MAX(0,(X39+X40)-IF(X4,583750,518900)*(1+TaxBracketInflation)^22)))*0.20 | Y44: =(Y42-MIN(Y42,MAX(0,(Y39+Y40)-IF(Y4,583750,518900)*(1+TaxBracketInflation)^23)))*0.15+(MIN(Y42,MAX(0,(Y39+Y40)-IF(Y4,583750,518900)*(1+TaxBracketInflation)^23)))*0.20 | Z44: =(Z42-MIN(Z42,MAX(0,(Z39+Z40)-IF(Z4,583750,518900)*(1+TaxBracketInflation)^24)))*0.15+(MIN(Z42,MAX(0,(Z39+Z40)-IF(Z4,583750,518900)*(1+TaxBracketInflation)^24)))*0.20 | AA44: =(AA42-MIN(AA42,MAX(0,(AA39+AA40)-IF(AA4,583750,518900)*(1+TaxBracketInflation)^25)))*0.15+(MIN(AA42,MAX(0,(AA39+AA40)-IF(AA4,583750,518900)*(1+TaxBracketInflation)^25)))*0.20 | AB44: =(AB42-MIN(AB42,MAX(0,(AB39+AB40)-IF(AB4,583750,518900)*(1+TaxBracketInflation)^26)))*0.15+(MIN(AB42,MAX(0,(AB39+AB40)-IF(AB4,583750,518900)*(1+TaxBracketInflation)^26)))*0.20 | AC44: =(AC42-MIN(AC42,MAX(0,(AC39+AC40)-IF(AC4,583750,518900)*(1+TaxBracketInflation)^27)))*0.15+(MIN(AC42,MAX(0,(AC39+AC40)-IF(AC4,583750,518900)*(1+TaxBracketInflation)^27)))*0.20 | AD44: =(AD42-MIN(AD42,MAX(0,(AD39+AD40)-IF(AD4,583750,518900)*(1+TaxBracketInflation)^28)))*0.15+(MIN(AD42,MAX(0,(AD39+AD40)-IF(AD4,583750,518900)*(1+TaxBracketInflation)^28)))*0.20 | AE44: =(AE42-MIN(AE42,MAX(0,(AE39+AE40)-IF(AE4,583750,518900)*(1+TaxBracketInflation)^29)))*0.15+(MIN(AE42,MAX(0,(AE39+AE40)-IF(AE4,583750,518900)*(1+TaxBracketInflation)^29)))*0.20
A45: NIIT (3.8%) | B45: =0.038*MIN(B40,MAX(0,(B39+IF(B4,StdDeduction,StdDeductionSingle)*(1+TaxBracketInflation)^0+B40)-IF(B4,NIITThreshold,NIITThresholdSingle)*(1+TaxBracketInflation)^0)) | C45: =0.038*MIN(C40,MAX(0,(C39+IF(C4,StdDeduction,StdDeductionSingle)*(1+TaxBracketInflation)^1+C40)-IF(C4,NIITThreshold,NIITThresholdSingle)*(1+TaxBracketInflation)^1)) | D45: =0.038*MIN(D40,MAX(0,(D39+IF(D4,StdDeduction,StdDeductionSingle)*(1+TaxBracketInflation)^2+D40)-IF(D4,NIITThreshold,NIITThresholdSingle)*(1+TaxBracketInflation)^2)) | E45: =0.038*MIN(E40,MAX(0,(E39+IF(E4,StdDeduction,StdDeductionSingle)*(1+TaxBracketInflation)^3+E40)-IF(E4,NIITThreshold,NIITThresholdSingle)*(1+TaxBracketInflation)^3)) | F45: =0.038*MIN(F40,MAX(0,(F39+IF(F4,StdDeduction,StdDeductionSingle)*(1+TaxBracketInflation)^4+F40)-IF(F4,NIITThreshold,NIITThresholdSingle)*(1+TaxBracketInflation)^4)) | G45: =0.038*MIN(G40,MAX(0,(G39+IF(G4,StdDeduction,StdDeductionSingle)*(1+TaxBracketInflation)^5+G40)-IF(G4,NIITThreshold,NIITThresholdSingle)*(1+TaxBracketInflation)^5)) | H45: =0.038*MIN(H40,MAX(0,(H39+IF(H4,StdDeduction,StdDeductionSingle)*(1+TaxBracketInflation)^6+H40)-IF(H4,NIITThreshold,NIITThresholdSingle)*(1+TaxBracketInflation)^6)) | I45: =0.038*MIN(I40,MAX(0,(I39+IF(I4,StdDeduction,StdDeductionSingle)*(1+TaxBracketInflation)^7+I40)-IF(I4,NIITThreshold,NIITThresholdSingle)*(1+TaxBracketInflation)^7)) | J45: =0.038*MIN(J40,MAX(0,(J39+IF(J4,StdDeduction,StdDeductionSingle)*(1+TaxBracketInflation)^8+J40)-IF(J4,NIITThreshold,NIITThresholdSingle)*(1+TaxBracketInflation)^8)) | K45: =0.038*MIN(K40,MAX(0,(K39+IF(K4,StdDeduction,StdDeductionSingle)*(1+TaxBracketInflation)^9+K40)-IF(K4,NIITThreshold,NIITThresholdSingle)*(1+TaxBracketInflation)^9)) | L45: =0.038*MIN(L40,MAX(0,(L39+IF(L4,StdDeduction,StdDeductionSingle)*(1+TaxBracketInflation)^10+L40)-IF(L4,NIITThreshold,NIITThresholdSingle)*(1+TaxBracketInflation)^10)) | M45: =0.038*MIN(M40,MAX(0,(M39+IF(M4,StdDeduction,StdDeductionSingle)*(1+TaxBracketInflation)^11+M40)-IF(M4,NIITThreshold,NIITThresholdSingle)*(1+TaxBracketInflation)^11)) | N45: =0.038*MIN(N40,MAX(0,(N39+IF(N4,StdDeduction,StdDeductionSingle)*(1+TaxBracketInflation)^12+N40)-IF(N4,NIITThreshold,NIITThresholdSingle)*(1+TaxBracketInflation)^12)) | O45: =0.038*MIN(O40,MAX(0,(O39+IF(O4,StdDeduction,StdDeductionSingle)*(1+TaxBracketInflation)^13+O40)-IF(O4,NIITThreshold,NIITThresholdSingle)*(1+TaxBracketInflation)^13)) | P45: =0.038*MIN(P40,MAX(0,(P39+IF(P4,StdDeduction,StdDeductionSingle)*(1+TaxBracketInflation)^14+P40)-IF(P4,NIITThreshold,NIITThresholdSingle)*(1+TaxBracketInflation)^14)) | Q45: =0.038*MIN(Q40,MAX(0,(Q39+IF(Q4,StdDeduction,StdDeductionSingle)*(1+TaxBracketInflation)^15+Q40)-IF(Q4,NIITThreshold,NIITThresholdSingle)*(1+TaxBracketInflation)^15)) | R45: =0.038*MIN(R40,MAX(0,(R39+IF(R4,StdDeduction,StdDeductionSingle)*(1+TaxBracketInflation)^16+R40)-IF(R4,NIITThreshold,NIITThresholdSingle)*(1+TaxBracketInflation)^16)) | S45: =0.038*MIN(S40,MAX(0,(S39+IF(S4,StdDeduction,StdDeductionSingle)*(1+TaxBracketInflation)^17+S40)-IF(S4,NIITThreshold,NIITThresholdSingle)*(1+TaxBracketInflation)^17)) | T45: =0.038*MIN(T40,MAX(0,(T39+IF(T4,StdDeduction,StdDeductionSingle)*(1+TaxBracketInflation)^18+T40)-IF(T4,NIITThreshold,NIITThresholdSingle)*(1+TaxBracketInflation)^18)) | U45: =0.038*MIN(U40,MAX(0,(U39+IF(U4,StdDeduction,StdDeductionSingle)*(1+TaxBracketInflation)^19+U40)-IF(U4,NIITThreshold,NIITThresholdSingle)*(1+TaxBracketInflation)^19)) | V45: =0.038*MIN(V40,MAX(0,(V39+IF(V4,StdDeduction,StdDeductionSingle)*(1+TaxBracketInflation)^20+V40)-IF(V4,NIITThreshold,NIITThresholdSingle)*(1+TaxBracketInflation)^20)) | W45: =0.038*MIN(W40,MAX(0,(W39+IF(W4,StdDeduction,StdDeductionSingle)*(1+TaxBracketInflation)^21+W40)-IF(W4,NIITThreshold,NIITThresholdSingle)*(1+TaxBracketInflation)^21)) | X45: =0.038*MIN(X40,MAX(0,(X39+IF(X4,StdDeduction,StdDeductionSingle)*(1+TaxBracketInflation)^22+X40)-IF(X4,NIITThreshold,NIITThresholdSingle)*(1+TaxBracketInflation)^22)) | Y45: =0.038*MIN(Y40,MAX(0,(Y39+IF(Y4,StdDeduction,StdDeductionSingle)*(1+TaxBracketInflation)^23+Y40)-IF(Y4,NIITThreshold,NIITThresholdSingle)*(1+TaxBracketInflation)^23)) | Z45: =0.038*MIN(Z40,MAX(0,(Z39+IF(Z4,StdDeduction,StdDeductionSingle)*(1+TaxBracketInflation)^24+Z40)-IF(Z4,NIITThreshold,NIITThresholdSingle)*(1+TaxBracketInflation)^24)) | AA45: =0.038*MIN(AA40,MAX(0,(AA39+IF(AA4,StdDeduction,StdDeductionSingle)*(1+TaxBracketInflation)^25+AA40)-IF(AA4,NIITThreshold,NIITThresholdSingle)*(1+TaxBracketInflation)^25)) | AB45: =0.038*MIN(AB40,MAX(0,(AB39+IF(AB4,StdDeduction,StdDeductionSingle)*(1+TaxBracketInflation)^26+AB40)-IF(AB4,NIITThreshold,NIITThresholdSingle)*(1+TaxBracketInflation)^26)) | AC45: =0.038*MIN(AC40,MAX(0,(AC39+IF(AC4,StdDeduction,StdDeductionSingle)*(1+TaxBracketInflation)^27+AC40)-IF(AC4,NIITThreshold,NIITThresholdSingle)*(1+TaxBracketInflation)^27)) | AD45: =0.038*MIN(AD40,MAX(0,(AD39+IF(AD4,StdDeduction,StdDeductionSingle)*(1+TaxBracketInflation)^28+AD40)-IF(AD4,NIITThreshold,NIITThresholdSingle)*(1+TaxBracketInflation)^28)) | AE45: =0.038*MIN(AE40,MAX(0,(AE39+IF(AE4,StdDeduction,StdDeductionSingle)*(1+TaxBracketInflation)^29+AE40)-IF(AE4,NIITThreshold,NIITThresholdSingle)*(1+TaxBracketInflation)^29))
A46: Illinois Tax | B46: =(B14+B40)*ILTaxRate | C46: =(C14+C40)*ILTaxRate | D46: =(D14+D40)*ILTaxRate | E46: =(E14+E40)*ILTaxRate | F46: =(F14+F40)*ILTaxRate | G46: =(G14+G40)*ILTaxRate | H46: =(H14+H40)*ILTaxRate | I46: =(I14+I40)*ILTaxRate | ... AE46: =(AE14+AE40)*ILTaxRate
A47: Total Tax | B47: =B43+B44+B45+B46 | C47: =C43+C44+C45+C46 | D47: =D43+D44+D45+D46 | E47: =E43+E44+E45+E46 | F47: =F43+F44+F45+F46 | G47: =G43+G44+G45+G46 | H47: =H43+H44+H45+H46 | I47: =I43+I44+I45+I46 | ... AE47: =AE43+AE44+AE45+AE46
A49: ENDING BALANCES
A50: After-Tax | B50: =MAX(0,B7+B20+B16-B32) | C50: =MAX(0,C7+C20+C16-C32) | D50: =MAX(0,D7+D20+D16-D32) | E50: =MAX(0,E7+E20+E16-E32) | F50: =MAX(0,F7+F20+F16-F32) | G50: =MAX(0,G7+G20+G16-G32) | H50: =MAX(0,H7+H20+H16-H32) | I50: =MAX(0,I7+I20+I16-I32) | ... AE50: =MAX(0,AE7+AE20+AE16-AE32)
A51: Traditional IRA | B51: =MAX(0,B8-B17+B21-B16-B33) | C51: =MAX(0,C8-C17+C21-C16-C33) | D51: =MAX(0,D8-D17+D21-D16-D33) | E51: =MAX(0,E8-E17+E21-E16-E33) | F51: =MAX(0,F8-F17+F21-F16-F33) | G51: =MAX(0,G8-G17+G21-G16-G33) | H51: =MAX(0,H8-H17+H21-H16-H33) | I51: =MAX(0,I8-I17+I21-I16-I33) | ... AE51: =MAX(0,AE8-AE17+AE21-AE16-AE33)
A52: Roth IRA | B52: =MAX(0,B9+B17+B22-B34) | C52: =MAX(0,C9+C17+C22-C34) | D52: =MAX(0,D9+D17+D22-D34) | E52: =MAX(0,E9+E17+E22-E34) | F52: =MAX(0,F9+F17+F22-F34) | G52: =MAX(0,G9+G17+G22-G34) | H52: =MAX(0,H9+H17+H22-H34) | I52: =MAX(0,I9+I17+I22-I34) | ... AE52: =MAX(0,AE9+AE17+AE22-AE34)
A53: Total | B53: =B50+B51+B52 | C53: =C50+C51+C52 | D53: =D50+D51+D52 | E53: =E50+E51+E52 | F53: =F50+F51+F52 | G53: =G50+G51+G52 | H53: =H50+H51+H52 | I53: =I50+I51+I52 | ... AE53: =AE50+AE51+AE52
A54: Heir-Adjusted Value | B54: =B50+B51*(1-HeirTaxRate)+B52 | C54: =C50+C51*(1-HeirTaxRate)+C52 | D54: =D50+D51*(1-HeirTaxRate)+D52 | E54: =E50+E51*(1-HeirTaxRate)+E52 | F54: =F50+F51*(1-HeirTaxRate)+F52 | G54: =G50+G51*(1-HeirTaxRate)+G52 | H54: =H50+H51*(1-HeirTaxRate)+H52 | I54: =I50+I51*(1-HeirTaxRate)+I52 | ... AE54: =AE50+AE51*(1-HeirTaxRate)+AE52
A56: PRESENT VALUES (2026$)
A57: PV After-Tax | B57: =B50/(1+DiscountRate)^0 | C57: =C50/(1+DiscountRate)^1 | D57: =D50/(1+DiscountRate)^2 | E57: =E50/(1+DiscountRate)^3 | F57: =F50/(1+DiscountRate)^4 | G57: =G50/(1+DiscountRate)^5 | H57: =H50/(1+DiscountRate)^6 | I57: =I50/(1+DiscountRate)^7 | J57: =J50/(1+DiscountRate)^8 | K57: =K50/(1+DiscountRate)^9 | L57: =L50/(1+DiscountRate)^10 | M57: =M50/(1+DiscountRate)^11 | N57: =N50/(1+DiscountRate)^12 | O57: =O50/(1+DiscountRate)^13 | P57: =P50/(1+DiscountRate)^14 | Q57: =Q50/(1+DiscountRate)^15 | R57: =R50/(1+DiscountRate)^16 | S57: =S50/(1+DiscountRate)^17 | T57: =T50/(1+DiscountRate)^18 | U57: =U50/(1+DiscountRate)^19 | V57: =V50/(1+DiscountRate)^20 | W57: =W50/(1+DiscountRate)^21 | X57: =X50/(1+DiscountRate)^22 | Y57: =Y50/(1+DiscountRate)^23 | Z57: =Z50/(1+DiscountRate)^24 | AA57: =AA50/(1+DiscountRate)^25 | AB57: =AB50/(1+DiscountRate)^26 | AC57: =AC50/(1+DiscountRate)^27 | AD57: =AD50/(1+DiscountRate)^28 | AE57: =AE50/(1+DiscountRate)^29
A58: PV Traditional IRA | B58: =B51/(1+DiscountRate)^0 | C58: =C51/(1+DiscountRate)^1 | D58: =D51/(1+DiscountRate)^2 | E58: =E51/(1+DiscountRate)^3 | F58: =F51/(1+DiscountRate)^4 | G58: =G51/(1+DiscountRate)^5 | H58: =H51/(1+DiscountRate)^6 | I58: =I51/(1+DiscountRate)^7 | J58: =J51/(1+DiscountRate)^8 | K58: =K51/(1+DiscountRate)^9 | L58: =L51/(1+DiscountRate)^10 | M58: =M51/(1+DiscountRate)^11 | N58: =N51/(1+DiscountRate)^12 | O58: =O51/(1+DiscountRate)^13 | P58: =P51/(1+DiscountRate)^14 | Q58: =Q51/(1+DiscountRate)^15 | R58: =R51/(1+DiscountRate)^16 | S58: =S51/(1+DiscountRate)^17 | T58: =T51/(1+DiscountRate)^18 | U58: =U51/(1+DiscountRate)^19 | V58: =V51/(1+DiscountRate)^20 | W58: =W51/(1+DiscountRate)^21 | X58: =X51/(1+DiscountRate)^22 | Y58: =Y51/(1+DiscountRate)^23 | Z58: =Z51/(1+DiscountRate)^24 | AA58: =AA51/(1+DiscountRate)^25 | AB58: =AB51/(1+DiscountRate)^26 | AC58: =AC51/(1+DiscountRate)^27 | AD58: =AD51/(1+DiscountRate)^28 | AE58: =AE51/(1+DiscountRate)^29
A59: PV Roth IRA | B59: =B52/(1+DiscountRate)^0 | C59: =C52/(1+DiscountRate)^1 | D59: =D52/(1+DiscountRate)^2 | E59: =E52/(1+DiscountRate)^3 | F59: =F52/(1+DiscountRate)^4 | G59: =G52/(1+DiscountRate)^5 | H59: =H52/(1+DiscountRate)^6 | I59: =I52/(1+DiscountRate)^7 | J59: =J52/(1+DiscountRate)^8 | K59: =K52/(1+DiscountRate)^9 | L59: =L52/(1+DiscountRate)^10 | M59: =M52/(1+DiscountRate)^11 | N59: =N52/(1+DiscountRate)^12 | O59: =O52/(1+DiscountRate)^13 | P59: =P52/(1+DiscountRate)^14 | Q59: =Q52/(1+DiscountRate)^15 | R59: =R52/(1+DiscountRate)^16 | S59: =S52/(1+DiscountRate)^17 | T59: =T52/(1+DiscountRate)^18 | U59: =U52/(1+DiscountRate)^19 | V59: =V52/(1+DiscountRate)^20 | W59: =W52/(1+DiscountRate)^21 | X59: =X52/(1+DiscountRate)^22 | Y59: =Y52/(1+DiscountRate)^23 | Z59: =Z52/(1+DiscountRate)^24 | AA59: =AA52/(1+DiscountRate)^25 | AB59: =AB52/(1+DiscountRate)^26 | AC59: =AC52/(1+DiscountRate)^27 | AD59: =AD52/(1+DiscountRate)^28 | AE59: =AE52/(1+DiscountRate)^29
A60: PV Total | B60: =B53/(1+DiscountRate)^0 | C60: =C53/(1+DiscountRate)^1 | D60: =D53/(1+DiscountRate)^2 | E60: =E53/(1+DiscountRate)^3 | F60: =F53/(1+DiscountRate)^4 | G60: =G53/(1+DiscountRate)^5 | H60: =H53/(1+DiscountRate)^6 | I60: =I53/(1+DiscountRate)^7 | J60: =J53/(1+DiscountRate)^8 | K60: =K53/(1+DiscountRate)^9 | L60: =L53/(1+DiscountRate)^10 | M60: =M53/(1+DiscountRate)^11 | N60: =N53/(1+DiscountRate)^12 | O60: =O53/(1+DiscountRate)^13 | P60: =P53/(1+DiscountRate)^14 | Q60: =Q53/(1+DiscountRate)^15 | R60: =R53/(1+DiscountRate)^16 | S60: =S53/(1+DiscountRate)^17 | T60: =T53/(1+DiscountRate)^18 | U60: =U53/(1+DiscountRate)^19 | V60: =V53/(1+DiscountRate)^20 | W60: =W53/(1+DiscountRate)^21 | X60: =X53/(1+DiscountRate)^22 | Y60: =Y53/(1+DiscountRate)^23 | Z60: =Z53/(1+DiscountRate)^24 | AA60: =AA53/(1+DiscountRate)^25 | AB60: =AB53/(1+DiscountRate)^26 | AC60: =AC53/(1+DiscountRate)^27 | AD60: =AD53/(1+DiscountRate)^28 | AE60: =AE53/(1+DiscountRate)^29
A61: PV Heir-Adjusted | B61: =B54/(1+DiscountRate)^0 | C61: =C54/(1+DiscountRate)^1 | D61: =D54/(1+DiscountRate)^2 | E61: =E54/(1+DiscountRate)^3 | F61: =F54/(1+DiscountRate)^4 | G61: =G54/(1+DiscountRate)^5 | H61: =H54/(1+DiscountRate)^6 | I61: =I54/(1+DiscountRate)^7 | J61: =J54/(1+DiscountRate)^8 | K61: =K54/(1+DiscountRate)^9 | L61: =L54/(1+DiscountRate)^10 | M61: =M54/(1+DiscountRate)^11 | N61: =N54/(1+DiscountRate)^12 | O61: =O54/(1+DiscountRate)^13 | P61: =P54/(1+DiscountRate)^14 | Q61: =Q54/(1+DiscountRate)^15 | R61: =R54/(1+DiscountRate)^16 | S61: =S54/(1+DiscountRate)^17 | T61: =T54/(1+DiscountRate)^18 | U61: =U54/(1+DiscountRate)^19 | V61: =V54/(1+DiscountRate)^20 | W61: =W54/(1+DiscountRate)^21 | X61: =X54/(1+DiscountRate)^22 | Y61: =Y54/(1+DiscountRate)^23 | Z61: =Z54/(1+DiscountRate)^24 | AA61: =AA54/(1+DiscountRate)^25 | AB61: =AB54/(1+DiscountRate)^26 | AC61: =AC54/(1+DiscountRate)^27 | AD61: =AD54/(1+DiscountRate)^28 | AE61: =AE54/(1+DiscountRate)^29
A62: PV Expenses | B62: =B15/(1+DiscountRate)^0 | C62: =C15/(1+DiscountRate)^1 | D62: =D15/(1+DiscountRate)^2 | E62: =E15/(1+DiscountRate)^3 | F62: =F15/(1+DiscountRate)^4 | G62: =G15/(1+DiscountRate)^5 | H62: =H15/(1+DiscountRate)^6 | I62: =I15/(1+DiscountRate)^7 | J62: =J15/(1+DiscountRate)^8 | K62: =K15/(1+DiscountRate)^9 | L62: =L15/(1+DiscountRate)^10 | M62: =M15/(1+DiscountRate)^11 | N62: =N15/(1+DiscountRate)^12 | O62: =O15/(1+DiscountRate)^13 | P62: =P15/(1+DiscountRate)^14 | Q62: =Q15/(1+DiscountRate)^15 | R62: =R15/(1+DiscountRate)^16 | S62: =S15/(1+DiscountRate)^17 | T62: =T15/(1+DiscountRate)^18 | U62: =U15/(1+DiscountRate)^19 | V62: =V15/(1+DiscountRate)^20 | W62: =W15/(1+DiscountRate)^21 | X62: =X15/(1+DiscountRate)^22 | Y62: =Y15/(1+DiscountRate)^23 | Z62: =Z15/(1+DiscountRate)^24 | AA62: =AA15/(1+DiscountRate)^25 | AB62: =AB15/(1+DiscountRate)^26 | AC62: =AC15/(1+DiscountRate)^27 | AD62: =AD15/(1+DiscountRate)^28 | AE62: =AE15/(1+DiscountRate)^29

Sheet Risk Allocation
A1: Year | B1: =Projections!B1 | C1: =Projections!C1 | D1: =Projections!D1 | E1: =Projections!E1 | F1: =Projections!F1 | G1: =Projections!G1 | H1: =Projections!H1 | I1: =Projections!I1 | ... AE1: =Projections!AE1
A3: ACCOUNT BALANCES (from Projections)
A4: After-Tax | B4: =Projections!B7 | C4: =Projections!C7 | D4: =Projections!D7 | E4: =Projections!E7 | F4: =Projections!F7 | G4: =Projections!G7 | H4: =Projections!H7 | I4: =Projections!I7 | ... AE4: =Projections!AE7
A5: Traditional IRA | B5: =Projections!B8 | C5: =Projections!C8 | D5: =Projections!D8 | E5: =Projections!E8 | F5: =Projections!F8 | G5: =Projections!G8 | H5: =Projections!H8 | I5: =Projections!I8 | ... AE5: =Projections!AE8
A6: Roth IRA | B6: =Projections!B9 | C6: =Projections!C9 | D6: =Projections!D9 | E6: =Projections!E9 | F6: =Projections!F9 | G6: =Projections!G9 | H6: =Projections!H9 | I6: =Projections!I9 | ... AE6: =Projections!AE9
A7: Total Portfolio | B7: =B4+B5+B6 | C7: =C4+C5+C6 | D7: =D4+D5+D6 | E7: =E4+E5+E6 | F7: =F4+F5+F6 | G7: =G4+G5+G6 | H7: =H4+H5+H6 | I7: =I4+I5+I6 | ... AE7: =AE4+AE5+AE6
A9: RISK TARGETS
A10: Low Risk Target | B10: =LowRiskTarget | C10: =LowRiskTarget | D10: =LowRiskTarget | E10: =LowRiskTarget | F10: =LowRiskTarget | G10: =LowRiskTarget | H10: =LowRiskTarget | I10: =LowRiskTarget | ... AE10: =LowRiskTarget
A11: Moderate Target | B11: =ModRiskTarget | C11: =ModRiskTarget | D11: =ModRiskTarget | E11: =ModRiskTarget | F11: =ModRiskTarget | G11: =ModRiskTarget | H11: =ModRiskTarget | I11: =ModRiskTarget | ... AE11: =ModRiskTarget
A12: High Risk Target (remainder) | B12: =MAX(0,B7-B10-B11) | C12: =MAX(0,C7-C10-C11) | D12: =MAX(0,D7-D10-D11) | E12: =MAX(0,E7-E10-E11) | F12: =MAX(0,F7-F10-F11) | G12: =MAX(0,G7-G10-G11) | H12: =MAX(0,H7-H10-H11) | I12: =MAX(0,I7-I10-I11) | ... AE12: =MAX(0,AE7-AE10-AE11)
A14: RECOMMENDED ALLOCATION
A15: After-Tax: Low Risk | B15: =MIN(B4,B10) | C15: =MIN(C4,C10) | D15: =MIN(D4,D10) | E15: =MIN(E4,E10) | F15: =MIN(F4,F10) | G15: =MIN(G4,G10) | H15: =MIN(H4,H10) | I15: =MIN(I4,I10) | ... AE15: =MIN(AE4,AE10)
A16: After-Tax: Moderate | B16: =MIN(B4-B15,MAX(0,B11-(B18))) | C16: =MIN(C4-C15,MAX(0,C11-(C18))) | D16: =MIN(D4-D15,MAX(0,D11-(D18))) | E16: =MIN(E4-E15,MAX(0,E11-(E18))) | F16: =MIN(F4-F15,MAX(0,F11-(F18))) | G16: =MIN(G4-G15,MAX(0,G11-(G18))) | H16: =MIN(H4-H15,MAX(0,H11-(H18))) | I16: =MIN(I4-I15,MAX(0,I11-(I18))) | ... AE16: =MIN(AE4-AE15,MAX(0,AE11-(AE18)))
A17: After-Tax: High Risk | B17: =MAX(0,B4-B15-B16) | C17: =MAX(0,C4-C15-C16) | D17: =MAX(0,D4-D15-D16) | E17: =MAX(0,E4-E15-E16) | F17: =MAX(0,F4-F15-F16) | G17: =MAX(0,G4-G15-G16) | H17: =MAX(0,H4-H15-H16) | I17: =MAX(0,I4-I15-I16) | ... AE17: =MAX(0,AE4-AE15-AE16)
A18: IRA: Low Risk | B18: =MIN(B5,MAX(0,B10-B15)) | C18: =MIN(C5,MAX(0,C10-C15)) | D18: =MIN(D5,MAX(0,D10-D15)) | E18: =MIN(E5,MAX(0,E10-E15)) | F18: =MIN(F5,MAX(0,F10-F15)) | G18: =MIN(G5,MAX(0,G10-G15)) | H18: =MIN(H5,MAX(0,H10-H15)) | I18: =MIN(I5,MAX(0,I10-I15)) | ... AE18: =MIN(AE5,MAX(0,AE10-AE15))
A19: IRA: Moderate | B19: =MIN(B5-B18,B11) | C19: =MIN(C5-C18,C11) | D19: =MIN(D5-D18,D11) | E19: =MIN(E5-E18,E11) | F19: =MIN(F5-F18,F11) | G19: =MIN(G5-G18,G11) | H19: =MIN(H5-H18,H11) | I19: =MIN(I5-I18,I11) | ... AE19: =MIN(AE5-AE18,AE11)
A20: IRA: High Risk | B20: =MAX(0,B5-B18-B19) | C20: =MAX(0,C5-C18-C19) | D20: =MAX(0,D5-D18-D19) | E20: =MAX(0,E5-E18-E19) | F20: =MAX(0,F5-F18-F19) | G20: =MAX(0,G5-G18-G19) | H20: =MAX(0,H5-H18-H19) | I20: =MAX(0,I5-I18-I19) | ... AE20: =MAX(0,AE5-AE18-AE19)
A21: Roth: Low Risk | B21: =MAX(0,B6-B22-B23) | C21: =MAX(0,C6-C22-C23) | D21: =MAX(0,D6-D22-D23) | E21: =MAX(0,E6-E22-E23) | F21: =MAX(0,F6-F22-F23) | G21: =MAX(0,G6-G22-G23) | H21: =MAX(0,H6-H22-H23) | I21: =MAX(0,I6-I22-I23) | ... AE21: =MAX(0,AE6-AE22-AE23)
A22: Roth: Moderate | B22: =MIN(B6-B23,MAX(0,B11-B19-B16)) | C22: =MIN(C6-C23,MAX(0,C11-C19-C16)) | D22: =MIN(D6-D23,MAX(0,D11-D19-D16)) | E22: =MIN(E6-E23,MAX(0,E11-E19-E16)) | F22: =MIN(F6-F23,MAX(0,F11-F19-F16)) | G22: =MIN(G6-G23,MAX(0,G11-G19-G16)) | H22: =MIN(H6-H23,MAX(0,H11-H19-H16)) | I22: =MIN(I6-I23,MAX(0,I11-I19-I16)) | ... AE22: =MIN(AE6-AE23,MAX(0,AE11-AE19-AE16))
A23: Roth: High Risk | B23: =MIN(B6,B12) | C23: =MIN(C6,C12) | D23: =MIN(D6,D12) | E23: =MIN(E6,E12) | F23: =MIN(F6,F12) | G23: =MIN(G6,G12) | H23: =MIN(H6,H12) | I23: =MIN(I6,I12) | ... AE23: =MIN(AE6,AE12)
A25: BLENDED RETURNS
A26: After-Tax Blended Return | B26: =IF(B4>0,(B15*LowRiskReturn+B16*ModRiskReturn+B17*HighRiskReturn)/B4,0) | C26: =IF(C4>0,(C15*LowRiskReturn+C16*ModRiskReturn+C17*HighRiskReturn)/C4,0) | D26: =IF(D4>0,(D15*LowRiskReturn+D16*ModRiskReturn+D17*HighRiskReturn)/D4,0) | E26: =IF(E4>0,(E15*LowRiskReturn+E16*ModRiskReturn+E17*HighRiskReturn)/E4,0) | F26: =IF(F4>0,(F15*LowRiskReturn+F16*ModRiskReturn+F17*HighRiskReturn)/F4,0) | G26: =IF(G4>0,(G15*LowRiskReturn+G16*ModRiskReturn+G17*HighRiskReturn)/G4,0) | H26: =IF(H4>0,(H15*LowRiskReturn+H16*ModRiskReturn+H17*HighRiskReturn)/H4,0) | I26: =IF(I4>0,(I15*LowRiskReturn+I16*ModRiskReturn+I17*HighRiskReturn)/I4,0) | ... AE26: =IF(AE4>0,(AE15*LowRiskReturn+AE16*ModRiskReturn+AE17*HighRiskReturn)/AE4,0)
A27: IRA Blended Return | B27: =IF(B5>0,(B18*LowRiskReturn+B19*ModRiskReturn+B20*HighRiskReturn)/B5,0) | C27: =IF(C5>0,(C18*LowRiskReturn+C19*ModRiskReturn+C20*HighRiskReturn)/C5,0) | D27: =IF(D5>0,(D18*LowRiskReturn+D19*ModRiskReturn+D20*HighRiskReturn)/D5,0) | E27: =IF(E5>0,(E18*LowRiskReturn+E19*ModRiskReturn+E20*HighRiskReturn)/E5,0) | F27: =IF(F5>0,(F18*LowRiskReturn+F19*ModRiskReturn+F20*HighRiskReturn)/F5,0) | G27: =IF(G5>0,(G18*LowRiskReturn+G19*ModRiskReturn+G20*HighRiskReturn)/G5,0) | H27: =IF(H5>0,(H18*LowRiskReturn+H19*ModRiskReturn+H20*HighRiskReturn)/H5,0) | I27: =IF(I5>0,(I18*LowRiskReturn+I19*ModRiskReturn+I20*HighRiskReturn)/I5,0) | ... AE27: =IF(AE5>0,(AE18*LowRiskReturn+AE19*ModRiskReturn+AE20*HighRiskReturn)/AE5,0)
A28: Roth Blended Return | B28: =IF(B6>0,(B21*LowRiskReturn+B22*ModRiskReturn+B23*HighRiskReturn)/B6,0) | C28: =IF(C6>0,(C21*LowRiskReturn+C22*ModRiskReturn+C23*HighRiskReturn)/C6,0) | D28: =IF(D6>0,(D21*LowRiskReturn+D22*ModRiskReturn+D23*HighRiskReturn)/D6,0) | E28: =IF(E6>0,(E21*LowRiskReturn+E22*ModRiskReturn+E23*HighRiskReturn)/E6,0) | F28: =IF(F6>0,(F21*LowRiskReturn+F22*ModRiskReturn+F23*HighRiskReturn)/F6,0) | G28: =IF(G6>0,(G21*LowRiskReturn+G22*ModRiskReturn+G23*HighRiskReturn)/G6,0) | H28: =IF(H6>0,(H21*LowRiskReturn+H22*ModRiskReturn+H23*HighRiskReturn)/H6,0) | I28: =IF(I6>0,(I21*LowRiskReturn+I22*ModRiskReturn+I23*HighRiskReturn)/I6,0) | ... AE28: =IF(AE6>0,(AE21*LowRiskReturn+AE22*ModRiskReturn+AE23*HighRiskReturn)/AE6,0)
A30: MODEL ASSUMPTIONS (for comparison)
A31: After-Tax Return (current) | B31: =ReturnAfterTax | C31: =ReturnAfterTax | D31: =ReturnAfterTax | E31: =ReturnAfterTax | F31: =ReturnAfterTax | G31: =ReturnAfterTax | H31: =ReturnAfterTax | I31: =ReturnAfterTax | ... AE31: =ReturnAfterTax
A32: IRA Return (current) | B32: =ReturnIRA | C32: =ReturnIRA | D32: =ReturnIRA | E32: =ReturnIRA | F32: =ReturnIRA | G32: =ReturnIRA | H32: =ReturnIRA | I32: =ReturnIRA | ... AE32: =ReturnIRA
A33: Roth Return (current) | B33: =ReturnRoth | C33: =ReturnRoth | D33: =ReturnRoth | E33: =ReturnRoth | F33: =ReturnRoth | G33: =ReturnRoth | H33: =ReturnRoth | I33: =ReturnRoth | ... AE33: =ReturnRoth
A35: VARIANCE
A36: After-Tax Δ | B36: =B26-B31 | C36: =C26-C31 | D36: =D26-D31 | E36: =E26-E31 | F36: =F26-F31 | G36: =G26-G31 | H36: =H26-H31 | I36: =I26-I31 | ... AE36: =AE26-AE31
A37: IRA Δ | B37: =B27-B32 | C37: =C27-C32 | D37: =D27-D32 | E37: =E27-E32 | F37: =F27-F32 | G37: =G27-G32 | H37: =H27-H32 | I37: =I27-I32 | ... AE37: =AE27-AE32
A38: Roth Δ | B38: =B28-B33 | C38: =C28-C33 | D38: =D28-D33 | E38: =E28-E33 | F38: =F28-F33 | G38: =G28-G33 | H38: =H28-H33 | I38: =I28-I33 | ... AE38: =AE28-AE33
A40: NOTE: This tab shows recommended asset allocation to maintain your risk ladder.
A41: The 'Blended Returns' show what each account should earn if properly allocated.
A42: The 'Variance' rows show the difference between recommended and current model assumptions.
A43: To use blended returns in projections, copy the blended return values to the Inputs tab.
